ALU/user/src/mux3to1_32bit.v
module mux3to1_32bit(choice1, choice2, choice3, out, sel);
	parameter n = 32;
	input[n-1:0] choice1;
	input[n-1:0] choice2;
	input[n-1:0] choice3;
	input[1:0] sel;
	output reg[n-1:0] out;

	always @(*) begin
		case(sel)
		2'b00: out = choice1;
		2'b01: out = choice2;
		2'b10: out = choice3;
		endcase
	end

endmodule

ALU/user/src/or32.v
module or32(operendA, operendB, out);
	parameter n = 32;
	input[n-1:0] operendA;
	input[n-1:0] operendB;
	output[n-1:0] out;
	
	assign out = operendA | operendB;
	
endmodule

ALU/user/src/mux2to1_32bit_01mux.v
module mux2to1_32bit_01mux(sel, out);
	input sel;
	output reg[31:0] out;
	
	always @(*)begin
		case(sel)
		0: out = 32'b0;
		1: out = 32'hffffffff;
		endcase
	end
endmodule

ALU/user/src/mux2to1_1bit.v
module mux2to1_1bit(choice1, choice2, out, sel);
	input choice1, choice2, sel;
	output reg out;
	
	always @(*)begin
		case(sel)
		0: out = choice1;
		1: out = choice2;
		endcase
	end
endmodule

ALU/user/src/adder32.v
module adder32(A, B, Cin, Add_Carry, Add_Overflow, Add_Sign, Add_Result, Zero);
	parameter n = 32;
	input [n-1:0] A;
	input [n-1:0] B;
	input Cin;
	output Add_Carry, Add_Overflow, Add_Sign, Zero;
	output[n-1:0] Add_Result;

	wire cout;

	assign {cout, Add_Result} = A + B + Cin;
	assign Add_Carry = ~(cout ^ Cin);
	assign Add_Overflow = cout ^ Add_Result[n-1] ^ A[n-1] ^ B[n-1];
	assign Add_Sign = Add_Result[n-1];
	/*
	if(Add_Result == 32'b0)
		assign Zero = 1;
	else
		assign Zero = 0;
	*/
	assign Zero = ~(| Add_Result);

endmodule

ALU/user/src/xor32.v
module xor32(operendA, operendB, out);
	parameter n = 32;
	input[n-1:0] operendA;
	input[n-1:0] operendB;
	output reg[n-1:0] out;
	
	always @(*) begin
		out = operendA ^ operendB;
	end

endmodule

ALU/user/src/extend32.v
module extend32(SUBctr, extend_out);
	input SUBctr;
	output reg[31:0] extend_out;
	always @(*) begin
	if(SUBctr == 1)
		extend_out = 32'hffffffff;
	else
		extend_out = 32'b0;
	end

endmodule

ALU/user/src/crtgenerator.v
module crtgenerator(ALUctr, SUBctr, OPctr, OVctr, SIGctr);
	parameter n = 3;
	input[n-1:0] ALUctr;
	output reg SUBctr, OVctr, SIGctr;
	output reg[1:0] OPctr; 
	
	always @(*) begin
		SUBctr = ALUctr[2];
		OVctr = !ALUctr[1] & ALUctr[0];
		SIGctr = ALUctr[0];
		OPctr[1] = ALUctr[2] & ALUctr[1];
		OPctr[0] = !ALUctr[2] & ALUctr[1] & !ALUctr[0];
	end

endmodule

ALU/user/src/ALU.v
`include "/Users/yr/code/computer-organization/computer-organization-labs/ALU/user/src/crtgenerator.v"
`include "/Users/yr/code/computer-organization/computer-organization-labs/ALU/user/src/adder32.v"
`include "/Users/yr/code/computer-organization/computer-organization-labs/ALU/user/src/extend32.v"
`include "/Users/yr/code/computer-organization/computer-organization-labs/ALU/user/src/mux2to1_1bit.v"
`include "/Users/yr/code/computer-organization/computer-organization-labs/ALU/user/src/mux2to1_32bit_01mux.v"
`include "/Users/yr/code/computer-organization/computer-organization-labs/ALU/user/src/mux3to1_32bit.v"
`include "/Users/yr/code/computer-organization/computer-organization-labs/ALU/user/src/or32.v"
`include "/Users/yr/code/computer-organization/computer-organization-labs/ALU/user/src/xor32.v"

module ALU(A, B, ALUctr, Zero, Overflow, Result);
	parameter n = 32;
	input [n-1:0] A;
	input [n-1:0] B;
	input [2:0] ALUctr;
	output [n-1:0] Result;
	//flags
	output Zero;
	output Overflow;
	// ctr signals
	wire SUBctr, OVctr, SIGctr;
	wire[1:0] OPctr;
	wire[n-1:0] SUBctr_ext;
	wire[n-1:0] B_to_add;
	wire Add_Carry, Add_Overflow, Add_Sign;
	wire[n-1:0]Add_Result;
	wire[n-1:0] mux3_op2;
	wire[n-1:0] mux3_op3;
	wire mux2_op1, mux2_op2;
	wire less;

	crtgenerator gen(.ALUctr(ALUctr), .SUBctr(SUBctr),
					 .OPctr(OPctr), .OVctr(OVctr), .SIGctr(SIGctr));

	extend32 extend(.SUBctr(SUBctr), .extend_out(SUBctr_ext));

	xor32 x(.operendA(B), .operendB(SUBctr_ext), .out(B_to_add));

	adder32 adder(.A(A), .B(B_to_add), .Cin(SUBctr),
			.Add_Carry(Add_Carry),
			.Add_Overflow(Add_Overflow),
			.Add_Sign(Add_Sign),
			.Add_Result(Add_Result), .Zero(Zero));

	and(Overflow, Add_Overflow, OVctr);

	xor(mux2_op1, SUBctr, Add_Carry);
	xor(mux2_op2, Add_Overflow, Add_Sign);

	mux2to1_1bit mux1(.choice1(mux2_op1), .choice2(mux2_op2),
					  .out(less), .sel(SIGctr));

	mux2to1_32bit_01mux mux2(.sel(less), .out(mux3_op3));

	or32 or_gate(.operendA(A), .operendB(B), .out(mux3_op2));

	mux3to1_32bit mux3(.choice1(Add_Result),
					   .choice2(mux3_op2),
					   .choice3(mux3_op3),
					   .out(Result), .sel(OPctr));
endmodule

ALU/user/sim/testbench.v
`timescale 1ns/1ps
`include "/Users/yr/code/computer-organization/computer-organization-labs/ALU/user/src/ALU.v"

module testbench;
parameter n = 32;
reg [n-1:0] A;
reg [n-1:0] B;
reg [2:0] ALUctr;
//Instance
// outports wire

wire [n-1:0] 	Result;
wire         	Zero;
wire         	Overflow;
ALU u_ALU(
	.A        	( A         ),
	.B        	( B         ),
	.ALUctr   	( ALUctr    ),
	.Result   	( Result    ),
	.Zero     	( Zero      ),
	.Overflow 	( Overflow  )
);

initial begin
    $dumpfile("wave.vcd");
    $dumpvars(0, testbench);

    // 无符号加法，不判溢出
    ALUctr = 3'b000;
    A = 32'd16;
    B = 32'd18;
    #10000
    A = 32'hfffffff1;
    B = 32'he;
    #10000
    B = B + 1;
    #10000

    // 带符号加法, 判溢出
    ALUctr = 3'b001;
    A = 32'h7ffffff1;
    B = 32'd5;
    #10000
    B = 32'hf; // 上溢
    #10000
    A = -32'd16;
    B = -32'd8;
    #10000
    // 下溢
    A = 32'h80000001;
    B = 32'h80000001;
    #10000

    // 或运算
    // 0001 | 1000 = 1001
    ALUctr = 3'b010;
    A = 32'h11111111;
    B = 32'h88888888;
    #10000

    // 无符号减法 不判溢出
    ALUctr = 3'b100;
    A = 32'd16;
    B = 32'd10;
    #10000
    B = 32'd16;
    #10000
    B = 32'd17;
    #10000

    // 带符号减法 判断溢出
    ALUctr = 3'b101;
    A = 32'd16;
    B = 32'd8;
    #10000
    B = 32'd16;
    #10000
    B = 32'd17;
    #10000
    A = 32'h7fffffff; // 上溢
    B = -32'd1;
    #10000
    A = 32'h80000001; // 下溢
    B = 32'd2;
    #10000

    // 无符号数 小于比较 小于置1
    ALUctr = 3'b110;
    A = 32'd16;
    B = 32'd8;
    #10000 B = 32'd16;
    #10000 B = 32'd17;
    #10000 B = -32'd1;
    #10000

    // 带符号数 小于比较 小于置1
    ALUctr = 3'b111;
    A = 32'd16;
    B = 32'd8;
    #10000 B = 32'd16;
    #10000 B = 32'd17;
    #10000 B = -32'd1;
    #10000 $finish;

end

endmodule  //TOP

ALU/user/sim/wave.vcd
$date
	Tue Nov 21 10:22:48 2023
$end
$version
	Icarus Verilog
$end
$timescale
	1ps
$end
$scope module testbench $end
$var wire 1 ! Zero $end
$var wire 32 " Result [31:0] $end
$var wire 1 # Overflow $end
$var parameter 32 $ n $end
$var reg 32 % A [31:0] $end
$var reg 3 & ALUctr [2:0] $end
$var reg 32 ' B [31:0] $end
$scope module u_ALU $end
$var wire 32 ( A [31:0] $end
$var wire 3 ) ALUctr [2:0] $end
$var wire 32 * B [31:0] $end
$var wire 1 # Overflow $end
$var wire 1 + mux2_op1 $end
$var wire 1 , mux2_op2 $end
$var wire 32 - mux3_op3 [31:0] $end
$var wire 32 . mux3_op2 [31:0] $end
$var wire 1 / less $end
$var wire 1 ! Zero $end
$var wire 32 0 SUBctr_ext [31:0] $end
$var wire 1 1 SUBctr $end
$var wire 1 2 SIGctr $end
$var wire 32 3 Result [31:0] $end
$var wire 1 4 OVctr $end
$var wire 2 5 OPctr [1:0] $end
$var wire 32 6 B_to_add [31:0] $end
$var wire 1 7 Add_Sign $end
$var wire 32 8 Add_Result [31:0] $end
$var wire 1 9 Add_Overflow $end
$var wire 1 : Add_Carry $end
$var parameter 32 ; n $end
$scope module adder $end
$var wire 32 < A [31:0] $end
$var wire 1 : Add_Carry $end
$var wire 1 9 Add_Overflow $end
$var wire 1 ! Zero $end
$var wire 1 = cout $end
$var wire 1 1 Cin $end
$var wire 32 > B [31:0] $end
$var wire 1 7 Add_Sign $end
$var wire 32 ? Add_Result [31:0] $end
$var parameter 32 @ n $end
$upscope $end
$scope module extend $end
$var wire 1 1 SUBctr $end
$var reg 32 A extend_out [31:0] $end
$upscope $end
$scope module gen $end
$var wire 3 B ALUctr [2:0] $end
$var parameter 32 C n $end
$var reg 2 D OPctr [1:0] $end
$var reg 1 4 OVctr $end
$var reg 1 2 SIGctr $end
$var reg 1 1 SUBctr $end
$upscope $end
$scope module mux1 $end
$var wire 1 + choice1 $end
$var wire 1 , choice2 $end
$var wire 1 2 sel $end
$var reg 1 / out $end
$upscope $end
$scope module mux2 $end
$var wire 1 / sel $end
$var reg 32 E out [31:0] $end
$upscope $end
$scope module mux3 $end
$var wire 32 F choice1 [31:0] $end
$var wire 32 G choice3 [31:0] $end
$var wire 2 H sel [1:0] $end
$var wire 32 I choice2 [31:0] $end
$var parameter 32 J n $end
$var reg 32 K out [31:0] $end
$upscope $end
$scope module or_gate $end
$var wire 32 L operendA [31:0] $end
$var wire 32 M operendB [31:0] $end
$var wire 32 N out [31:0] $end
$var parameter 32 O n $end
$upscope $end
$scope module x $end
$var wire 32 P operendA [31:0] $end
$var wire 32 Q operendB [31:0] $end
$var parameter 32 R n $end
$var reg 32 S out [31:0] $end
$upscope $end
$upscope $end
$upscope $end
$enddefinitions $end
$comment Show the parameter values. $end
$dumpall
b100000 R
b100000 O
b100000 J
b11 C
b100000 @
b100000 ;
b100000 $
$end
#0
$dumpvars
b10010 S
b0 Q
b10010 P
b10010 N
b10010 M
b10000 L
b100010 K
b10010 I
b0 H
b11111111111111111111111111111111 G
b100010 F
b11111111111111111111111111111111 E
b0 D
b0 B
b0 A
b100010 ?
b10010 >
0=
b10000 <
1:
09
b100010 8
07
b10010 6
b0 5
04
b100010 3
02
01
b0 0
1/
b10010 .
b11111111111111111111111111111111 -
0,
1+
b10010 *
b0 )
b10000 (
b10010 '
b0 &
b10000 %
0#
b100010 "
0!
$end
#10000000
b11111111111111111111111111111111 -
b11111111111111111111111111111111 E
b11111111111111111111111111111111 G
1,
1/
1+
17
1:
09
b11111111111111111111111111111111 "
b11111111111111111111111111111111 3
b11111111111111111111111111111111 K
b1110 6
b1110 >
b1110 S
b11111111111111111111111111111111 8
b11111111111111111111111111111111 ?
b11111111111111111111111111111111 F
0=
b11111111111111111111111111111111 .
b11111111111111111111111111111111 I
b11111111111111111111111111111111 N
b1110 '
b1110 *
b1110 M
b1110 P
b11111111111111111111111111110001 %
b11111111111111111111111111110001 (
b11111111111111111111111111110001 <
b11111111111111111111111111110001 L
#20000000
b0 -
b0 E
b0 G
0/
09
0+
0,
0:
07
1!
b0 "
b0 3
b0 K
b0 8
b0 ?
b0 F
1=
b1111 6
b1111 >
b1111 S
b1111 '
b1111 *
b1111 M
b1111 P
#30000000
b0 -
b0 E
b0 G
0/
0,
1+
0#
1:
09
07
0!
b1111111111111111111111111110110 "
b1111111111111111111111111110110 3
b1111111111111111111111111110110 K
b101 6
b101 >
b101 S
b1111111111111111111111111110110 8
b1111111111111111111111111110110 ?
b1111111111111111111111111110110 F
0=
b1111111111111111111111111110101 .
b1111111111111111111111111110101 I
b1111111111111111111111111110101 N
12
14
b101 '
b101 *
b101 M
b101 P
b1111111111111111111111111110001 %
b1111111111111111111111111110001 (
b1111111111111111111111111110001 <
b1111111111111111111111111110001 L
b1 &
b1 )
b1 B
#40000000
1#
19
b0 -
b0 E
b0 G
0/
0,
17
b10000000000000000000000000000000 "
b10000000000000000000000000000000 3
b10000000000000000000000000000000 K
b10000000000000000000000000000000 8
b10000000000000000000000000000000 ?
b10000000000000000000000000000000 F
b1111111111111111111111111111111 .
b1111111111111111111111111111111 I
b1111111111111111111111111111111 N
b1111 6
b1111 >
b1111 S
b1111 '
b1111 *
b1111 M
b1111 P
#50000000
b11111111111111111111111111111111 -
b11111111111111111111111111111111 E
b11111111111111111111111111111111 G
1/
1,
0#
09
0+
0:
1=
b11111111111111111111111111101000 "
b11111111111111111111111111101000 3
b11111111111111111111111111101000 K
b11111111111111111111111111111000 6
b11111111111111111111111111111000 >
b11111111111111111111111111111000 S
b11111111111111111111111111101000 8
b11111111111111111111111111101000 ?
b11111111111111111111111111101000 F
b11111111111111111111111111111000 .
b11111111111111111111111111111000 I
b11111111111111111111111111111000 N
b11111111111111111111111111111000 '
b11111111111111111111111111111000 *
b11111111111111111111111111111000 M
b11111111111111111111111111111000 P
b11111111111111111111111111110000 %
b11111111111111111111111111110000 (
b11111111111111111111111111110000 <
b11111111111111111111111111110000 L
#60000000
1#
19
b11111111111111111111111111111111 -
b11111111111111111111111111111111 E
b11111111111111111111111111111111 G
1/
1,
07
b10 "
b10 3
b10 K
b10000000000000000000000000000001 6
b10000000000000000000000000000001 >
b10000000000000000000000000000001 S
b10 8
b10 ?
b10 F
b10000000000000000000000000000001 .
b10000000000000000000000000000001 I
b10000000000000000000000000000001 N
b10000000000000000000000000000001 '
b10000000000000000000000000000001 *
b10000000000000000000000000000001 M
b10000000000000000000000000000001 P
b10000000000000000000000000000001 %
b10000000000000000000000000000001 (
b10000000000000000000000000000001 <
b10000000000000000000000000000001 L
#70000000
1,
1+
1:
09
b11111111111111111111111111111111 -
b11111111111111111111111111111111 E
b11111111111111111111111111111111 G
17
b10011001100110011001100110011001 "
b10011001100110011001100110011001 3
b10011001100110011001100110011001 K
1/
0#
b10001000100010001000100010001000 6
b10001000100010001000100010001000 >
b10001000100010001000100010001000 S
b10011001100110011001100110011001 8
b10011001100110011001100110011001 ?
b10011001100110011001100110011001 F
0=
b10011001100110011001100110011001 .
b10011001100110011001100110011001 I
b10011001100110011001100110011001 N
b1 5
b1 D
b1 H
02
04
b10001000100010001000100010001000 '
b10001000100010001000100010001000 *
b10001000100010001000100010001000 M
b10001000100010001000100010001000 P
b10001000100010001000100010001 %
b10001000100010001000100010001 (
b10001000100010001000100010001 <
b10001000100010001000100010001 L
b10 &
b10 )
b10 B
#80000000
0,
b0 -
b0 E
b0 G
1=
09
07
1:
0/
b110 "
b110 3
b110 K
0+
b11111111111111111111111111111111 0
b11111111111111111111111111111111 A
b11111111111111111111111111111111 Q
b11111111111111111111111111110101 6
b11111111111111111111111111110101 >
b11111111111111111111111111110101 S
b110 8
b110 ?
b110 F
b11010 .
b11010 I
b11010 N
b0 5
b0 D
b0 H
11
b1010 '
b1010 *
b1010 M
b1010 P
b10000 %
b10000 (
b10000 <
b10000 L
b100 &
b100 )
b100 B
#90000000
1!
b0 "
b0 3
b0 K
b0 8
b0 ?
b0 F
b10000 .
b10000 I
b10000 N
b11111111111111111111111111101111 6
b11111111111111111111111111101111 >
b11111111111111111111111111101111 S
b10000 '
b10000 *
b10000 M
b10000 P
#100000000
b11111111111111111111111111111111 -
b11111111111111111111111111111111 E
b11111111111111111111111111111111 G
1/
09
1+
1,
0:
17
0!
b11111111111111111111111111111111 "
b11111111111111111111111111111111 3
b11111111111111111111111111111111 K
b11111111111111111111111111111111 8
b11111111111111111111111111111111 ?
b11111111111111111111111111111111 F
0=
b10001 .
b10001 I
b10001 N
b11111111111111111111111111101110 6
b11111111111111111111111111101110 >
b11111111111111111111111111101110 S
b10001 '
b10001 *
b10001 M
b10001 P
#110000000
b0 -
b0 E
b0 G
0#
0/
09
0+
0,
1:
07
b1000 "
b1000 3
b1000 K
b1000 8
b1000 ?
b1000 F
1=
b11000 .
b11000 I
b11000 N
b11111111111111111111111111110111 6
b11111111111111111111111111110111 >
b11111111111111111111111111110111 S
12
14
b1000 '
b1000 *
b1000 M
b1000 P
b101 &
b101 )
b101 B
#120000000
1!
b0 "
b0 3
b0 K
b0 8
b0 ?
b0 F
b10000 .
b10000 I
b10000 N
b11111111111111111111111111101111 6
b11111111111111111111111111101111 >
b11111111111111111111111111101111 S
b10000 '
b10000 *
b10000 M
b10000 P
#130000000
b11111111111111111111111111111111 -
b11111111111111111111111111111111 E
b11111111111111111111111111111111 G
0#
1/
09
1+
1,
0:
17
0!
b11111111111111111111111111111111 "
b11111111111111111111111111111111 3
b11111111111111111111111111111111 K
b11111111111111111111111111111111 8
b11111111111111111111111111111111 ?
b11111111111111111111111111111111 F
0=
b10001 .
b10001 I
b10001 N
b11111111111111111111111111101110 6
b11111111111111111111111111101110 >
b11111111111111111111111111101110 S
b10001 '
b10001 *
b10001 M
b10001 P
#140000000
1#
19
b0 -
b0 E
b0 G
0/
1+
0,
0:
17
b10000000000000000000000000000000 "
b10000000000000000000000000000000 3
b10000000000000000000000000000000 K
b0 6
b0 >
b0 S
b10000000000000000000000000000000 8
b10000000000000000000000000000000 ?
b10000000000000000000000000000000 F
0=
b11111111111111111111111111111111 .
b11111111111111111111111111111111 I
b11111111111111111111111111111111 N
b11111111111111111111111111111111 '
b11111111111111111111111111111111 *
b11111111111111111111111111111111 M
b11111111111111111111111111111111 P
b1111111111111111111111111111111 %
b1111111111111111111111111111111 (
b1111111111111111111111111111111 <
b1111111111111111111111111111111 L
#150000000
b11111111111111111111111111111111 -
b11111111111111111111111111111111 E
b11111111111111111111111111111111 G
1#
1/
19
0+
1,
1:
07
1=
b1111111111111111111111111111111 "
b1111111111111111111111111111111 3
b1111111111111111111111111111111 K
b11111111111111111111111111111101 6
b11111111111111111111111111111101 >
b11111111111111111111111111111101 S
b1111111111111111111111111111111 8
b1111111111111111111111111111111 ?
b1111111111111111111111111111111 F
b10000000000000000000000000000011 .
b10000000000000000000000000000011 I
b10000000000000000000000000000011 N
b10 '
b10 *
b10 M
b10 P
b10000000000000000000000000000001 %
b10000000000000000000000000000001 (
b10000000000000000000000000000001 <
b10000000000000000000000000000001 L
#160000000
0,
09
b0 -
b0 E
b0 G
b0 "
b0 3
b0 K
0/
0#
b11111111111111111111111111110111 6
b11111111111111111111111111110111 >
b11111111111111111111111111110111 S
b1000 8
b1000 ?
b1000 F
b11000 .
b11000 I
b11000 N
b10 5
b10 D
b10 H
02
04
b1000 '
b1000 *
b1000 M
b1000 P
b10000 %
b10000 (
b10000 <
b10000 L
b110 &
b110 )
b110 B
#170000000
1!
b0 8
b0 ?
b0 F
b10000 .
b10000 I
b10000 N
b11111111111111111111111111101111 6
b11111111111111111111111111101111 >
b11111111111111111111111111101111 S
b10000 '
b10000 *
b10000 M
b10000 P
#180000000
b11111111111111111111111111111111 "
b11111111111111111111111111111111 3
b11111111111111111111111111111111 K
b11111111111111111111111111111111 -
b11111111111111111111111111111111 E
b11111111111111111111111111111111 G
1/
09
1+
1,
0:
17
0!
b11111111111111111111111111111111 8
b11111111111111111111111111111111 ?
b11111111111111111111111111111111 F
0=
b10001 .
b10001 I
b10001 N
b11111111111111111111111111101110 6
b11111111111111111111111111101110 >
b11111111111111111111111111101110 S
b10001 '
b10001 *
b10001 M
b10001 P
#190000000
0,
09
07
b10001 8
b10001 ?
b10001 F
b11111111111111111111111111111111 .
b11111111111111111111111111111111 I
b11111111111111111111111111111111 N
b0 6
b0 >
b0 S
b11111111111111111111111111111111 '
b11111111111111111111111111111111 *
b11111111111111111111111111111111 M
b11111111111111111111111111111111 P
#200000000
0+
0,
1:
b0 "
b0 3
b0 K
09
b0 -
b0 E
b0 G
b1000 8
b1000 ?
b1000 F
1=
0/
b11000 .
b11000 I
b11000 N
b11111111111111111111111111110111 6
b11111111111111111111111111110111 >
b11111111111111111111111111110111 S
12
b1000 '
b1000 *
b1000 M
b1000 P
b111 &
b111 )
b111 B
#210000000
1!
b0 8
b0 ?
b0 F
b10000 .
b10000 I
b10000 N
b11111111111111111111111111101111 6
b11111111111111111111111111101111 >
b11111111111111111111111111101111 S
b10000 '
b10000 *
b10000 M
b10000 P
#220000000
b11111111111111111111111111111111 "
b11111111111111111111111111111111 3
b11111111111111111111111111111111 K
b11111111111111111111111111111111 -
b11111111111111111111111111111111 E
b11111111111111111111111111111111 G
1/
09
1+
1,
0:
17
0!
b11111111111111111111111111111111 8
b11111111111111111111111111111111 ?
b11111111111111111111111111111111 F
0=
b10001 .
b10001 I
b10001 N
b11111111111111111111111111101110 6
b11111111111111111111111111101110 >
b11111111111111111111111111101110 S
b10001 '
b10001 *
b10001 M
b10001 P
#230000000
b0 "
b0 3
b0 K
b0 -
b0 E
b0 G
0/
0,
09
07
b10001 8
b10001 ?
b10001 F
b11111111111111111111111111111111 .
b11111111111111111111111111111111 I
b11111111111111111111111111111111 N
b0 6
b0 >
b0 S
b11111111111111111111111111111111 '
b11111111111111111111111111111111 *
b11111111111111111111111111111111 M
b11111111111111111111111111111111 P
