control/user/src/aluCtr.v
module aluCtr(
    input [5:0] func,
    output reg[2:0] ALUctr
);

always @(*) begin
    case(func)
        6'b100000: ALUctr = 3'b001; // add
        6'b100010: ALUctr = 3'b101; // sub
        6'b100100: ALUctr = 3'b100; // subu
        6'b100101: ALUctr = 3'b111; // slt
        6'b101010: ALUctr = 3'b110; // sltu
    endcase
end
endmodule

control/user/src/mainCtr.v
module mainCtr(
    input Rtype,
    input ori,
    input addiu,
    input lw,
    input sw,
    input beq,
    input jump,
    output RegWr,
    output ALUSrc,
    output RegDst,
    output MemtoReg,
    output MemWr,
    output branch,
    output Jump,
    output ExtOp,
    output [2:0] ALUOp,
    output rtype
);
    assign rtype = Rtype;
    assign RegWr = Rtype | ori | addiu | lw;
    assign ALUSrc = ori | addiu | lw | sw;
    assign RegDst = Rtype;
    assign MemtoReg = lw;
    assign MemWr = sw;
    assign branch = beq;
    assign Jump = jump;
    assign ExtOp = addiu | lw | sw;
    assign ALUOp[2] = beq;
    assign ALUOp[1] = ori;
    assign ALUOp[0] = Rtype;

endmodule

control/user/src/insDecoder.v
module insDecoder(
    input[5:0] op,
    output Rtype,
    output ori,
    output addiu,
    output lw,
    output sw,
    output beq,
    output jump
);

    assign Rtype = (op == 6'b000000);
    assign ori = (op == 6'b001101);
    assign addiu = (op == 6'b001001);
    assign lw = (op == 6'b100011);
    assign sw = (op == 6'b101011);
    assign beq = (op == 6'b000100);
    assign jump = (op == 6'b000010);


endmodule

control/user/src/cpuCtr.v
`include "/Users/yr/code/computer-organization/computer-organization-labs/control/user/src/aluCtr.v"
`include "/Users/yr/code/computer-organization/computer-organization-labs/control/user/src/insDecoder.v"
`include "/Users/yr/code/computer-organization/computer-organization-labs/control/user/src/mainCtr.v"


module cpuCtr(
    input [5:0] op,
    input [5:0] func,
    output RegWr,
    output ALUSrc,
    output RegDst,
    output MemtoReg,
    output MemWr,
    output branch,
    output Jump,
    output ExtOp,
    output [2:0] ALUctr,
    output rtype
);

    // outports wire
    wire       	Rtype;
    wire       	ori;
    wire       	addiu;
    wire       	lw;
    wire       	sw;
    wire       	beq;
    wire       	jump;

    insDecoder u_insDecoder(
        .op    	( op     ),
        .Rtype 	( Rtype  ),
        .ori   	( ori    ),
        .addiu 	( addiu  ),
        .lw    	( lw     ),
        .sw    	( sw     ),
        .beq   	( beq    ),
        .jump  	( jump   )
    );

    wire[2:0] ALUOp0;

    mainCtr u_mainCtr(
        .Rtype      ( Rtype      ),
        .ori        ( ori        ),
        .addiu      ( addiu      ),
        .lw         ( lw         ),
        .sw         ( sw         ),
        .beq        ( beq        ),
        .jump       ( jump       ),
        .RegWr      ( RegWr      ),
        .ALUSrc     ( ALUSrc     ),
        .RegDst     ( RegDst     ),
        .MemtoReg   ( MemtoReg   ),
        .MemWr      ( MemWr      ),
        .branch     ( branch     ),
        .Jump       ( Jump       ),
        .ExtOp      ( ExtOp      ),
        .ALUOp      ( ALUOp0     ),
        .rtype      ( rtype      )
    );

    wire[2:0] ALUOp1;
    aluCtr u_aluCtr(
        .func       ( func       ),
        .ALUctr     ( ALUOp1     )
    );

    assign ALUctr = Rtype ? ALUOp1 : ALUOp0;

endmodule

control/user/sim/testbench.v
`timescale 1ns / 1ps
`include "/Users/yr/code/computer-organization/computer-organization-labs/control/user/src/cpuCtr.v"
module testbench();

parameter DATA_WIDTH = 32;
parameter ADDR_WIDTH = 32;
parameter MAIN_FRE   = 100; //unit MHz
reg                   sys_clk = 0;
reg                   sys_rst = 1;
reg [DATA_WIDTH-1:0]  data = 0;
reg [ADDR_WIDTH-1:0]  addr = 0;

always begin
    #(500/MAIN_FRE) sys_clk = ~sys_clk;
end

always begin
    #50 sys_rst = 0;
end

always @(posedge sys_clk) begin
    if (sys_rst)
        addr = 0;
    else
        addr = addr + 1;
end
always @(posedge sys_clk) begin
    if (sys_rst)
        data = 0;
    else
        data = data + 1;
end

//Instance
// outports wire
wire       	RegWr;
wire       	ALUSrc;
wire       	RegDst;
wire       	MemtoReg;
wire       	MemWr;
wire       	branch;
wire       	Jump;
wire       	ExtOp;
wire [2:0] 	ALUctr;
wire       	rtype;

// input
reg[5:0] op;
reg[5:0] func;

cpuCtr u_cpuCtr(
	.op       	( op        ),
	.func     	( func      ),
	.RegWr    	( RegWr     ),
	.ALUSrc   	( ALUSrc    ),
	.RegDst   	( RegDst    ),
	.MemtoReg 	( MemtoReg  ),
	.MemWr    	( MemWr     ),
	.branch   	( branch    ),
	.Jump     	( Jump      ),
	.ExtOp    	( ExtOp     ),
	.ALUctr   	( ALUctr    ),
	.rtype    	( rtype     )
);



initial begin
    $dumpfile("wave.vcd");
    $dumpvars(0, testbench);

    #1000 op = 6'b000000; func = 6'b100000; // add
    #1000 op = 6'b000000; func = 6'b100010; // sub
    #1000 op = 6'b000000; func = 6'b100100; // and
    #1000 op = 6'b000000; func = 6'b100101; // or
    #1000 op = 6'b000000; func = 6'b101010; // slt
    #1000 op = 6'b001101; func = 6'b000000; // ori
    #1000 op = 6'b001001; func = 6'b000000; // addiu
    #1000 op = 6'b100011; func = 6'b000000; // lw
    #1000 op = 6'b101011; func = 6'b000000; // sw
    #1000 op = 6'b000100; func = 6'b000000; // beq
    #1000 op = 6'b000010; func = 6'b000000; // jump

    #50000 $finish;
end

endmodule  //TOP

control/user/sim/wave.vcd
$date
	Tue Dec 19 14:43:52 2023
$end
$version
	Icarus Verilog
$end
$timescale
	1ps
$end
$scope module testbench $end
$var wire 1 ! rtype $end
$var wire 1 " branch $end
$var wire 1 # RegWr $end
$var wire 1 $ RegDst $end
$var wire 1 % MemtoReg $end
$var wire 1 & MemWr $end
$var wire 1 ' Jump $end
$var wire 1 ( ExtOp $end
$var wire 3 ) ALUctr [2:0] $end
$var wire 1 * ALUSrc $end
$var parameter 32 + ADDR_WIDTH $end
$var parameter 32 , DATA_WIDTH $end
$var parameter 32 - MAIN_FRE $end
$var reg 32 . addr [31:0] $end
$var reg 32 / data [31:0] $end
$var reg 6 0 func [5:0] $end
$var reg 6 1 op [5:0] $end
$var reg 1 2 sys_clk $end
$var reg 1 3 sys_rst $end
$scope module u_cpuCtr $end
$var wire 6 4 func [5:0] $end
$var wire 6 5 op [5:0] $end
$var wire 1 6 sw $end
$var wire 1 ! rtype $end
$var wire 1 7 ori $end
$var wire 1 8 lw $end
$var wire 1 9 jump $end
$var wire 1 " branch $end
$var wire 1 : beq $end
$var wire 1 ; addiu $end
$var wire 1 < Rtype $end
$var wire 1 # RegWr $end
$var wire 1 $ RegDst $end
$var wire 1 % MemtoReg $end
$var wire 1 & MemWr $end
$var wire 1 ' Jump $end
$var wire 1 ( ExtOp $end
$var wire 3 = ALUctr [2:0] $end
$var wire 1 * ALUSrc $end
$var wire 3 > ALUOp1 [2:0] $end
$var wire 3 ? ALUOp0 [2:0] $end
$scope module u_aluCtr $end
$var wire 6 @ func [5:0] $end
$var reg 3 A ALUctr [2:0] $end
$upscope $end
$scope module u_insDecoder $end
$var wire 6 B op [5:0] $end
$var wire 1 6 sw $end
$var wire 1 7 ori $end
$var wire 1 8 lw $end
$var wire 1 9 jump $end
$var wire 1 : beq $end
$var wire 1 ; addiu $end
$var wire 1 < Rtype $end
$upscope $end
$scope module u_mainCtr $end
$var wire 1 * ALUSrc $end
$var wire 1 ( ExtOp $end
$var wire 1 ' Jump $end
$var wire 1 & MemWr $end
$var wire 1 % MemtoReg $end
$var wire 1 $ RegDst $end
$var wire 1 # RegWr $end
$var wire 1 < Rtype $end
$var wire 1 ; addiu $end
$var wire 1 : beq $end
$var wire 1 " branch $end
$var wire 1 9 jump $end
$var wire 1 8 lw $end
$var wire 1 7 ori $end
$var wire 1 ! rtype $end
$var wire 1 6 sw $end
$var wire 3 C ALUOp [2:0] $end
$upscope $end
$upscope $end
$upscope $end
$enddefinitions $end
$comment Show the parameter values. $end
$dumpall
b1100100 -
b100000 ,
b100000 +
$end
#0
$dumpvars
bx C
bx B
bx A
bx @
bx ?
bx >
bx =
x<
x;
x:
x9
x8
x7
x6
bx 5
bx 4
13
02
bx 1
bx 0
b0 /
b0 .
x*
bx )
x(
x'
x&
x%
x$
x#
x"
x!
$end
#5000
12
#10000
02
#15000
12
#20000
02
#25000
12
#30000
02
#35000
12
#40000
02
#45000
12
#50000
02
03
#55000
b1 /
b1 .
12
#60000
02
#65000
b10 .
b10 /
12
#70000
02
#75000
b11 /
b11 .
12
#80000
02
#85000
b100 .
b100 /
12
#90000
02
#95000
b101 /
b101 .
12
#100000
02
#105000
b110 .
b110 /
12
#110000
02
#115000
b111 /
b111 .
12
#120000
02
#125000
b1000 .
b1000 /
12
#130000
02
#135000
b1001 /
b1001 .
12
#140000
02
#145000
b1010 .
b1010 /
12
#150000
02
#155000
b1011 /
b1011 .
12
#160000
02
#165000
b1100 .
b1100 /
12
#170000
02
#175000
b1101 /
b1101 .
12
#180000
02
#185000
b1110 .
b1110 /
12
#190000
02
#195000
b1111 /
b1111 .
12
#200000
02
#205000
b10000 .
b10000 /
12
#210000
02
#215000
b10001 /
b10001 .
12
#220000
02
#225000
b10010 .
b10010 /
12
#230000
02
#235000
b10011 /
b10011 .
12
#240000
02
#245000
b10100 .
b10100 /
12
#250000
02
#255000
b10101 /
b10101 .
12
#260000
02
#265000
b10110 .
b10110 /
12
#270000
02
#275000
b10111 /
b10111 .
12
#280000
02
#285000
b11000 .
b11000 /
12
#290000
02
#295000
b11001 /
b11001 .
12
#300000
02
#305000
b11010 .
b11010 /
12
#310000
02
#315000
b11011 /
b11011 .
12
#320000
02
#325000
b11100 .
b11100 /
12
#330000
02
#335000
b11101 /
b11101 .
12
#340000
02
#345000
b11110 .
b11110 /
12
#350000
02
#355000
b11111 /
b11111 .
12
#360000
02
#365000
b100000 .
b100000 /
12
#370000
02
#375000
b100001 /
b100001 .
12
#380000
02
#385000
b100010 .
b100010 /
12
#390000
02
#395000
b100011 /
b100011 .
12
#400000
02
#405000
b100100 .
b100100 /
12
#410000
02
#415000
b100101 /
b100101 .
12
#420000
02
#425000
b100110 .
b100110 /
12
#430000
02
#435000
b100111 /
b100111 .
12
#440000
02
#445000
b101000 .
b101000 /
12
#450000
02
#455000
b101001 /
b101001 .
12
#460000
02
#465000
b101010 .
b101010 /
12
#470000
02
#475000
b101011 /
b101011 .
12
#480000
02
#485000
b101100 .
b101100 /
12
#490000
02
#495000
b101101 /
b101101 .
12
#500000
02
#505000
b101110 .
b101110 /
12
#510000
02
#515000
b101111 /
b101111 .
12
#520000
02
#525000
b110000 .
b110000 /
12
#530000
02
#535000
b110001 /
b110001 .
12
#540000
02
#545000
b110010 .
b110010 /
12
#550000
02
#555000
b110011 /
b110011 .
12
#560000
02
#565000
b110100 .
b110100 /
12
#570000
02
#575000
b110101 /
b110101 .
12
#580000
02
#585000
b110110 .
b110110 /
12
#590000
02
#595000
b110111 /
b110111 .
12
#600000
02
#605000
b111000 .
b111000 /
12
#610000
02
#615000
b111001 /
b111001 .
12
#620000
02
#625000
b111010 .
b111010 /
12
#630000
02
#635000
b111011 /
b111011 .
12
#640000
02
#645000
b111100 .
b111100 /
12
#650000
02
#655000
b111101 /
b111101 .
12
#660000
02
#665000
b111110 .
b111110 /
12
#670000
02
#675000
b111111 /
b111111 .
12
#680000
02
#685000
b1000000 .
b1000000 /
12
#690000
02
#695000
b1000001 /
b1000001 .
12
#700000
02
#705000
b1000010 .
b1000010 /
12
#710000
02
#715000
b1000011 /
b1000011 .
12
#720000
02
#725000
b1000100 .
b1000100 /
12
#730000
02
#735000
b1000101 /
b1000101 .
12
#740000
02
#745000
b1000110 .
b1000110 /
12
#750000
02
#755000
b1000111 /
b1000111 .
12
#760000
02
#765000
b1001000 .
b1001000 /
12
#770000
02
#775000
b1001001 /
b1001001 .
12
#780000
02
#785000
b1001010 .
b1001010 /
12
#790000
02
#795000
b1001011 /
b1001011 .
12
#800000
02
#805000
b1001100 .
b1001100 /
12
#810000
02
#815000
b1001101 /
b1001101 .
12
#820000
02
#825000
b1001110 .
b1001110 /
12
#830000
02
#835000
b1001111 /
b1001111 .
12
#840000
02
#845000
b1010000 .
b1010000 /
12
#850000
02
#855000
b1010001 /
b1010001 .
12
#860000
02
#865000
b1010010 .
b1010010 /
12
#870000
02
#875000
b1010011 /
b1010011 .
12
#880000
02
#885000
b1010100 .
b1010100 /
12
#890000
02
#895000
b1010101 /
b1010101 .
12
#900000
02
#905000
b1010110 .
b1010110 /
12
#910000
02
#915000
b1010111 /
b1010111 .
12
#920000
02
#925000
b1011000 .
b1011000 /
12
#930000
02
#935000
b1011001 /
b1011001 .
12
#940000
02
#945000
b1011010 .
b1011010 /
12
#950000
02
#955000
b1011011 /
b1011011 .
12
#960000
02
#965000
b1011100 .
b1011100 /
12
#970000
02
#975000
b1011101 /
b1011101 .
12
#980000
02
#985000
b1011110 .
b1011110 /
12
#990000
02
#995000
b1011111 /
b1011111 .
12
#1000000
1#
0*
b1 )
b1 =
0(
b1 >
b1 A
02
b100000 0
b100000 4
b100000 @
1!
1$
1<
07
0;
0%
08
0&
06
0"
b1 ?
b1 C
0:
0'
09
b0 1
b0 5
b0 B
#1005000
b1100000 .
b1100000 /
12
#1010000
02
#1015000
b1100001 /
b1100001 .
12
#1020000
02
#1025000
b1100010 .
b1100010 /
12
#1030000
02
#1035000
b1100011 /
b1100011 .
12
#1040000
02
#1045000
b1100100 .
b1100100 /
12
#1050000
02
#1055000
b1100101 /
b1100101 .
12
#1060000
02
#1065000
b1100110 .
b1100110 /
12
#1070000
02
#1075000
b1100111 /
b1100111 .
12
#1080000
02
#1085000
b1101000 .
b1101000 /
12
#1090000
02
#1095000
b1101001 /
b1101001 .
12
#1100000
02
#1105000
b1101010 .
b1101010 /
12
#1110000
02
#1115000
b1101011 /
b1101011 .
12
#1120000
02
#1125000
b1101100 .
b1101100 /
12
#1130000
02
#1135000
b1101101 /
b1101101 .
12
#1140000
02
#1145000
b1101110 .
b1101110 /
12
#1150000
02
#1155000
b1101111 /
b1101111 .
12
#1160000
02
#1165000
b1110000 .
b1110000 /
12
#1170000
02
#1175000
b1110001 /
b1110001 .
12
#1180000
02
#1185000
b1110010 .
b1110010 /
12
#1190000
02
#1195000
b1110011 /
b1110011 .
12
#1200000
02
#1205000
b1110100 .
b1110100 /
12
#1210000
02
#1215000
b1110101 /
b1110101 .
12
#1220000
02
#1225000
b1110110 .
b1110110 /
12
#1230000
02
#1235000
b1110111 /
b1110111 .
12
#1240000
02
#1245000
b1111000 .
b1111000 /
12
#1250000
02
#1255000
b1111001 /
b1111001 .
12
#1260000
02
#1265000
b1111010 .
b1111010 /
12
#1270000
02
#1275000
b1111011 /
b1111011 .
12
#1280000
02
#1285000
b1111100 .
b1111100 /
12
#1290000
02
#1295000
b1111101 /
b1111101 .
12
#1300000
02
#1305000
b1111110 .
b1111110 /
12
#1310000
02
#1315000
b1111111 /
b1111111 .
12
#1320000
02
#1325000
b10000000 .
b10000000 /
12
#1330000
02
#1335000
b10000001 /
b10000001 .
12
#1340000
02
#1345000
b10000010 .
b10000010 /
12
#1350000
02
#1355000
b10000011 /
b10000011 .
12
#1360000
02
#1365000
b10000100 .
b10000100 /
12
#1370000
02
#1375000
b10000101 /
b10000101 .
12
#1380000
02
#1385000
b10000110 .
b10000110 /
12
#1390000
02
#1395000
b10000111 /
b10000111 .
12
#1400000
02
#1405000
b10001000 .
b10001000 /
12
#1410000
02
#1415000
b10001001 /
b10001001 .
12
#1420000
02
#1425000
b10001010 .
b10001010 /
12
#1430000
02
#1435000
b10001011 /
b10001011 .
12
#1440000
02
#1445000
b10001100 .
b10001100 /
12
#1450000
02
#1455000
b10001101 /
b10001101 .
12
#1460000
02
#1465000
b10001110 .
b10001110 /
12
#1470000
02
#1475000
b10001111 /
b10001111 .
12
#1480000
02
#1485000
b10010000 .
b10010000 /
12
#1490000
02
#1495000
b10010001 /
b10010001 .
12
#1500000
02
#1505000
b10010010 .
b10010010 /
12
#1510000
02
#1515000
b10010011 /
b10010011 .
12
#1520000
02
#1525000
b10010100 .
b10010100 /
12
#1530000
02
#1535000
b10010101 /
b10010101 .
12
#1540000
02
#1545000
b10010110 .
b10010110 /
12
#1550000
02
#1555000
b10010111 /
b10010111 .
12
#1560000
02
#1565000
b10011000 .
b10011000 /
12
#1570000
02
#1575000
b10011001 /
b10011001 .
12
#1580000
02
#1585000
b10011010 .
b10011010 /
12
#1590000
02
#1595000
b10011011 /
b10011011 .
12
#1600000
02
#1605000
b10011100 .
b10011100 /
12
#1610000
02
#1615000
b10011101 /
b10011101 .
12
#1620000
02
#1625000
b10011110 .
b10011110 /
12
#1630000
02
#1635000
b10011111 /
b10011111 .
12
#1640000
02
#1645000
b10100000 .
b10100000 /
12
#1650000
02
#1655000
b10100001 /
b10100001 .
12
#1660000
02
#1665000
b10100010 .
b10100010 /
12
#1670000
02
#1675000
b10100011 /
b10100011 .
12
#1680000
02
#1685000
b10100100 .
b10100100 /
12
#1690000
02
#1695000
b10100101 /
b10100101 .
12
#1700000
02
#1705000
b10100110 .
b10100110 /
12
#1710000
02
#1715000
b10100111 /
b10100111 .
12
#1720000
02
#1725000
b10101000 .
b10101000 /
12
#1730000
02
#1735000
b10101001 /
b10101001 .
12
#1740000
02
#1745000
b10101010 .
b10101010 /
12
#1750000
02
#1755000
b10101011 /
b10101011 .
12
#1760000
02
#1765000
b10101100 .
b10101100 /
12
#1770000
02
#1775000
b10101101 /
b10101101 .
12
#1780000
02
#1785000
b10101110 .
b10101110 /
12
#1790000
02
#1795000
b10101111 /
b10101111 .
12
#1800000
02
#1805000
b10110000 .
b10110000 /
12
#1810000
02
#1815000
b10110001 /
b10110001 .
12
#1820000
02
#1825000
b10110010 .
b10110010 /
12
#1830000
02
#1835000
b10110011 /
b10110011 .
12
#1840000
02
#1845000
b10110100 .
b10110100 /
12
#1850000
02
#1855000
b10110101 /
b10110101 .
12
#1860000
02
#1865000
b10110110 .
b10110110 /
12
#1870000
02
#1875000
b10110111 /
b10110111 .
12
#1880000
02
#1885000
b10111000 .
b10111000 /
12
#1890000
02
#1895000
b10111001 /
b10111001 .
12
#1900000
02
#1905000
b10111010 .
b10111010 /
12
#1910000
02
#1915000
b10111011 /
b10111011 .
12
#1920000
02
#1925000
b10111100 .
b10111100 /
12
#1930000
02
#1935000
b10111101 /
b10111101 .
12
#1940000
02
#1945000
b10111110 .
b10111110 /
12
#1950000
02
#1955000
b10111111 /
b10111111 .
12
#1960000
02
#1965000
b11000000 .
b11000000 /
12
#1970000
02
#1975000
b11000001 /
b11000001 .
12
#1980000
02
#1985000
b11000010 .
b11000010 /
12
#1990000
02
#1995000
b11000011 /
b11000011 .
12
#2000000
b101 )
b101 =
b101 >
b101 A
02
b100010 0
b100010 4
b100010 @
#2005000
b11000100 .
b11000100 /
12
#2010000
02
#2015000
b11000101 /
b11000101 .
12
#2020000
02
#2025000
b11000110 .
b11000110 /
12
#2030000
02
#2035000
b11000111 /
b11000111 .
12
#2040000
02
#2045000
b11001000 .
b11001000 /
12
#2050000
02
#2055000
b11001001 /
b11001001 .
12
#2060000
02
#2065000
b11001010 .
b11001010 /
12
#2070000
02
#2075000
b11001011 /
b11001011 .
12
#2080000
02
#2085000
b11001100 .
b11001100 /
12
#2090000
02
#2095000
b11001101 /
b11001101 .
12
#2100000
02
#2105000
b11001110 .
b11001110 /
12
#2110000
02
#2115000
b11001111 /
b11001111 .
12
#2120000
02
#2125000
b11010000 .
b11010000 /
12
#2130000
02
#2135000
b11010001 /
b11010001 .
12
#2140000
02
#2145000
b11010010 .
b11010010 /
12
#2150000
02
#2155000
b11010011 /
b11010011 .
12
#2160000
02
#2165000
b11010100 .
b11010100 /
12
#2170000
02
#2175000
b11010101 /
b11010101 .
12
#2180000
02
#2185000
b11010110 .
b11010110 /
12
#2190000
02
#2195000
b11010111 /
b11010111 .
12
#2200000
02
#2205000
b11011000 .
b11011000 /
12
#2210000
02
#2215000
b11011001 /
b11011001 .
12
#2220000
02
#2225000
b11011010 .
b11011010 /
12
#2230000
02
#2235000
b11011011 /
b11011011 .
12
#2240000
02
#2245000
b11011100 .
b11011100 /
12
#2250000
02
#2255000
b11011101 /
b11011101 .
12
#2260000
02
#2265000
b11011110 .
b11011110 /
12
#2270000
02
#2275000
b11011111 /
b11011111 .
12
#2280000
02
#2285000
b11100000 .
b11100000 /
12
#2290000
02
#2295000
b11100001 /
b11100001 .
12
#2300000
02
#2305000
b11100010 .
b11100010 /
12
#2310000
02
#2315000
b11100011 /
b11100011 .
12
#2320000
02
#2325000
b11100100 .
b11100100 /
12
#2330000
02
#2335000
b11100101 /
b11100101 .
12
#2340000
02
#2345000
b11100110 .
b11100110 /
12
#2350000
02
#2355000
b11100111 /
b11100111 .
12
#2360000
02
#2365000
b11101000 .
b11101000 /
12
#2370000
02
#2375000
b11101001 /
b11101001 .
12
#2380000
02
#2385000
b11101010 .
b11101010 /
12
#2390000
02
#2395000
b11101011 /
b11101011 .
12
#2400000
02
#2405000
b11101100 .
b11101100 /
12
#2410000
02
#2415000
b11101101 /
b11101101 .
12
#2420000
02
#2425000
b11101110 .
b11101110 /
12
#2430000
02
#2435000
b11101111 /
b11101111 .
12
#2440000
02
#2445000
b11110000 .
b11110000 /
12
#2450000
02
#2455000
b11110001 /
b11110001 .
12
#2460000
02
#2465000
b11110010 .
b11110010 /
12
#2470000
02
#2475000
b11110011 /
b11110011 .
12
#2480000
02
#2485000
b11110100 .
b11110100 /
12
#2490000
02
#2495000
b11110101 /
b11110101 .
12
#2500000
02
#2505000
b11110110 .
b11110110 /
12
#2510000
02
#2515000
b11110111 /
b11110111 .
12
#2520000
02
#2525000
b11111000 .
b11111000 /
12
#2530000
02
#2535000
b11111001 /
b11111001 .
12
#2540000
02
#2545000
b11111010 .
b11111010 /
12
#2550000
02
#2555000
b11111011 /
b11111011 .
12
#2560000
02
#2565000
b11111100 .
b11111100 /
12
#2570000
02
#2575000
b11111101 /
b11111101 .
12
#2580000
02
#2585000
b11111110 .
b11111110 /
12
#2590000
02
#2595000
b11111111 /
b11111111 .
12
#2600000
02
#2605000
b100000000 .
b100000000 /
12
#2610000
02
#2615000
b100000001 /
b100000001 .
12
#2620000
02
#2625000
b100000010 .
b100000010 /
12
#2630000
02
#2635000
b100000011 /
b100000011 .
12
#2640000
02
#2645000
b100000100 .
b100000100 /
12
#2650000
02
#2655000
b100000101 /
b100000101 .
12
#2660000
02
#2665000
b100000110 .
b100000110 /
12
#2670000
02
#2675000
b100000111 /
b100000111 .
12
#2680000
02
#2685000
b100001000 .
b100001000 /
12
#2690000
02
#2695000
b100001001 /
b100001001 .
12
#2700000
02
#2705000
b100001010 .
b100001010 /
12
#2710000
02
#2715000
b100001011 /
b100001011 .
12
#2720000
02
#2725000
b100001100 .
b100001100 /
12
#2730000
02
#2735000
b100001101 /
b100001101 .
12
#2740000
02
#2745000
b100001110 .
b100001110 /
12
#2750000
02
#2755000
b100001111 /
b100001111 .
12
#2760000
02
#2765000
b100010000 .
b100010000 /
12
#2770000
02
#2775000
b100010001 /
b100010001 .
12
#2780000
02
#2785000
b100010010 .
b100010010 /
12
#2790000
02
#2795000
b100010011 /
b100010011 .
12
#2800000
02
#2805000
b100010100 .
b100010100 /
12
#2810000
02
#2815000
b100010101 /
b100010101 .
12
#2820000
02
#2825000
b100010110 .
b100010110 /
12
#2830000
02
#2835000
b100010111 /
b100010111 .
12
#2840000
02
#2845000
b100011000 .
b100011000 /
12
#2850000
02
#2855000
b100011001 /
b100011001 .
12
#2860000
02
#2865000
b100011010 .
b100011010 /
12
#2870000
02
#2875000
b100011011 /
b100011011 .
12
#2880000
02
#2885000
b100011100 .
b100011100 /
12
#2890000
02
#2895000
b100011101 /
b100011101 .
12
#2900000
02
#2905000
b100011110 .
b100011110 /
12
#2910000
02
#2915000
b100011111 /
b100011111 .
12
#2920000
02
#2925000
b100100000 .
b100100000 /
12
#2930000
02
#2935000
b100100001 /
b100100001 .
12
#2940000
02
#2945000
b100100010 .
b100100010 /
12
#2950000
02
#2955000
b100100011 /
b100100011 .
12
#2960000
02
#2965000
b100100100 .
b100100100 /
12
#2970000
02
#2975000
b100100101 /
b100100101 .
12
#2980000
02
#2985000
b100100110 .
b100100110 /
12
#2990000
02
#2995000
b100100111 /
b100100111 .
12
#3000000
b100 )
b100 =
b100 >
b100 A
02
b100100 0
b100100 4
b100100 @
#3005000
b100101000 .
b100101000 /
12
#3010000
02
#3015000
b100101001 /
b100101001 .
12
#3020000
02
#3025000
b100101010 .
b100101010 /
12
#3030000
02
#3035000
b100101011 /
b100101011 .
12
#3040000
02
#3045000
b100101100 .
b100101100 /
12
#3050000
02
#3055000
b100101101 /
b100101101 .
12
#3060000
02
#3065000
b100101110 .
b100101110 /
12
#3070000
02
#3075000
b100101111 /
b100101111 .
12
#3080000
02
#3085000
b100110000 .
b100110000 /
12
#3090000
02
#3095000
b100110001 /
b100110001 .
12
#3100000
02
#3105000
b100110010 .
b100110010 /
12
#3110000
02
#3115000
b100110011 /
b100110011 .
12
#3120000
02
#3125000
b100110100 .
b100110100 /
12
#3130000
02
#3135000
b100110101 /
b100110101 .
12
#3140000
02
#3145000
b100110110 .
b100110110 /
12
#3150000
02
#3155000
b100110111 /
b100110111 .
12
#3160000
02
#3165000
b100111000 .
b100111000 /
12
#3170000
02
#3175000
b100111001 /
b100111001 .
12
#3180000
02
#3185000
b100111010 .
b100111010 /
12
#3190000
02
#3195000
b100111011 /
b100111011 .
12
#3200000
02
#3205000
b100111100 .
b100111100 /
12
#3210000
02
#3215000
b100111101 /
b100111101 .
12
#3220000
02
#3225000
b100111110 .
b100111110 /
12
#3230000
02
#3235000
b100111111 /
b100111111 .
12
#3240000
02
#3245000
b101000000 .
b101000000 /
12
#3250000
02
#3255000
b101000001 /
b101000001 .
12
#3260000
02
#3265000
b101000010 .
b101000010 /
12
#3270000
02
#3275000
b101000011 /
b101000011 .
12
#3280000
02
#3285000
b101000100 .
b101000100 /
12
#3290000
02
#3295000
b101000101 /
b101000101 .
12
#3300000
02
#3305000
b101000110 .
b101000110 /
12
#3310000
02
#3315000
b101000111 /
b101000111 .
12
#3320000
02
#3325000
b101001000 .
b101001000 /
12
#3330000
02
#3335000
b101001001 /
b101001001 .
12
#3340000
02
#3345000
b101001010 .
b101001010 /
12
#3350000
02
#3355000
b101001011 /
b101001011 .
12
#3360000
02
#3365000
b101001100 .
b101001100 /
12
#3370000
02
#3375000
b101001101 /
b101001101 .
12
#3380000
02
#3385000
b101001110 .
b101001110 /
12
#3390000
02
#3395000
b101001111 /
b101001111 .
12
#3400000
02
#3405000
b101010000 .
b101010000 /
12
#3410000
02
#3415000
b101010001 /
b101010001 .
12
#3420000
02
#3425000
b101010010 .
b101010010 /
12
#3430000
02
#3435000
b101010011 /
b101010011 .
12
#3440000
02
#3445000
b101010100 .
b101010100 /
12
#3450000
02
#3455000
b101010101 /
b101010101 .
12
#3460000
02
#3465000
b101010110 .
b101010110 /
12
#3470000
02
#3475000
b101010111 /
b101010111 .
12
#3480000
02
#3485000
b101011000 .
b101011000 /
12
#3490000
02
#3495000
b101011001 /
b101011001 .
12
#3500000
02
#3505000
b101011010 .
b101011010 /
12
#3510000
02
#3515000
b101011011 /
b101011011 .
12
#3520000
02
#3525000
b101011100 .
b101011100 /
12
#3530000
02
#3535000
b101011101 /
b101011101 .
12
#3540000
02
#3545000
b101011110 .
b101011110 /
12
#3550000
02
#3555000
b101011111 /
b101011111 .
12
#3560000
02
#3565000
b101100000 .
b101100000 /
12
#3570000
02
#3575000
b101100001 /
b101100001 .
12
#3580000
02
#3585000
b101100010 .
b101100010 /
12
#3590000
02
#3595000
b101100011 /
b101100011 .
12
#3600000
02
#3605000
b101100100 .
b101100100 /
12
#3610000
02
#3615000
b101100101 /
b101100101 .
12
#3620000
02
#3625000
b101100110 .
b101100110 /
12
#3630000
02
#3635000
b101100111 /
b101100111 .
12
#3640000
02
#3645000
b101101000 .
b101101000 /
12
#3650000
02
#3655000
b101101001 /
b101101001 .
12
#3660000
02
#3665000
b101101010 .
b101101010 /
12
#3670000
02
#3675000
b101101011 /
b101101011 .
12
#3680000
02
#3685000
b101101100 .
b101101100 /
12
#3690000
02
#3695000
b101101101 /
b101101101 .
12
#3700000
02
#3705000
b101101110 .
b101101110 /
12
#3710000
02
#3715000
b101101111 /
b101101111 .
12
#3720000
02
#3725000
b101110000 .
b101110000 /
12
#3730000
02
#3735000
b101110001 /
b101110001 .
12
#3740000
02
#3745000
b101110010 .
b101110010 /
12
#3750000
02
#3755000
b101110011 /
b101110011 .
12
#3760000
02
#3765000
b101110100 .
b101110100 /
12
#3770000
02
#3775000
b101110101 /
b101110101 .
12
#3780000
02
#3785000
b101110110 .
b101110110 /
12
#3790000
02
#3795000
b101110111 /
b101110111 .
12
#3800000
02
#3805000
b101111000 .
b101111000 /
12
#3810000
02
#3815000
b101111001 /
b101111001 .
12
#3820000
02
#3825000
b101111010 .
b101111010 /
12
#3830000
02
#3835000
b101111011 /
b101111011 .
12
#3840000
02
#3845000
b101111100 .
b101111100 /
12
#3850000
02
#3855000
b101111101 /
b101111101 .
12
#3860000
02
#3865000
b101111110 .
b101111110 /
12
#3870000
02
#3875000
b101111111 /
b101111111 .
12
#3880000
02
#3885000
b110000000 .
b110000000 /
12
#3890000
02
#3895000
b110000001 /
b110000001 .
12
#3900000
02
#3905000
b110000010 .
b110000010 /
12
#3910000
02
#3915000
b110000011 /
b110000011 .
12
#3920000
02
#3925000
b110000100 .
b110000100 /
12
#3930000
02
#3935000
b110000101 /
b110000101 .
12
#3940000
02
#3945000
b110000110 .
b110000110 /
12
#3950000
02
#3955000
b110000111 /
b110000111 .
12
#3960000
02
