PC/user/src/Extend16to30.v
module Extend16to30(
    input[15:0] in,
    output[29:0] out
);
    // 进行符号扩展
    // always @(in) begin
    //     out = {{14{in[15]}}, in};
    // end
    assign out = {{14{in[15]}}, in};
endmodule

InsMEM/user/src/InsMEM.v
module InsMEM(
    input [31:0] InsAddr,
    output reg [31:0] InsData
    );

    reg [7:0] rom[511:0];

    initial begin
        $readmemh("/Users/yr/code/computer-organization/computer-organization-labs/InsMEM/user/data/Instruction.txt", rom);
        // $readmemh("/Users/yr/code/computer-organization/computer-organization-labs/InsMEM/user/data/fibInstruction.txt", rom);
    end
    // 大端方式
    always @(InsAddr) begin
        InsData[7:0] = rom[InsAddr+3];
        InsData[15:8] = rom[InsAddr+2];
        InsData[23:16] = rom[InsAddr+1];
        InsData[31:24] = rom[InsAddr];
    end

endmodule

PC/user/src/PC.v
module PC(
    input clk,
    input[29:0] nextAddr,
    output reg[29:0] curAddr
);
    // initial begin
    //     curAddr <= 0;
    // end
    always @(posedge clk) begin
        curAddr = nextAddr;
    end
endmodule

PC/user/src/IFU.v
`include "/Users/yr/code/computer-organization/computer-organization-labs/PC/user/src/PC.v"
`include "/Users/yr/code/computer-organization/computer-organization-labs/InsMEM/user/src/InsMEM.v"
`include "/Users/yr/code/computer-organization/computer-organization-labs/PC/user/src/Extend16to30.v"
`timescale 1ns/1ps;
module IFU(
    input clk,
    input jump,
    input branch,
    input zero,
    output[31:0] instruction
);
    reg[31:2] nextAddr;
    wire[31:2] curAddr;
    wire[31:2] extend_imme;

    initial begin
        nextAddr = 0;
    end

    PC pc(
        .clk(clk),
        .nextAddr(nextAddr),
        .curAddr(curAddr)
    );

    InsMEM insMem(
        .InsAddr({curAddr, 2'b00}),
        .InsData(instruction)
    );

    Extend16to30 extend16to30(
        .in(instruction[15:0]),
        .out(extend_imme)
    );

    always @(curAddr) begin
        #10
        if(jump)begin
            nextAddr = {curAddr[31:28], instruction[25:0]};
            $display("[DEBUG] jump curAddr: %h, nextAddr: %d", curAddr, nextAddr);
        end
        else if(branch && zero)begin
            nextAddr = curAddr + 1 + extend_imme;
            $display("[DEBUG] branch curAddr: %d, nextAddr: %d branch=%d zero=%d", curAddr, nextAddr, branch, zero);
            $display("[DEBUG] extend_imme: %d", extend_imme);
        end
        else begin
            nextAddr = curAddr + 1;
        end
    end
endmodule

PC/user/sim/testbench.v
`include "/Users/yr/code/computer-organization/computer-organization-labs/PC/user/src/IFU.v"
`timescale 1ns/1ps;
module testbench();

parameter DATA_WIDTH = 32;
parameter ADDR_WIDTH = 32;
parameter MAIN_FRE   = 100; //unit MHz
reg                   sys_clk = 0;
reg                   sys_rst = 1;
reg [DATA_WIDTH-1:0]  data = 0;
reg [ADDR_WIDTH-1:0]  addr = 0;

always begin
    #100 sys_clk = ~sys_clk;
end

always begin
    #50 sys_rst = 0;
end

always @(posedge sys_clk) begin
    if (sys_rst)
        addr = 0;
    else
        addr = addr + 1;
end
always @(posedge sys_clk) begin
    if (sys_rst)
        data = 0;
    else
        data = data + 1;
end

//Instance
// outports wire
wire [31:0] 	instruction;
reg jump = 0;
reg branch = 0;
reg zero = 0;

IFU u_IFU(
	.clk         	( sys_clk          ),
	.jump        	( jump         ),
	.branch      	( branch       ),
	.zero        	( zero         ),
	.instruction 	( instruction  )
);



initial begin
    $dumpfile("wave.vcd");
    $dumpvars(0, testbench);
    #3300 branch = 1; zero = 1;
    #200 branch = 0; zero = 0;
    #50000 $finish;
end

endmodule  //TOP

PC/user/sim/wave.vcd
$date
	Thu Dec 21 15:11:56 2023
$end
$version
	Icarus Verilog
$end
$timescale
	1ps
$end
$scope module testbench $end
$var wire 32 ! instruction [31:0] $end
$var parameter 32 " ADDR_WIDTH $end
$var parameter 32 # DATA_WIDTH $end
$var parameter 32 $ MAIN_FRE $end
$var reg 32 % addr [31:0] $end
$var reg 1 & branch $end
$var reg 32 ' data [31:0] $end
$var reg 1 ( jump $end
$var reg 1 ) sys_clk $end
$var reg 1 * sys_rst $end
$var reg 1 + zero $end
$scope module u_IFU $end
$var wire 1 & branch $end
$var wire 1 ) clk $end
$var wire 1 ( jump $end
$var wire 1 + zero $end
$var wire 32 , instruction [31:0] $end
$var wire 30 - extend_imme [31:2] $end
$var wire 30 . curAddr [31:2] $end
$var reg 30 / nextAddr [31:2] $end
$scope module extend16to30 $end
$var wire 16 0 in [15:0] $end
$var wire 30 1 out [29:0] $end
$upscope $end
$scope module insMem $end
$var wire 32 2 InsAddr [31:0] $end
$var reg 32 3 InsData [31:0] $end
$upscope $end
$scope module pc $end
$var wire 1 ) clk $end
$var wire 30 4 nextAddr [29:0] $end
$var reg 30 5 curAddr [29:0] $end
$upscope $end
$upscope $end
$upscope $end
$enddefinitions $end
$comment Show the parameter values. $end
$dumpall
b1100100 $
b100000 #
b100000 "
$end
#0
$dumpvars
bx 5
b0 4
bx 3
bx00 2
bx 1
bx 0
b0 /
bx .
bx -
bx ,
0+
1*
0)
0(
b0 '
0&
b0 %
bx !
$end
#50000
0*
#100000
b0 -
b0 1
b0 0
b10001100000001000000000000000000 !
b10001100000001000000000000000000 ,
b10001100000001000000000000000000 3
b0 2
b0 .
b0 5
b1 %
b1 '
1)
#110000
b1 /
b1 4
#200000
0)
#300000
b10001100000001010000000000000000 !
b10001100000001010000000000000000 ,
b10001100000001010000000000000000 3
b10 '
b10 %
b100 2
b1 .
b1 5
1)
#310000
b10 /
b10 4
#400000
0)
#500000
b11000000100000 -
b11000000100000 1
b11000000100000 0
b100001010011000000100000 !
b100001010011000000100000 ,
b100001010011000000100000 3
b1000 2
b10 .
b10 5
b11 %
b11 '
1)
#510000
b11 /
b11 4
#600000
0)
#700000
b100 -
b100 1
b100 0
b10101100000001100000000000000100 !
b10101100000001100000000000000100 ,
b10101100000001100000000000000100 3
b100 '
b100 %
b1100 2
b11 .
b11 5
1)
#710000
b100 /
b100 4
#800000
0)
#900000
b10001100000001110000000000000100 !
b10001100000001110000000000000100 ,
b10001100000001110000000000000100 3
b10000 2
b100 .
b100 5
b101 %
b101 '
1)
#910000
b101 /
b101 4
#1000000
0)
#1100000
b100000000100010 -
b100000000100010 1
b100000000100010 0
b100001110100000000100010 !
b100001110100000000100010 ,
b100001110100000000100010 3
b110 '
b110 %
b10100 2
b101 .
b101 5
1)
#1110000
b110 /
b110 4
#1200000
0)
#1300000
b1000 -
b1000 1
b1000 0
b10101100000010000000000000001000 !
b10101100000010000000000000001000 ,
b10101100000010000000000000001000 3
b11000 2
b110 .
b110 5
b111 %
b111 '
1)
#1310000
b111 /
b111 4
#1400000
0)
#1500000
b101000000101 -
b101000000101 1
b101000000101 0
b100100000000010000101000000101 !
b100100000000010000101000000101 ,
b100100000000010000101000000101 3
b1000 '
b1000 %
b11100 2
b111 .
b111 5
1)
#1510000
b1000 /
b1000 4
#1600000
0)
#1700000
b111111111111111111111110101000 -
b111111111111111111111110101000 1
b1111111110101000 0
b100100000000101111111110101000 !
b100100000000101111111110101000 ,
b100100000000101111111110101000 3
b100000 2
b1000 .
b1000 5
b1001 %
b1001 '
1)
#1710000
b1001 /
b1001 4
#1800000
0)
#1900000
b10110010000 -
b10110010000 1
b10110010000 0
b110100001000010000010110010000 !
b110100001000010000010110010000 ,
b110100001000010000010110010000 3
b1010 '
b1010 %
b100100 2
b1001 .
b1001 5
1)
#1910000
b1010 /
b1010 4
#2000000
0)
#2100000
b111111111111111000111101101100 -
b111111111111111000111101101100 1
b1000111101101100 0
b110100010000101000111101101100 !
b110100010000101000111101101100 ,
b110100010000101000111101101100 3
b101000 2
b1010 .
b1010 5
b1011 %
b1011 '
1)
#2110000
b1011 /
b1011 4
#2200000
0)
#2300000
b1100000101010 -
b1100000101010 1
b1100000101010 0
b1000100001100000101010 !
b1000100001100000101010 ,
b1000100001100000101010 3
b1100 '
b1100 %
b101100 2
b1011 .
b1011 5
1)
#2310000
b1100 /
b1100 4
#2400000
0)
#2500000
b1100000101011 -
b1100000101011 1
b1100000101011 0
b1000100001100000101011 !
b1000100001100000101011 ,
b1000100001100000101011 3
b110000 2
b1100 .
b1100 5
b1101 %
b1101 '
1)
#2510000
b1101 /
b1101 4
#2600000
0)
#2700000
b1100 -
b1100 1
b1100 0
b10001100000001000000000000001100 !
b10001100000001000000000000001100 ,
b10001100000001000000000000001100 3
b1110 '
b1110 %
b110100 2
b1101 .
b1101 5
1)
#2710000
b1110 /
b1110 4
#2800000
0)
#2900000
b11000000100010 -
b11000000100010 1
b11000000100010 0
b100001010011000000100010 !
b100001010011000000100010 ,
b100001010011000000100010 3
b111000 2
b1110 .
b1110 5
b1111 %
b1111 '
1)
#2910000
b1111 /
b1111 4
#3000000
0)
#3100000
b11000000100011 -
b11000000100011 1
b11000000100011 0
b1010011000000100011 !
b1010011000000100011 ,
b1010011000000100011 3
b10000 '
b10000 %
b111100 2
b1111 .
b1111 5
1)
#3110000
b10000 /
b10000 4
#3200000
0)
#3300000
b10 -
b10 1
b10 0
b10000011001100000000000000010 !
b10000011001100000000000000010 ,
b10000011001100000000000000010 3
b1000000 2
b10000 .
b10000 5
b10001 %
b10001 '
1)
1+
1&
#3310000
b10011 /
b10011 4
#3400000
0)
#3500000
b0 -
b0 1
b0 0
b10001100000011000000000000000000 !
b10001100000011000000000000000000 ,
b10001100000011000000000000000000 3
b10010 '
b10010 %
b1001100 2
b10011 .
b10011 5
1)
0+
0&
#3510000
b10100 /
b10100 4
#3600000
0)
#3700000
b10001100000011010000000000000000 !
b10001100000011010000000000000000 ,
b10001100000011010000000000000000 3
b1010000 2
b10100 .
b10100 5
b10011 %
b10011 '
1)
#3710000
b10101 /
b10101 4
#3800000
0)
#3900000
bx -
bx 1
bx 0
bx !
bx ,
bx 3
b10100 '
b10100 %
b1010100 2
b10101 .
b10101 5
1)
#3910000
b10110 /
b10110 4
#4000000
0)
#4100000
b1011000 2
b10110 .
b10110 5
b10101 %
b10101 '
1)
#4110000
b10111 /
b10111 4
#4200000
0)
#4300000
b10110 '
b10110 %
b1011100 2
b10111 .
b10111 5
1)
#4310000
b11000 /
b11000 4
#4400000
0)
#4500000
b1100000 2
b11000 .
b11000 5
b10111 %
b10111 '
1)
#4510000
b11001 /
b11001 4
#4600000
0)
#4700000
b11000 '
b11000 %
b1100100 2
b11001 .
b11001 5
1)
#4710000
b11010 /
b11010 4
#4800000
0)
#4900000
b1101000 2
b11010 .
b11010 5
b11001 %
b11001 '
1)
#4910000
b11011 /
b11011 4
#5000000
0)
#5100000
b11010 '
b11010 %
b1101100 2
b11011 .
b11011 5
1)
#5110000
b11100 /
b11100 4
#5200000
0)
#5300000
b1110000 2
b11100 .
b11100 5
b11011 %
b11011 '
1)
#5310000
b11101 /
b11101 4
#5400000
0)
#5500000
b11100 '
b11100 %
b1110100 2
b11101 .
b11101 5
1)
#5510000
b11110 /
b11110 4
#5600000
0)
#5700000
b1111000 2
b11110 .
b11110 5
b11101 %
b11101 '
1)
#5710000
b11111 /
b11111 4
#5800000
0)
#5900000
b11110 '
b11110 %
b1111100 2
b11111 .
b11111 5
1)
#5910000
b100000 /
b100000 4
#6000000
0)
#6100000
b10000000 2
b100000 .
b100000 5
b11111 %
b11111 '
1)
#6110000
b100001 /
b100001 4
#6200000
0)
#6300000
b100000 '
b100000 %
b10000100 2
b100001 .
b100001 5
1)
#6310000
b100010 /
b100010 4
#6400000
0)
#6500000
b10001000 2
b100010 .
b100010 5
b100001 %
b100001 '
1)
#6510000
b100011 /
b100011 4
#6600000
0)
#6700000
b100010 '
b100010 %
b10001100 2
b100011 .
b100011 5
1)
#6710000
b100100 /
b100100 4
#6800000
0)
#6900000
b10010000 2
b100100 .
b100100 5
b100011 %
b100011 '
1)
#6910000
b100101 /
b100101 4
#7000000
0)
#7100000
b100100 '
b100100 %
b10010100 2
b100101 .
b100101 5
1)
#7110000
b100110 /
b100110 4
#7200000
0)
#7300000
b10011000 2
b100110 .
b100110 5
b100101 %
b100101 '
1)
#7310000
b100111 /
b100111 4
#7400000
0)
#7500000
b100110 '
b100110 %
b10011100 2
b100111 .
b100111 5
1)
#7510000
b101000 /
b101000 4
#7600000
0)
#7700000
b10100000 2
b101000 .
b101000 5
b100111 %
b100111 '
1)
#7710000
b101001 /
b101001 4
#7800000
0)
#7900000
b101000 '
b101000 %
b10100100 2
b101001 .
b101001 5
1)
#7910000
b101010 /
b101010 4
#8000000
0)
#8100000
b10101000 2
b101010 .
b101010 5
b101001 %
b101001 '
1)
#8110000
b101011 /
b101011 4
#8200000
0)
#8300000
b101010 '
b101010 %
b10101100 2
b101011 .
b101011 5
1)
#8310000
b101100 /
b101100 4
#8400000
0)
#8500000
b10110000 2
b101100 .
b101100 5
b101011 %
b101011 '
1)
#8510000
b101101 /
b101101 4
#8600000
0)
#8700000
b101100 '
b101100 %
b10110100 2
b101101 .
b101101 5
1)
#8710000
b101110 /
b101110 4
#8800000
0)
#8900000
b10111000 2
b101110 .
b101110 5
b101101 %
b101101 '
1)
#8910000
b101111 /
b101111 4
#9000000
0)
#9100000
b101110 '
b101110 %
b10111100 2
b101111 .
b101111 5
1)
#9110000
b110000 /
b110000 4
#9200000
0)
#9300000
b11000000 2
b110000 .
b110000 5
b101111 %
b101111 '
1)
#9310000
b110001 /
b110001 4
#9400000
0)
#9500000
b110000 '
b110000 %
b11000100 2
b110001 .
b110001 5
1)
#9510000
b110010 /
b110010 4
#9600000
0)
#9700000
b11001000 2
b110010 .
b110010 5
b110001 %
b110001 '
1)
#9710000
b110011 /
b110011 4
#9800000
0)
#9900000
b110010 '
b110010 %
b11001100 2
b110011 .
b110011 5
1)
#9910000
b110100 /
b110100 4
#10000000
0)
#10100000
b11010000 2
b110100 .
b110100 5
b110011 %
b110011 '
1)
#10110000
b110101 /
b110101 4
#10200000
0)
#10300000
b110100 '
b110100 %
b11010100 2
b110101 .
b110101 5
1)
#10310000
b110110 /
b110110 4
#10400000
0)
#10500000
b11011000 2
b110110 .
b110110 5
b110101 %
b110101 '
1)
#10510000
b110111 /
b110111 4
#10600000
0)
#10700000
b110110 '
b110110 %
b11011100 2
b110111 .
b110111 5
1)
#10710000
b111000 /
b111000 4
#10800000
0)
#10900000
b11100000 2
b111000 .
b111000 5
b110111 %
b110111 '
1)
#10910000
b111001 /
b111001 4
#11000000
0)
#11100000
b111000 '
b111000 %
b11100100 2
b111001 .
b111001 5
1)
#11110000
b111010 /
b111010 4
#11200000
0)
#11300000
b11101000 2
b111010 .
b111010 5
b111001 %
b111001 '
1)
#11310000
b111011 /
b111011 4
#11400000
0)
#11500000
b111010 '
b111010 %
b11101100 2
b111011 .
b111011 5
1)
#11510000
b111100 /
b111100 4
#11600000
0)
#11700000
b11110000 2
b111100 .
b111100 5
b111011 %
b111011 '
1)
#11710000
b111101 /
b111101 4
#11800000
0)
#11900000
b111100 '
b111100 %
b11110100 2
b111101 .
b111101 5
1)
#11910000
b111110 /
b111110 4
#12000000
0)
#12100000
b11111000 2
b111110 .
b111110 5
b111101 %
b111101 '
1)
#12110000
b111111 /
b111111 4
#12200000
0)
#12300000
b111110 '
b111110 %
b11111100 2
b111111 .
b111111 5
1)
#12310000
b1000000 /
b1000000 4
#12400000
0)
#12500000
b100000000 2
b1000000 .
b1000000 5
b111111 %
b111111 '
1)
#12510000
b1000001 /
b1000001 4
#12600000
0)
#12700000
b1000000 '
b1000000 %
b100000100 2
b1000001 .
b1000001 5
1)
#12710000
b1000010 /
b1000010 4
#12800000
0)
#12900000
b100001000 2
b1000010 .
b1000010 5
b1000001 %
b1000001 '
1)
#12910000
b1000011 /
b1000011 4
#13000000
0)
#13100000
b1000010 '
b1000010 %
b100001100 2
b1000011 .
b1000011 5
1)
#13110000
b1000100 /
b1000100 4
#13200000
0)
#13300000
b100010000 2
b1000100 .
b1000100 5
b1000011 %
b1000011 '
1)
#13310000
b1000101 /
b1000101 4
#13400000
0)
#13500000
b1000100 '
b1000100 %
b100010100 2
b1000101 .
b1000101 5
1)
#13510000
b1000110 /
b1000110 4
#13600000
0)
#13700000
b100011000 2
b1000110 .
b1000110 5
b1000101 %
b1000101 '
1)
#13710000
b1000111 /
b1000111 4
#13800000
0)
#13900000
b1000110 '
b1000110 %
b100011100 2
b1000111 .
b1000111 5
1)
#13910000
b1001000 /
b1001000 4
#14000000
0)
#14100000
b100100000 2
b1001000 .
b1001000 5
b1000111 %
b1000111 '
1)
#14110000
b1001001 /
b1001001 4
#14200000
0)
#14300000
b1001000 '
b1001000 %
b100100100 2
b1001001 .
b1001001 5
1)
#14310000
b1001010 /
b1001010 4
#14400000
0)
#14500000
b100101000 2
b1001010 .
b1001010 5
b1001001 %
b1001001 '
1)
#14510000
b1001011 /
b1001011 4
#14600000
0)
#14700000
b1001010 '
b1001010 %
b100101100 2
b1001011 .
b1001011 5
1)
#14710000
b1001100 /
b1001100 4
#14800000
0)
#14900000
b100110000 2
b1001100 .
b1001100 5
b1001011 %
b1001011 '
1)
#14910000
b1001101 /
b1001101 4
#15000000
0)
#15100000
b1001100 '
b1001100 %
b100110100 2
b1001101 .
b1001101 5
1)
#15110000
b1001110 /
b1001110 4
#15200000
0)
#15300000
b100111000 2
b1001110 .
b1001110 5
b1001101 %
b1001101 '
1)
#15310000
b1001111 /
b1001111 4
#15400000
0)
#15500000
b1001110 '
b1001110 %
b100111100 2
b1001111 .
b1001111 5
1)
#15510000
b1010000 /
b1010000 4
#15600000
0)
#15700000
b101000000 2
b1010000 .
b1010000 5
b1001111 %
b1001111 '
1)
#15710000
b1010001 /
b1010001 4
#15800000
0)
#15900000
b1010000 '
b1010000 %
b101000100 2
b1010001 .
b1010001 5
1)
#15910000
b1010010 /
b1010010 4
#16000000
0)
#16100000
b101001000 2
b1010010 .
b1010010 5
b1010001 %
b1010001 '
1)
#16110000
b1010011 /
b1010011 4
#16200000
0)
#16300000
b1010010 '
b1010010 %
b101001100 2
b1010011 .
b1010011 5
1)
#16310000
b1010100 /
b1010100 4
#16400000
0)
#16500000
b101010000 2
b1010100 .
b1010100 5
b1010011 %
b1010011 '
1)
#16510000
b1010101 /
b1010101 4
#16600000
0)
#16700000
b1010100 '
b1010100 %
b101010100 2
b1010101 .
b1010101 5
1)
#16710000
b1010110 /
b1010110 4
#16800000
0)
#16900000
b101011000 2
b1010110 .
b1010110 5
b1010101 %
b1010101 '
1)
#16910000
b1010111 /
b1010111 4
#17000000
0)
#17100000
b1010110 '
b1010110 %
b101011100 2
b1010111 .
b1010111 5
1)
#17110000
b1011000 /
b1011000 4
#17200000
0)
#17300000
b101100000 2
b1011000 .
b1011000 5
b1010111 %
b1010111 '
1)
#17310000
b1011001 /
b1011001 4
#17400000
0)
#17500000
b1011000 '
b1011000 %
b101100100 2
b1011001 .
b1011001 5
1)
#17510000
b1011010 /
b1011010 4
#17600000
0)
#17700000
b101101000 2
b1011010 .
b1011010 5
b1011001 %
b1011001 '
1)
#17710000
b1011011 /
b1011011 4
#17800000
0)
#17900000
b1011010 '
b1011010 %
b101101100 2
b1011011 .
b1011011 5
1)
#17910000
b1011100 /
b1011100 4
#18000000
0)
#18100000
b101110000 2
b1011100 .
b1011100 5
b1011011 %
b1011011 '
1)
#18110000
b1011101 /
b1011101 4
#18200000
0)
#18300000
b1011100 '
b1011100 %
b101110100 2
b1011101 .
b1011101 5
1)
#18310000
b1011110 /
b1011110 4
#18400000
0)
#18500000
b101111000 2
b1011110 .
b1011110 5
b1011101 %
b1011101 '
1)
#18510000
b1011111 /
b1011111 4
#18600000
0)
#18700000
b1011110 '
b1011110 %
b101111100 2
b1011111 .
b1011111 5
1)
#18710000
b1100000 /
b1100000 4
#18800000
0)
#18900000
b110000000 2
b1100000 .
b1100000 5
b1011111 %
b1011111 '
1)
#18910000
b1100001 /
b1100001 4
#19000000
0)
#19100000
b1100000 '
b1100000 %
b110000100 2
b1100001 .
b1100001 5
1)
#19110000
b1100010 /
b1100010 4
#19200000
0)
#19300000
b110001000 2
b1100010 .
b1100010 5
b1100001 %
b1100001 '
1)
#19310000
b1100011 /
b1100011 4
#19400000
0)
#19500000
b1100010 '
b1100010 %
b110001100 2
b1100011 .
b1100011 5
1)
#19510000
b1100100 /
b1100100 4
#19600000
0)
#19700000
b110010000 2
b1100100 .
b1100100 5
b1100011 %
b1100011 '
1)
#19710000
b1100101 /
b1100101 4
#19800000
0)
#19900000
b1100100 '
b1100100 %
b110010100 2
b1100101 .
b1100101 5
1)
#19910000
b1100110 /
b1100110 4
#20000000
0)
#20100000
b110011000 2
b1100110 .
b1100110 5
b1100101 %
b1100101 '
1)
#20110000
b1100111 /
b1100111 4
#20200000
0)
#20300000
b1100110 '
b1100110 %
b110011100 2
b1100111 .
b1100111 5
1)
#20310000
b1101000 /
b1101000 4
#20400000
0)
#20500000
b110100000 2
b1101000 .
b1101000 5
b1100111 %
b1100111 '
1)
#20510000
b1101001 /
b1101001 4
#20600000
0)
#20700000
b1101000 '
b1101000 %
b110100100 2
b1101001 .
b1101001 5
1)
#20710000
b1101010 /
b1101010 4
#20800000
0)
#20900000
b110101000 2
b1101010 .
b1101010 5
b1101001 %
b1101001 '
1)
#20910000
b1101011 /
b1101011 4
#21000000
0)
#21100000
b1101010 '
b1101010 %
b110101100 2
b1101011 .
b1101011 5
1)
#21110000
b1101100 /
b1101100 4
#21200000
0)
#21300000
b110110000 2
b1101100 .
b1101100 5
b1101011 %
b1101011 '
1)
#21310000
b1101101 /
b1101101 4
#21400000
0)
#21500000
b1101100 '
b1101100 %
b110110100 2
b1101101 .
b1101101 5
1)
#21510000
b1101110 /
b1101110 4
#21600000
0)
#21700000
b110111000 2
b1101110 .
b1101110 5
b1101101 %
b1101101 '
1)
#21710000
b1101111 /
b1101111 4
#21800000
0)
#21900000
b1101110 '
b1101110 %
b110111100 2
b1101111 .
b1101111 5
1)
#21910000
b1110000 /
b1110000 4
#22000000
0)
#22100000
b111000000 2
b1110000 .
b1110000 5
b1101111 %
b1101111 '
1)
#22110000
b1110001 /
b1110001 4
#22200000
0)
#22300000
b1110000 '
b1110000 %
b111000100 2
b1110001 .
b1110001 5
1)
#22310000
b1110010 /
b1110010 4
#22400000
0)
#22500000
b111001000 2
b1110010 .
b1110010 5
b1110001 %
b1110001 '
1)
#22510000
b1110011 /
b1110011 4
#22600000
0)
#22700000
b1110010 '
b1110010 %
b111001100 2
b1110011 .
b1110011 5
1)
#22710000
b1110100 /
b1110100 4
#22800000
0)
#22900000
b111010000 2
b1110100 .
b1110100 5
b1110011 %
b1110011 '
1)
#22910000
b1110101 /
b1110101 4
#23000000
0)
#23100000
b1110100 '
b1110100 %
b111010100 2
b1110101 .
b1110101 5
1)
#23110000
b1110110 /
b1110110 4
#23200000
0)
#23300000
b111011000 2
b1110110 .
b1110110 5
b1110101 %
b1110101 '
1)
#23310000
b1110111 /
b1110111 4
#23400000
0)
#23500000
b1110110 '
b1110110 %
b111011100 2
b1110111 .
b1110111 5
1)
#23510000
b1111000 /
b1111000 4
#23600000
0)
#23700000
b111100000 2
b1111000 .
b1111000 5
b1110111 %
b1110111 '
1)
#23710000
b1111001 /
b1111001 4
#23800000
0)
#23900000
b1111000 '
b1111000 %
b111100100 2
b1111001 .
b1111001 5
1)
#23910000
b1111010 /
b1111010 4
#24000000
0)
#24100000
b111101000 2
b1111010 .
b1111010 5
b1111001 %
b1111001 '
1)
#24110000
b1111011 /
b1111011 4
#24200000
0)
#24300000
b1111010 '
b1111010 %
b111101100 2
b1111011 .
b1111011 5
1)
#24310000
b1111100 /
b1111100 4
#24400000
0)
#24500000
b111110000 2
b1111100 .
b1111100 5
b1111011 %
b1111011 '
1)
#24510000
b1111101 /
b1111101 4
#24600000
0)
#24700000
b1111100 '
b1111100 %
b111110100 2
b1111101 .
b1111101 5
1)
#24710000
b1111110 /
b1111110 4
#24800000
0)
#24900000
b111111000 2
b1111110 .
b1111110 5
b1111101 %
b1111101 '
1)
#24910000
b1111111 /
b1111111 4
#25000000
0)
#25100000
b1111110 '
b1111110 %
b111111100 2
b1111111 .
b1111111 5
1)
#25110000
b10000000 /
b10000000 4
#25200000
0)
#25300000
b1000000000 2
b10000000 .
b10000000 5
b1111111 %
b1111111 '
1)
#25310000
b10000001 /
b10000001 4
#25400000
0)
#25500000
b10000000 '
b10000000 %
b1000000100 2
b10000001 .
b10000001 5
1)
#25510000
b10000010 /
b10000010 4
#25600000
0)
#25700000
b1000001000 2
b10000010 .
b10000010 5
b10000001 %
b10000001 '
1)
#25710000
b10000011 /
b10000011 4
#25800000
0)
#25900000
b10000010 '
b10000010 %
b1000001100 2
b10000011 .
b10000011 5
1)
#25910000
b10000100 /
b10000100 4
#26000000
0)
#26100000
b1000010000 2
b10000100 .
b10000100 5
b10000011 %
b10000011 '
1)
#26110000
b10000101 /
b10000101 4
#26200000
0)
#26300000
b10000100 '
b10000100 %
b1000010100 2
b10000101 .
b10000101 5
1)
#26310000
b10000110 /
b10000110 4
#26400000
0)
#26500000
b1000011000 2
b10000110 .
b10000110 5
b10000101 %
b10000101 '
1)
#26510000
b10000111 /
b10000111 4
#26600000
0)
#26700000
b10000110 '
b10000110 %
b1000011100 2
b10000111 .
b10000111 5
1)
#26710000
b10001000 /
b10001000 4
#26800000
0)
#26900000
b1000100000 2
b10001000 .
b10001000 5
b10000111 %
b10000111 '
1)
#26910000
b10001001 /
b10001001 4
#27000000
0)
#27100000
b10001000 '
b10001000 %
b1000100100 2
b10001001 .
b10001001 5
1)
#27110000
b10001010 /
b10001010 4
#27200000
0)
#27300000
b1000101000 2
b10001010 .
b10001010 5
b10001001 %
b10001001 '
1)
#27310000
b10001011 /
b10001011 4
#27400000
0)
#27500000
b10001010 '
b10001010 %
b1000101100 2
b10001011 .
b10001011 5
1)
#27510000
b10001100 /
b10001100 4
#27600000
0)
#27700000
b1000110000 2
b10001100 .
b10001100 5
b10001011 %
b10001011 '
1)
#27710000
b10001101 /
b10001101 4
#27800000
0)
#27900000
b10001100 '
b10001100 %
b1000110100 2
b10001101 .
b10001101 5
1)
#27910000
b10001110 /
b10001110 4
#28000000
0)
#28100000
b1000111000 2
b10001110 .
b10001110 5
b10001101 %
b10001101 '
1)
#28110000
b10001111 /
b10001111 4
#28200000
0)
#28300000
b10001110 '
b10001110 %
b1000111100 2
b10001111 .
b10001111 5
1)
#28310000
b10010000 /
b10010000 4
#28400000
0)
#28500000
b1001000000 2
b10010000 .
b10010000 5
b10001111 %
b10001111 '
1)
#28510000
b10010001 /
b10010001 4
#28600000
0)
#28700000
b10010000 '
b10010000 %
b1001000100 2
b10010001 .
b10010001 5
1)
#28710000
b10010010 /
b10010010 4
#28800000
0)
#28900000
b1001001000 2
b10010010 .
b10010010 5
b10010001 %
b10010001 '
1)
#28910000
b10010011 /
b10010011 4
#29000000
0)
#29100000
b10010010 '
b10010010 %
b1001001100 2
b10010011 .
b10010011 5
1)
#29110000
b10010100 /
b10010100 4
#29200000
0)
#29300000
b1001010000 2
b10010100 .
b10010100 5
b10010011 %
b10010011 '
1)
#29310000
b10010101 /
b10010101 4
#29400000
0)
#29500000
b10010100 '
b10010100 %
b1001010100 2
b10010101 .
b10010101 5
1)
#29510000
b10010110 /
b10010110 4
#29600000
0)
#29700000
b1001011000 2
b10010110 .
b10010110 5
b10010101 %
b10010101 '
1)
#29710000
b10010111 /
b10010111 4
#29800000
0)
#29900000
b10010110 '
b10010110 %
b1001011100 2
b10010111 .
b10010111 5
1)
#29910000
b10011000 /
b10011000 4
#30000000
0)
#30100000
b1001100000 2
b10011000 .
b10011000 5
b10010111 %
b10010111 '
1)
#30110000
b10011001 /
b10011001 4
#30200000
0)
#30300000
b10011000 '
b10011000 %
b1001100100 2
b10011001 .
b10011001 5
1)
#30310000
b10011010 /
b10011010 4
#30400000
0)
#30500000
b1001101000 2
b10011010 .
b10011010 5
b10011001 %
b10011001 '
1)
#30510000
b10011011 /
b10011011 4
#30600000
0)
#30700000
b10011010 '
b10011010 %
b1001101100 2
b10011011 .
b10011011 5
1)
#30710000
b10011100 /
b10011100 4
#30800000
0)
#30900000
b1001110000 2
b10011100 .
b10011100 5
b10011011 %
b10011011 '
1)
#30910000
b10011101 /
b10011101 4
#31000000
0)
#31100000
b10011100 '
b10011100 %
b1001110100 2
b10011101 .
b10011101 5
1)
#31110000
b10011110 /
b10011110 4
#31200000
0)
#31300000
b1001111000 2
b10011110 .
b10011110 5
b10011101 %
b10011101 '
1)
#31310000
b10011111 /
b10011111 4
#31400000
0)
#31500000
b10011110 '
b10011110 %
b1001111100 2
b10011111 .
b10011111 5
1)
#31510000
b10100000 /
b10100000 4
#31600000
0)
#31700000
b1010000000 2
b10100000 .
b10100000 5
b10011111 %
b10011111 '
1)
#31710000
b10100001 /
b10100001 4
#31800000
0)
#31900000
b10100000 '
b10100000 %
b1010000100 2
b10100001 .
b10100001 5
1)
#31910000
b10100010 /
b10100010 4
#32000000
0)
#32100000
b1010001000 2
b10100010 .
b10100010 5
b10100001 %
b10100001 '
1)
#32110000
b10100011 /
b10100011 4
#32200000
0)
#32300000
b10100010 '
b10100010 %
b1010001100 2
b10100011 .
b10100011 5
1)
#32310000
b10100100 /
b10100100 4
#32400000
0)
#32500000
b1010010000 2
b10100100 .
b10100100 5
b10100011 %
b10100011 '
1)
#32510000
b10100101 /
b10100101 4
#32600000
0)
#32700000
b10100100 '
b10100100 %
b1010010100 2
b10100101 .
b10100101 5
1)
#32710000
b10100110 /
b10100110 4
#32800000
0)
#32900000
b1010011000 2
b10100110 .
b10100110 5
b10100101 %
b10100101 '
1)
#32910000
b10100111 /
b10100111 4
#33000000
0)
#33100000
b10100110 '
b10100110 %
b1010011100 2
b10100111 .
b10100111 5
1)
#33110000
b10101000 /
b10101000 4
#33200000
0)
