PC/user/src/Extend16to30.v
module Extend16to30(
    input[15:0] in,
    output[29:0] out
);
    // 进行符号扩展
    assign out = {{14{in[15]}}, in};
endmodule

InsMEM/user/src/InsMEM.v
module InsMEM(
    input [31:0] InsAddr,
    output reg [31:0] InsData
    );

    reg [7:0] rom[511:0];

    initial begin
        $readmemh("/Users/yr/code/computer-organization/computer-organization-labs/InsMEM/user/data/Instruction.txt", rom);
    end
    // 大端方式
    always @(InsAddr) begin
        InsData[7:0] = rom[InsAddr+3];
        InsData[15:8] = rom[InsAddr+2];
        InsData[23:16] = rom[InsAddr+1];
        InsData[31:24] = rom[InsAddr];
    end

endmodule

PC/user/src/PC.v
module PC(
    input clk,
    input[29:0] nextAddr,
    output reg[29:0] curAddr
);
    // initial begin
    //     curAddr <= 0;
    // end
    always @(posedge clk) begin
        curAddr <= nextAddr;
    end
endmodule

PC/user/src/IFU.v
`include "/Users/yr/code/computer-organization/computer-organization-labs/PC/user/src/PC.v"
`include "/Users/yr/code/computer-organization/computer-organization-labs/InsMEM/user/src/InsMEM.v"
`include "/Users/yr/code/computer-organization/computer-organization-labs/PC/user/src/Extend16to30.v"
module IFU(
    input clk,
    input jump,
    input branch,
    input zero,
    output[31:0] instruction
);
    reg[31:2] nextAddr;
    wire[31:2] curAddr;
    wire[31:2] extend_imme;

    initial begin
        nextAddr <= 0;
    end

    PC pc(
        .clk(clk),
        .nextAddr(nextAddr),
        .curAddr(curAddr)
    );

    InsMEM insMem(
        .InsAddr({curAddr, 2'b00}),
        .InsData(instruction)
    );

    Extend16to30 extend16to30(
        .in(instruction[15:0]),
        .out(extend_imme)
    );

    always @(curAddr) begin
        if(jump)begin
            nextAddr <= {curAddr[31:28] + instruction[25:0]};
        end
        else if(branch && zero)begin
            nextAddr <= curAddr + 1 + extend_imme;
        end
        else begin
            nextAddr <= curAddr + 1;
        end
    end
endmodule

PC/user/sim/testbench.v
`include "/Users/yr/code/computer-organization/computer-organization-labs/PC/user/src/IFU.v"
`timescale 1ns/1ps;
module testbench();

parameter DATA_WIDTH = 32;
parameter ADDR_WIDTH = 32;
parameter MAIN_FRE   = 100; //unit MHz
reg                   sys_clk = 0;
reg                   sys_rst = 1;
reg [DATA_WIDTH-1:0]  data = 0;
reg [ADDR_WIDTH-1:0]  addr = 0;

always begin
    #(500/MAIN_FRE) sys_clk = ~sys_clk;
end

always begin
    #50 sys_rst = 0;
end

always @(posedge sys_clk) begin
    if (sys_rst)
        addr = 0;
    else
        addr = addr + 1;
end
always @(posedge sys_clk) begin
    if (sys_rst)
        data = 0;
    else
        data = data + 1;
end

//Instance
// outports wire
wire [31:0] 	instruction;
reg jump = 0;
reg branch = 0;
reg zero = 0;

IFU u_IFU(
	.clk         	( sys_clk          ),
	.jump        	( jump         ),
	.branch      	( branch       ),
	.zero        	( zero         ),
	.instruction 	( instruction  )
);



initial begin
    $dumpfile("wave.vcd");
    $dumpvars(0, testbench);
    #50000 $finish;
end

endmodule  //TOP

PC/user/sim/wave.vcd
$date
	Tue Dec 19 21:11:06 2023
$end
$version
	Icarus Verilog
$end
$timescale
	1ps
$end
$scope module testbench $end
$var wire 32 ! instruction [31:0] $end
$var parameter 32 " ADDR_WIDTH $end
$var parameter 32 # DATA_WIDTH $end
$var parameter 32 $ MAIN_FRE $end
$var reg 32 % addr [31:0] $end
$var reg 1 & branch $end
$var reg 32 ' data [31:0] $end
$var reg 1 ( jump $end
$var reg 1 ) sys_clk $end
$var reg 1 * sys_rst $end
$var reg 1 + zero $end
$scope module u_IFU $end
$var wire 1 & branch $end
$var wire 1 ) clk $end
$var wire 1 ( jump $end
$var wire 1 + zero $end
$var wire 32 , instruction [31:0] $end
$var wire 30 - extend_imme [31:2] $end
$var wire 30 . curAddr [31:2] $end
$var reg 30 / nextAddr [31:2] $end
$scope module extend16to30 $end
$var wire 16 0 in [15:0] $end
$var wire 30 1 out [29:0] $end
$upscope $end
$scope module insMem $end
$var wire 32 2 InsAddr [31:0] $end
$var reg 32 3 InsData [31:0] $end
$upscope $end
$scope module pc $end
$var wire 1 ) clk $end
$var wire 30 4 nextAddr [29:0] $end
$var reg 30 5 curAddr [29:0] $end
$upscope $end
$upscope $end
$upscope $end
$enddefinitions $end
$comment Show the parameter values. $end
$dumpall
b1100100 $
b100000 #
b100000 "
$end
#0
$dumpvars
bx 5
b0 4
bx 3
bx00 2
bx 1
bx 0
b0 /
bx .
bx -
bx ,
0+
1*
0)
0(
b0 '
0&
b0 %
bx !
$end
#50000
0*
#100000
b1 /
b1 4
b0 -
b0 1
b0 0
b10001100000001000000000000000000 !
b10001100000001000000000000000000 ,
b10001100000001000000000000000000 3
b0 2
b0 .
b0 5
b1 %
b1 '
1)
#200000
0)
#300000
b10 /
b10 4
b10001100000001010000000000000000 !
b10001100000001010000000000000000 ,
b10001100000001010000000000000000 3
b100 2
b1 .
b1 5
b10 '
b10 %
1)
#400000
0)
#500000
b11 /
b11 4
b10100000100000 -
b10100000100000 1
b10100000100000 0
b110001000010100000100000 !
b110001000010100000100000 ,
b110001000010100000100000 3
b1000 2
b10 .
b10 5
b11 %
b11 '
1)
#600000
0)
#700000
b100 /
b100 4
b100 -
b100 1
b100 0
b10101100000001100000000000000100 !
b10101100000001100000000000000100 ,
b10101100000001100000000000000100 3
b1100 2
b11 .
b11 5
b100 '
b100 %
1)
#800000
0)
#900000
b101 /
b101 4
bx -
bx 1
bx 0
bx !
bx ,
bx 3
b10000 2
b100 .
b100 5
b101 %
b101 '
1)
#1000000
0)
#1100000
b110 /
b110 4
b10100 2
b101 .
b101 5
b110 '
b110 %
1)
#1200000
0)
#1300000
b111 /
b111 4
b11000 2
b110 .
b110 5
b111 %
b111 '
1)
#1400000
0)
#1500000
b1000 /
b1000 4
b11100 2
b111 .
b111 5
b1000 '
b1000 %
1)
#1600000
0)
#1700000
b1001 /
b1001 4
b100000 2
b1000 .
b1000 5
b1001 %
b1001 '
1)
#1800000
0)
#1900000
b1010 /
b1010 4
b100100 2
b1001 .
b1001 5
b1010 '
b1010 %
1)
#2000000
0)
#2100000
b1011 /
b1011 4
b101000 2
b1010 .
b1010 5
b1011 %
b1011 '
1)
#2200000
0)
#2300000
b1100 /
b1100 4
b101100 2
b1011 .
b1011 5
b1100 '
b1100 %
1)
#2400000
0)
#2500000
b1101 /
b1101 4
b110000 2
b1100 .
b1100 5
b1101 %
b1101 '
1)
#2600000
0)
#2700000
b1110 /
b1110 4
b110100 2
b1101 .
b1101 5
b1110 '
b1110 %
1)
#2800000
0)
#2900000
b1111 /
b1111 4
b111000 2
b1110 .
b1110 5
b1111 %
b1111 '
1)
#3000000
0)
#3100000
b10000 /
b10000 4
b111100 2
b1111 .
b1111 5
b10000 '
b10000 %
1)
#3200000
0)
#3300000
b10001 /
b10001 4
b1000000 2
b10000 .
b10000 5
b10001 %
b10001 '
1)
#3400000
0)
#3500000
b10010 /
b10010 4
b1000100 2
b10001 .
b10001 5
b10010 '
b10010 %
1)
#3600000
0)
#3700000
b10011 /
b10011 4
b1001000 2
b10010 .
b10010 5
b10011 %
b10011 '
1)
#3800000
0)
#3900000
b10100 /
b10100 4
b1001100 2
b10011 .
b10011 5
b10100 '
b10100 %
1)
#4000000
0)
#4100000
b10101 /
b10101 4
b1010000 2
b10100 .
b10100 5
b10101 %
b10101 '
1)
#4200000
0)
#4300000
b10110 /
b10110 4
b1010100 2
b10101 .
b10101 5
b10110 '
b10110 %
1)
#4400000
0)
#4500000
b10111 /
b10111 4
b1011000 2
b10110 .
b10110 5
b10111 %
b10111 '
1)
#4600000
0)
#4700000
b11000 /
b11000 4
b1011100 2
b10111 .
b10111 5
b11000 '
b11000 %
1)
#4800000
0)
#4900000
b11001 /
b11001 4
b1100000 2
b11000 .
b11000 5
b11001 %
b11001 '
1)
#5000000
0)
#5100000
b11010 /
b11010 4
b1100100 2
b11001 .
b11001 5
b11010 '
b11010 %
1)
#5200000
0)
#5300000
b11011 /
b11011 4
b1101000 2
b11010 .
b11010 5
b11011 %
b11011 '
1)
#5400000
0)
#5500000
b11100 /
b11100 4
b1101100 2
b11011 .
b11011 5
b11100 '
b11100 %
1)
#5600000
0)
#5700000
b11101 /
b11101 4
b1110000 2
b11100 .
b11100 5
b11101 %
b11101 '
1)
#5800000
0)
#5900000
b11110 /
b11110 4
b1110100 2
b11101 .
b11101 5
b11110 '
b11110 %
1)
#6000000
0)
#6100000
b11111 /
b11111 4
b1111000 2
b11110 .
b11110 5
b11111 %
b11111 '
1)
#6200000
0)
#6300000
b100000 /
b100000 4
b1111100 2
b11111 .
b11111 5
b100000 '
b100000 %
1)
#6400000
0)
#6500000
b100001 /
b100001 4
b10000000 2
b100000 .
b100000 5
b100001 %
b100001 '
1)
#6600000
0)
#6700000
b100010 /
b100010 4
b10000100 2
b100001 .
b100001 5
b100010 '
b100010 %
1)
#6800000
0)
#6900000
b100011 /
b100011 4
b10001000 2
b100010 .
b100010 5
b100011 %
b100011 '
1)
#7000000
0)
#7100000
b100100 /
b100100 4
b10001100 2
b100011 .
b100011 5
b100100 '
b100100 %
1)
#7200000
0)
#7300000
b100101 /
b100101 4
b10010000 2
b100100 .
b100100 5
b100101 %
b100101 '
1)
#7400000
0)
#7500000
b100110 /
b100110 4
b10010100 2
b100101 .
b100101 5
b100110 '
b100110 %
1)
#7600000
0)
#7700000
b100111 /
b100111 4
b10011000 2
b100110 .
b100110 5
b100111 %
b100111 '
1)
#7800000
0)
#7900000
b101000 /
b101000 4
b10011100 2
b100111 .
b100111 5
b101000 '
b101000 %
1)
#8000000
0)
#8100000
b101001 /
b101001 4
b10100000 2
b101000 .
b101000 5
b101001 %
b101001 '
1)
#8200000
0)
#8300000
b101010 /
b101010 4
b10100100 2
b101001 .
b101001 5
b101010 '
b101010 %
1)
#8400000
0)
#8500000
b101011 /
b101011 4
b10101000 2
b101010 .
b101010 5
b101011 %
b101011 '
1)
#8600000
0)
#8700000
b101100 /
b101100 4
b10101100 2
b101011 .
b101011 5
b101100 '
b101100 %
1)
#8800000
0)
#8900000
b101101 /
b101101 4
b10110000 2
b101100 .
b101100 5
b101101 %
b101101 '
1)
#9000000
0)
#9100000
b101110 /
b101110 4
b10110100 2
b101101 .
b101101 5
b101110 '
b101110 %
1)
#9200000
0)
#9300000
b101111 /
b101111 4
b10111000 2
b101110 .
b101110 5
b101111 %
b101111 '
1)
#9400000
0)
#9500000
b110000 /
b110000 4
b10111100 2
b101111 .
b101111 5
b110000 '
b110000 %
1)
#9600000
0)
#9700000
b110001 /
b110001 4
b11000000 2
b110000 .
b110000 5
b110001 %
b110001 '
1)
#9800000
0)
#9900000
b110010 /
b110010 4
b11000100 2
b110001 .
b110001 5
b110010 '
b110010 %
1)
#10000000
0)
#10100000
b110011 /
b110011 4
b11001000 2
b110010 .
b110010 5
b110011 %
b110011 '
1)
#10200000
0)
#10300000
b110100 /
b110100 4
b11001100 2
b110011 .
b110011 5
b110100 '
b110100 %
1)
#10400000
0)
#10500000
b110101 /
b110101 4
b11010000 2
b110100 .
b110100 5
b110101 %
b110101 '
1)
#10600000
0)
#10700000
b110110 /
b110110 4
b11010100 2
b110101 .
b110101 5
b110110 '
b110110 %
1)
#10800000
0)
#10900000
b110111 /
b110111 4
b11011000 2
b110110 .
b110110 5
b110111 %
b110111 '
1)
#11000000
0)
#11100000
b111000 /
b111000 4
b11011100 2
b110111 .
b110111 5
b111000 '
b111000 %
1)
#11200000
0)
#11300000
b111001 /
b111001 4
b11100000 2
b111000 .
b111000 5
b111001 %
b111001 '
1)
#11400000
0)
#11500000
b111010 /
b111010 4
b11100100 2
b111001 .
b111001 5
b111010 '
b111010 %
1)
#11600000
0)
#11700000
b111011 /
b111011 4
b11101000 2
b111010 .
b111010 5
b111011 %
b111011 '
1)
#11800000
0)
#11900000
b111100 /
b111100 4
b11101100 2
b111011 .
b111011 5
b111100 '
b111100 %
1)
#12000000
0)
#12100000
b111101 /
b111101 4
b11110000 2
b111100 .
b111100 5
b111101 %
b111101 '
1)
#12200000
0)
#12300000
b111110 /
b111110 4
b11110100 2
b111101 .
b111101 5
b111110 '
b111110 %
1)
#12400000
0)
#12500000
b111111 /
b111111 4
b11111000 2
b111110 .
b111110 5
b111111 %
b111111 '
1)
#12600000
0)
#12700000
b1000000 /
b1000000 4
b11111100 2
b111111 .
b111111 5
b1000000 '
b1000000 %
1)
#12800000
0)
#12900000
b1000001 /
b1000001 4
b100000000 2
b1000000 .
b1000000 5
b1000001 %
b1000001 '
1)
#13000000
0)
#13100000
b1000010 /
b1000010 4
b100000100 2
b1000001 .
b1000001 5
b1000010 '
b1000010 %
1)
#13200000
0)
#13300000
b1000011 /
b1000011 4
b100001000 2
b1000010 .
b1000010 5
b1000011 %
b1000011 '
1)
#13400000
0)
#13500000
b1000100 /
b1000100 4
b100001100 2
b1000011 .
b1000011 5
b1000100 '
b1000100 %
1)
#13600000
0)
#13700000
b1000101 /
b1000101 4
b100010000 2
b1000100 .
b1000100 5
b1000101 %
b1000101 '
1)
#13800000
0)
#13900000
b1000110 /
b1000110 4
b100010100 2
b1000101 .
b1000101 5
b1000110 '
b1000110 %
1)
#14000000
0)
#14100000
b1000111 /
b1000111 4
b100011000 2
b1000110 .
b1000110 5
b1000111 %
b1000111 '
1)
#14200000
0)
#14300000
b1001000 /
b1001000 4
b100011100 2
b1000111 .
b1000111 5
b1001000 '
b1001000 %
1)
#14400000
0)
#14500000
b1001001 /
b1001001 4
b100100000 2
b1001000 .
b1001000 5
b1001001 %
b1001001 '
1)
#14600000
0)
#14700000
b1001010 /
b1001010 4
b100100100 2
b1001001 .
b1001001 5
b1001010 '
b1001010 %
1)
#14800000
0)
#14900000
b1001011 /
b1001011 4
b100101000 2
b1001010 .
b1001010 5
b1001011 %
b1001011 '
1)
#15000000
0)
#15100000
b1001100 /
b1001100 4
b100101100 2
b1001011 .
b1001011 5
b1001100 '
b1001100 %
1)
#15200000
0)
#15300000
b1001101 /
b1001101 4
b100110000 2
b1001100 .
b1001100 5
b1001101 %
b1001101 '
1)
#15400000
0)
#15500000
b1001110 /
b1001110 4
b100110100 2
b1001101 .
b1001101 5
b1001110 '
b1001110 %
1)
#15600000
0)
#15700000
b1001111 /
b1001111 4
b100111000 2
b1001110 .
b1001110 5
b1001111 %
b1001111 '
1)
#15800000
0)
#15900000
b1010000 /
b1010000 4
b100111100 2
b1001111 .
b1001111 5
b1010000 '
b1010000 %
1)
#16000000
0)
#16100000
b1010001 /
b1010001 4
b101000000 2
b1010000 .
b1010000 5
b1010001 %
b1010001 '
1)
#16200000
0)
#16300000
b1010010 /
b1010010 4
b101000100 2
b1010001 .
b1010001 5
b1010010 '
b1010010 %
1)
#16400000
0)
#16500000
b1010011 /
b1010011 4
b101001000 2
b1010010 .
b1010010 5
b1010011 %
b1010011 '
1)
#16600000
0)
#16700000
b1010100 /
b1010100 4
b101001100 2
b1010011 .
b1010011 5
b1010100 '
b1010100 %
1)
#16800000
0)
#16900000
b1010101 /
b1010101 4
b101010000 2
b1010100 .
b1010100 5
b1010101 %
b1010101 '
1)
#17000000
0)
#17100000
b1010110 /
b1010110 4
b101010100 2
b1010101 .
b1010101 5
b1010110 '
b1010110 %
1)
#17200000
0)
#17300000
b1010111 /
b1010111 4
b101011000 2
b1010110 .
b1010110 5
b1010111 %
b1010111 '
1)
#17400000
0)
#17500000
b1011000 /
b1011000 4
b101011100 2
b1010111 .
b1010111 5
b1011000 '
b1011000 %
1)
#17600000
0)
#17700000
b1011001 /
b1011001 4
b101100000 2
b1011000 .
b1011000 5
b1011001 %
b1011001 '
1)
#17800000
0)
#17900000
b1011010 /
b1011010 4
b101100100 2
b1011001 .
b1011001 5
b1011010 '
b1011010 %
1)
#18000000
0)
#18100000
b1011011 /
b1011011 4
b101101000 2
b1011010 .
b1011010 5
b1011011 %
b1011011 '
1)
#18200000
0)
#18300000
b1011100 /
b1011100 4
b101101100 2
b1011011 .
b1011011 5
b1011100 '
b1011100 %
1)
#18400000
0)
#18500000
b1011101 /
b1011101 4
b101110000 2
b1011100 .
b1011100 5
b1011101 %
b1011101 '
1)
#18600000
0)
#18700000
b1011110 /
b1011110 4
b101110100 2
b1011101 .
b1011101 5
b1011110 '
b1011110 %
1)
#18800000
0)
#18900000
b1011111 /
b1011111 4
b101111000 2
b1011110 .
b1011110 5
b1011111 %
b1011111 '
1)
#19000000
0)
#19100000
b1100000 /
b1100000 4
b101111100 2
b1011111 .
b1011111 5
b1100000 '
b1100000 %
1)
#19200000
0)
#19300000
b1100001 /
b1100001 4
b110000000 2
b1100000 .
b1100000 5
b1100001 %
b1100001 '
1)
#19400000
0)
#19500000
b1100010 /
b1100010 4
b110000100 2
b1100001 .
b1100001 5
b1100010 '
b1100010 %
1)
#19600000
0)
#19700000
b1100011 /
b1100011 4
b110001000 2
b1100010 .
b1100010 5
b1100011 %
b1100011 '
1)
#19800000
0)
#19900000
b1100100 /
b1100100 4
b110001100 2
b1100011 .
b1100011 5
b1100100 '
b1100100 %
1)
#20000000
0)
#20100000
b1100101 /
b1100101 4
b110010000 2
b1100100 .
b1100100 5
b1100101 %
b1100101 '
1)
#20200000
0)
#20300000
b1100110 /
b1100110 4
b110010100 2
b1100101 .
b1100101 5
b1100110 '
b1100110 %
1)
#20400000
0)
#20500000
b1100111 /
b1100111 4
b110011000 2
b1100110 .
b1100110 5
b1100111 %
b1100111 '
1)
#20600000
0)
#20700000
b1101000 /
b1101000 4
b110011100 2
b1100111 .
b1100111 5
b1101000 '
b1101000 %
1)
#20800000
0)
#20900000
b1101001 /
b1101001 4
b110100000 2
b1101000 .
b1101000 5
b1101001 %
b1101001 '
1)
#21000000
0)
#21100000
b1101010 /
b1101010 4
b110100100 2
b1101001 .
b1101001 5
b1101010 '
b1101010 %
1)
#21200000
0)
#21300000
b1101011 /
b1101011 4
b110101000 2
b1101010 .
b1101010 5
b1101011 %
b1101011 '
1)
#21400000
0)
#21500000
b1101100 /
b1101100 4
b110101100 2
b1101011 .
b1101011 5
b1101100 '
b1101100 %
1)
#21600000
0)
#21700000
b1101101 /
b1101101 4
b110110000 2
b1101100 .
b1101100 5
b1101101 %
b1101101 '
1)
#21800000
0)
#21900000
b1101110 /
b1101110 4
b110110100 2
b1101101 .
b1101101 5
b1101110 '
b1101110 %
1)
#22000000
0)
#22100000
b1101111 /
b1101111 4
b110111000 2
b1101110 .
b1101110 5
b1101111 %
b1101111 '
1)
#22200000
0)
#22300000
b1110000 /
b1110000 4
b110111100 2
b1101111 .
b1101111 5
b1110000 '
b1110000 %
1)
#22400000
0)
#22500000
b1110001 /
b1110001 4
b111000000 2
b1110000 .
b1110000 5
b1110001 %
b1110001 '
1)
#22600000
0)
#22700000
b1110010 /
b1110010 4
b111000100 2
b1110001 .
b1110001 5
b1110010 '
b1110010 %
1)
#22800000
0)
#22900000
b1110011 /
b1110011 4
b111001000 2
b1110010 .
b1110010 5
b1110011 %
b1110011 '
1)
#23000000
0)
#23100000
b1110100 /
b1110100 4
b111001100 2
b1110011 .
b1110011 5
b1110100 '
b1110100 %
1)
#23200000
0)
#23300000
b1110101 /
b1110101 4
b111010000 2
b1110100 .
b1110100 5
b1110101 %
b1110101 '
1)
#23400000
0)
#23500000
b1110110 /
b1110110 4
b111010100 2
b1110101 .
b1110101 5
b1110110 '
b1110110 %
1)
#23600000
0)
#23700000
b1110111 /
b1110111 4
b111011000 2
b1110110 .
b1110110 5
b1110111 %
b1110111 '
1)
#23800000
0)
#23900000
b1111000 /
b1111000 4
b111011100 2
b1110111 .
b1110111 5
b1111000 '
b1111000 %
1)
#24000000
0)
#24100000
b1111001 /
b1111001 4
b111100000 2
b1111000 .
b1111000 5
b1111001 %
b1111001 '
1)
#24200000
0)
#24300000
b1111010 /
b1111010 4
b111100100 2
b1111001 .
b1111001 5
b1111010 '
b1111010 %
1)
#24400000
0)
#24500000
b1111011 /
b1111011 4
b111101000 2
b1111010 .
b1111010 5
b1111011 %
b1111011 '
1)
#24600000
0)
#24700000
b1111100 /
b1111100 4
b111101100 2
b1111011 .
b1111011 5
b1111100 '
b1111100 %
1)
#24800000
0)
#24900000
b1111101 /
b1111101 4
b111110000 2
b1111100 .
b1111100 5
b1111101 %
b1111101 '
1)
#25000000
0)
#25100000
b1111110 /
b1111110 4
b111110100 2
b1111101 .
b1111101 5
b1111110 '
b1111110 %
1)
#25200000
0)
#25300000
b1111111 /
b1111111 4
b111111000 2
b1111110 .
b1111110 5
b1111111 %
b1111111 '
1)
#25400000
0)
#25500000
b10000000 /
b10000000 4
b111111100 2
b1111111 .
b1111111 5
b10000000 '
b10000000 %
1)
#25600000
0)
#25700000
b10000001 /
b10000001 4
b1000000000 2
b10000000 .
b10000000 5
b10000001 %
b10000001 '
1)
#25800000
0)
#25900000
b10000010 /
b10000010 4
b1000000100 2
b10000001 .
b10000001 5
b10000010 '
b10000010 %
1)
#26000000
0)
#26100000
b10000011 /
b10000011 4
b1000001000 2
b10000010 .
b10000010 5
b10000011 %
b10000011 '
1)
#26200000
0)
#26300000
b10000100 /
b10000100 4
b1000001100 2
b10000011 .
b10000011 5
b10000100 '
b10000100 %
1)
#26400000
0)
#26500000
b10000101 /
b10000101 4
b1000010000 2
b10000100 .
b10000100 5
b10000101 %
b10000101 '
1)
#26600000
0)
#26700000
b10000110 /
b10000110 4
b1000010100 2
b10000101 .
b10000101 5
b10000110 '
b10000110 %
1)
#26800000
0)
#26900000
b10000111 /
b10000111 4
b1000011000 2
b10000110 .
b10000110 5
b10000111 %
b10000111 '
1)
#27000000
0)
#27100000
b10001000 /
b10001000 4
b1000011100 2
b10000111 .
b10000111 5
b10001000 '
b10001000 %
1)
#27200000
0)
#27300000
b10001001 /
b10001001 4
b1000100000 2
b10001000 .
b10001000 5
b10001001 %
b10001001 '
1)
#27400000
0)
#27500000
b10001010 /
b10001010 4
b1000100100 2
b10001001 .
b10001001 5
b10001010 '
b10001010 %
1)
#27600000
0)
#27700000
b10001011 /
b10001011 4
b1000101000 2
b10001010 .
b10001010 5
b10001011 %
b10001011 '
1)
#27800000
0)
#27900000
b10001100 /
b10001100 4
b1000101100 2
b10001011 .
b10001011 5
b10001100 '
b10001100 %
1)
#28000000
0)
#28100000
b10001101 /
b10001101 4
b1000110000 2
b10001100 .
b10001100 5
b10001101 %
b10001101 '
1)
#28200000
0)
#28300000
b10001110 /
b10001110 4
b1000110100 2
b10001101 .
b10001101 5
b10001110 '
b10001110 %
1)
#28400000
0)
#28500000
b10001111 /
b10001111 4
b1000111000 2
b10001110 .
b10001110 5
b10001111 %
b10001111 '
1)
#28600000
0)
#28700000
b10010000 /
b10010000 4
b1000111100 2
b10001111 .
b10001111 5
b10010000 '
b10010000 %
1)
#28800000
0)
#28900000
b10010001 /
b10010001 4
b1001000000 2
b10010000 .
b10010000 5
b10010001 %
b10010001 '
1)
#29000000
0)
#29100000
b10010010 /
b10010010 4
b1001000100 2
b10010001 .
b10010001 5
b10010010 '
b10010010 %
1)
#29200000
0)
#29300000
b10010011 /
b10010011 4
b1001001000 2
b10010010 .
b10010010 5
b10010011 %
b10010011 '
1)
#29400000
0)
#29500000
b10010100 /
b10010100 4
b1001001100 2
b10010011 .
b10010011 5
b10010100 '
b10010100 %
1)
#29600000
0)
#29700000
b10010101 /
b10010101 4
b1001010000 2
b10010100 .
b10010100 5
b10010101 %
b10010101 '
1)
#29800000
0)
#29900000
b10010110 /
b10010110 4
b1001010100 2
b10010101 .
b10010101 5
b10010110 '
b10010110 %
1)
#30000000
0)
#30100000
b10010111 /
b10010111 4
b1001011000 2
b10010110 .
b10010110 5
b10010111 %
b10010111 '
1)
#30200000
0)
#30300000
b10011000 /
b10011000 4
b1001011100 2
b10010111 .
b10010111 5
b10011000 '
b10011000 %
1)
#30400000
0)
#30500000
b10011001 /
b10011001 4
b1001100000 2
b10011000 .
b10011000 5
b10011001 %
b10011001 '
1)
#30600000
0)
#30700000
b10011010 /
b10011010 4
b1001100100 2
b10011001 .
b10011001 5
b10011010 '
b10011010 %
1)
#30800000
0)
#30900000
b10011011 /
b10011011 4
b1001101000 2
b10011010 .
b10011010 5
b10011011 %
b10011011 '
1)
#31000000
0)
#31100000
b10011100 /
b10011100 4
b1001101100 2
b10011011 .
b10011011 5
b10011100 '
b10011100 %
1)
#31200000
0)
#31300000
b10011101 /
b10011101 4
b1001110000 2
b10011100 .
b10011100 5
b10011101 %
b10011101 '
1)
#31400000
0)
#31500000
b10011110 /
b10011110 4
b1001110100 2
b10011101 .
b10011101 5
b10011110 '
b10011110 %
1)
#31600000
0)
#31700000
b10011111 /
b10011111 4
b1001111000 2
b10011110 .
b10011110 5
b10011111 %
b10011111 '
1)
#31800000
0)
#31900000
b10100000 /
b10100000 4
b1001111100 2
b10011111 .
b10011111 5
b10100000 '
b10100000 %
1)
#32000000
0)
#32100000
b10100001 /
b10100001 4
b1010000000 2
b10100000 .
b10100000 5
b10100001 %
b10100001 '
1)
#32200000
0)
#32300000
b10100010 /
b10100010 4
b1010000100 2
b10100001 .
b10100001 5
b10100010 '
b10100010 %
1)
#32400000
0)
#32500000
b10100011 /
b10100011 4
b1010001000 2
b10100010 .
b10100010 5
b10100011 %
b10100011 '
1)
#32600000
0)
#32700000
b10100100 /
b10100100 4
b1010001100 2
b10100011 .
b10100011 5
b10100100 '
b10100100 %
1)
#32800000
0)
#32900000
b10100101 /
b10100101 4
b1010010000 2
b10100100 .
b10100100 5
b10100101 %
b10100101 '
1)
#33000000
0)
#33100000
b10100110 /
b10100110 4
b1010010100 2
b10100101 .
b10100101 5
b10100110 '
b10100110 %
1)
#33200000
0)
#33300000
b10100111 /
b10100111 4
b1010011000 2
b10100110 .
b10100110 5
b10100111 %
b10100111 '
1)
#33400000
0)
#33500000
b10101000 /
b10101000 4
b1010011100 2
b10100111 .
b10100111 5
b10101000 '
b10101000 %
1)
#33600000
0)
#33700000
b10101001 /
b10101001 4
b1010100000 2
b10101000 .
b10101000 5
b10101001 %
b10101001 '
1)
#33800000
0)
#33900000
b10101010 /
b10101010 4
b1010100100 2
b10101001 .
b10101001 5
b10101010 '
b10101010 %
1)
#34000000
0)
#34100000
b10101011 /
b10101011 4
b1010101000 2
b10101010 .
b10101010 5
b10101011 %
b10101011 '
1)
#34200000
0)
#34300000
b10101100 /
b10101100 4
b1010101100 2
b10101011 .
b10101011 5
b10101100 '
b10101100 %
1)
#34400000
0)
#34500000
b10101101 /
b10101101 4
b1010110000 2
b10101100 .
b10101100 5
b10101101 %
b10101101 '
1)
#34600000
0)
#34700000
b10101110 /
b10101110 4
b1010110100 2
b10101101 .
b10101101 5
b10101110 '
b10101110 %
1)
#34800000
0)
#34900000
b10101111 /
b10101111 4
b1010111000 2
b10101110 .
b10101110 5
b10101111 %
b10101111 '
1)
#35000000
0)
#35100000
b10110000 /
b10110000 4
b1010111100 2
b10101111 .
b10101111 5
b10110000 '
b10110000 %
1)
#35200000
0)
#35300000
b10110001 /
b10110001 4
b1011000000 2
b10110000 .
b10110000 5
b10110001 %
b10110001 '
1)
#35400000
0)
#35500000
b10110010 /
b10110010 4
b1011000100 2
b10110001 .
b10110001 5
b10110010 '
b10110010 %
1)
#35600000
0)
#35700000
b10110011 /
b10110011 4
b1011001000 2
b10110010 .
b10110010 5
b10110011 %
b10110011 '
1)
#35800000
0)
#35900000
b10110100 /
b10110100 4
b1011001100 2
b10110011 .
b10110011 5
b10110100 '
b10110100 %
1)
#36000000
0)
#36100000
b10110101 /
b10110101 4
b1011010000 2
b10110100 .
b10110100 5
b10110101 %
b10110101 '
1)
#36200000
0)
#36300000
b10110110 /
b10110110 4
b1011010100 2
b10110101 .
b10110101 5
b10110110 '
b10110110 %
1)
#36400000
0)
#36500000
b10110111 /
b10110111 4
b1011011000 2
b10110110 .
b10110110 5
b10110111 %
b10110111 '
1)
#36600000
0)
#36700000
b10111000 /
b10111000 4
b1011011100 2
b10110111 .
b10110111 5
b10111000 '
b10111000 %
1)
#36800000
0)
#36900000
b10111001 /
b10111001 4
b1011100000 2
b10111000 .
b10111000 5
b10111001 %
b10111001 '
1)
#37000000
0)
#37100000
b10111010 /
b10111010 4
b1011100100 2
b10111001 .
b10111001 5
b10111010 '
b10111010 %
1)
#37200000
0)
#37300000
b10111011 /
b10111011 4
b1011101000 2
b10111010 .
b10111010 5
b10111011 %
b10111011 '
1)
#37400000
0)
#37500000
b10111100 /
b10111100 4
b1011101100 2
b10111011 .
b10111011 5
b10111100 '
b10111100 %
1)
#37600000
0)
#37700000
b10111101 /
b10111101 4
b1011110000 2
b10111100 .
b10111100 5
b10111101 %
b10111101 '
1)
#37800000
0)
#37900000
b10111110 /
b10111110 4
b1011110100 2
b10111101 .
b10111101 5
b10111110 '
b10111110 %
1)
#38000000
0)
#38100000
b10111111 /
b10111111 4
b1011111000 2
b10111110 .
b10111110 5
b10111111 %
b10111111 '
1)
#38200000
0)
#38300000
b11000000 /
b11000000 4
b1011111100 2
b10111111 .
b10111111 5
b11000000 '
b11000000 %
1)
#38400000
0)
#38500000
b11000001 /
b11000001 4
b1100000000 2
b11000000 .
b11000000 5
b11000001 %
b11000001 '
1)
#38600000
0)
#38700000
b11000010 /
b11000010 4
b1100000100 2
b11000001 .
b11000001 5
b11000010 '
b11000010 %
1)
#38800000
0)
#38900000
b11000011 /
b11000011 4
b1100001000 2
b11000010 .
b11000010 5
b11000011 %
b11000011 '
1)
#39000000
0)
#39100000
b11000100 /
b11000100 4
b1100001100 2
b11000011 .
b11000011 5
b11000100 '
b11000100 %
1)
#39200000
0)
#39300000
b11000101 /
b11000101 4
b1100010000 2
b11000100 .
b11000100 5
b11000101 %
b11000101 '
1)
#39400000
0)
