PC/user/src/Extend16to30.v
module Extend16to30(
    input[15:0] in,
    output[29:0] out
);
    // 进行符号扩展
    assign out = {{14{in[15]}}, in};
endmodule

InsMEM/user/src/InsMEM.v
module InsMEM(
    input [31:0] InsAddr,
    output reg [31:0] InsData
    );

    reg [7:0] rom[511:0];

    initial begin
        $readmemh("/Users/yr/code/computer-organization/computer-organization-labs/InsMEM/user/data/Instruction.txt", rom);
        // $readmemh("/Users/yr/code/computer-organization/computer-organization-labs/InsMEM/user/data/fibInstruction.txt", rom);
    end
    // 大端方式
    always @(InsAddr) begin
        InsData[7:0] = rom[InsAddr+3];
        InsData[15:8] = rom[InsAddr+2];
        InsData[23:16] = rom[InsAddr+1];
        InsData[31:24] = rom[InsAddr];
    end

endmodule

PC/user/src/PC.v
module PC(
    input clk,
    input[29:0] nextAddr,
    output reg[29:0] curAddr
);
    initial begin
        curAddr <= 0;
    end
    always @(posedge clk) begin
        curAddr = nextAddr;
    end
endmodule

PC/user/src/IFU.v
`include "/Users/yr/code/computer-organization/computer-organization-labs/PC/user/src/PC.v"
`include "/Users/yr/code/computer-organization/computer-organization-labs/InsMEM/user/src/InsMEM.v"
`include "/Users/yr/code/computer-organization/computer-organization-labs/PC/user/src/Extend16to30.v"
module IFU(
    input clk,
    input jump,
    input branch,
    input zero,
    output[31:0] instruction
);
    reg[31:2] nextAddr;
    wire[31:2] curAddr;
    wire[31:2] extend_imme;

    PC pc(
        .clk(clk),
        .nextAddr(nextAddr),
        .curAddr(curAddr)
    );

    InsMEM insMem(
        .InsAddr({curAddr, 2'b00}),
        .InsData(instruction)
    );

    Extend16to30 extend16to30(
        .in(instruction[15:0]),
        .out(extend_imme)
    );

    always @(posedge clk) begin
        if(jump)begin
            nextAddr <= {curAddr[31:28] + instruction[25:0]};
        end
        else if(branch && zero)begin
            nextAddr <= curAddr + 1 + extend_imme;
        end
        else begin
            nextAddr <= curAddr + 1;
        end
    end
endmodule

PC/user/sim/testbench.v
`include "/Users/yr/code/computer-organization/computer-organization-labs/PC/user/src/IFU.v"
`timescale 1ns/1ps;
module testbench();

parameter DATA_WIDTH = 32;
parameter ADDR_WIDTH = 32;
parameter MAIN_FRE   = 100; //unit MHz
reg                   sys_clk = 0;
reg                   sys_rst = 1;
reg [DATA_WIDTH-1:0]  data = 0;
reg [ADDR_WIDTH-1:0]  addr = 0;

always begin
    #(500/MAIN_FRE) sys_clk = ~sys_clk;
end

always begin
    #50 sys_rst = 0;
end

always @(posedge sys_clk) begin
    if (sys_rst)
        addr = 0;
    else
        addr = addr + 1;
end
always @(posedge sys_clk) begin
    if (sys_rst)
        data = 0;
    else
        data = data + 1;
end

//Instance
// outports wire
wire [31:0] 	instruction;
reg jump = 0;
reg branch = 0;
reg zero = 0;

IFU u_IFU(
	.clk         	( sys_clk          ),
	.jump        	( jump         ),
	.branch      	( branch       ),
	.zero        	( zero         ),
	.instruction 	( instruction  )
);



initial begin
    $dumpfile("wave.vcd");
    $dumpvars(0, testbench);
    #50000 $finish;
end

endmodule  //TOP

PC/user/sim/wave.vcd
$date
	Tue Dec 19 10:51:03 2023
$end
$version
	Icarus Verilog
$end
$timescale
	1ps
$end
$scope module testbench $end
$var wire 32 ! instruction [31:0] $end
$var parameter 32 " ADDR_WIDTH $end
$var parameter 32 # DATA_WIDTH $end
$var parameter 32 $ MAIN_FRE $end
$var reg 32 % addr [31:0] $end
$var reg 1 & branch $end
$var reg 32 ' data [31:0] $end
$var reg 1 ( jump $end
$var reg 1 ) sys_clk $end
$var reg 1 * sys_rst $end
$var reg 1 + zero $end
$scope module u_IFU $end
$var wire 1 & branch $end
$var wire 1 ) clk $end
$var wire 1 ( jump $end
$var wire 1 + zero $end
$var wire 32 , instruction [31:0] $end
$var wire 30 - extend_imme [31:2] $end
$var wire 30 . curAddr [31:2] $end
$var reg 30 / nextAddr [31:2] $end
$scope module extend16to30 $end
$var wire 16 0 in [15:0] $end
$var wire 30 1 out [29:0] $end
$upscope $end
$scope module insMem $end
$var wire 32 2 InsAddr [31:0] $end
$var reg 32 3 InsData [31:0] $end
$upscope $end
$scope module pc $end
$var wire 1 ) clk $end
$var wire 30 4 nextAddr [29:0] $end
$var reg 30 5 curAddr [29:0] $end
$upscope $end
$upscope $end
$upscope $end
$enddefinitions $end
$comment Show the parameter values. $end
$dumpall
b1100100 $
b100000 #
b100000 "
$end
#0
$dumpvars
b0 5
bx 4
b10000001000000011 3
b0 2
b1000000011 1
b1000000011 0
bx /
b0 .
b1000000011 -
b10000001000000011 ,
0+
1*
0)
0(
b0 '
0&
b0 %
b10000001000000011 !
$end
#5000
b1 /
b1 4
bx -
bx 1
bx 0
bx !
bx ,
bx 3
bx00 2
bx .
bx 5
1)
#10000
0)
#15000
b10 /
b10 4
b11000000111 -
b11000000111 1
b11000000111 0
b100000001010000011000000111 !
b100000001010000011000000111 ,
b100000001010000011000000111 3
b100 2
b1 .
b1 5
1)
#20000
0)
#25000
b101000001011 -
b101000001011 1
b101000001011 0
b1000000010010000101000001011 !
b1000000010010000101000001011 ,
b1000000010010000101000001011 3
b1000 2
b10 .
b10 5
1)
#30000
0)
#35000
b11 /
b11 4
1)
#40000
0)
#45000
b111000001111 -
b111000001111 1
b111000001111 0
b1100000011010000111000001111 !
b1100000011010000111000001111 ,
b1100000011010000111000001111 3
b1100 2
b11 .
b11 5
1)
#50000
0)
0*
#55000
b100 /
b100 4
b1 '
b1 %
1)
#60000
0)
#65000
b1001000010011 -
b1001000010011 1
b1001000010011 0
b10000000100010001001000010011 !
b10000000100010001001000010011 ,
b10000000100010001001000010011 3
b10000 2
b100 .
b100 5
b10 %
b10 '
1)
#70000
0)
#75000
b101 /
b101 4
b11 '
b11 %
1)
#80000
0)
#85000
b1011000010111 -
b1011000010111 1
b1011000010111 0
b10100000101010001011000010111 !
b10100000101010001011000010111 ,
b10100000101010001011000010111 3
b10100 2
b101 .
b101 5
b100 %
b100 '
1)
#90000
0)
#95000
b110 /
b110 4
b101 '
b101 %
1)
#100000
0)
#105000
b1101000011011 -
b1101000011011 1
b1101000011011 0
b11000000110010001101000011011 !
b11000000110010001101000011011 ,
b11000000110010001101000011011 3
b11000 2
b110 .
b110 5
b110 %
b110 '
1)
#110000
0)
#115000
b111 /
b111 4
b111 '
b111 %
1)
#120000
0)
#125000
b1111000011111 -
b1111000011111 1
b1111000011111 0
b11100000111010001111000011111 !
b11100000111010001111000011111 ,
b11100000111010001111000011111 3
b11100 2
b111 .
b111 5
b1000 %
b1000 '
1)
#130000
0)
#135000
b1000 /
b1000 4
b1001 '
b1001 %
1)
#140000
0)
#145000
b1000000011 -
b1000000011 1
b1000000011 0
b10000001000000011 !
b10000001000000011 ,
b10000001000000011 3
b100000 2
b1000 .
b1000 5
b1010 %
b1010 '
1)
#150000
0)
#155000
b1001 /
b1001 4
b1011 '
b1011 %
1)
#160000
0)
#165000
b11000000111 -
b11000000111 1
b11000000111 0
b100000001010000011000000111 !
b100000001010000011000000111 ,
b100000001010000011000000111 3
b100100 2
b1001 .
b1001 5
b1100 %
b1100 '
1)
#170000
0)
#175000
b1010 /
b1010 4
b1101 '
b1101 %
1)
#180000
0)
#185000
b101000001011 -
b101000001011 1
b101000001011 0
b1000000010010000101000001011 !
b1000000010010000101000001011 ,
b1000000010010000101000001011 3
b101000 2
b1010 .
b1010 5
b1110 %
b1110 '
1)
#190000
0)
#195000
b1011 /
b1011 4
b1111 '
b1111 %
1)
#200000
0)
#205000
b111000001111 -
b111000001111 1
b111000001111 0
b1100000011010000111000001111 !
b1100000011010000111000001111 ,
b1100000011010000111000001111 3
b101100 2
b1011 .
b1011 5
b10000 %
b10000 '
1)
#210000
0)
#215000
b1100 /
b1100 4
b10001 '
b10001 %
1)
#220000
0)
#225000
b1001000010011 -
b1001000010011 1
b1001000010011 0
b10000000100010001001000010011 !
b10000000100010001001000010011 ,
b10000000100010001001000010011 3
b110000 2
b1100 .
b1100 5
b10010 %
b10010 '
1)
#230000
0)
#235000
b1101 /
b1101 4
b10011 '
b10011 %
1)
#240000
0)
#245000
b1011000010111 -
b1011000010111 1
b1011000010111 0
b10100000101010001011000010111 !
b10100000101010001011000010111 ,
b10100000101010001011000010111 3
b110100 2
b1101 .
b1101 5
b10100 %
b10100 '
1)
#250000
0)
#255000
b1110 /
b1110 4
b10101 '
b10101 %
1)
#260000
0)
#265000
b1101000011011 -
b1101000011011 1
b1101000011011 0
b11000000110010001101000011011 !
b11000000110010001101000011011 ,
b11000000110010001101000011011 3
b111000 2
b1110 .
b1110 5
b10110 %
b10110 '
1)
#270000
0)
#275000
b1111 /
b1111 4
b10111 '
b10111 %
1)
#280000
0)
#285000
b1111000011111 -
b1111000011111 1
b1111000011111 0
b11100000111010001111000011111 !
b11100000111010001111000011111 ,
b11100000111010001111000011111 3
b111100 2
b1111 .
b1111 5
b11000 %
b11000 '
1)
#290000
0)
#295000
b10000 /
b10000 4
b11001 '
b11001 %
1)
#300000
0)
#305000
b1000000011 -
b1000000011 1
b1000000011 0
b10000001000000011 !
b10000001000000011 ,
b10000001000000011 3
b1000000 2
b10000 .
b10000 5
b11010 %
b11010 '
1)
#310000
0)
#315000
b10001 /
b10001 4
b11011 '
b11011 %
1)
#320000
0)
#325000
b11000000111 -
b11000000111 1
b11000000111 0
b100000001010000011000000111 !
b100000001010000011000000111 ,
b100000001010000011000000111 3
b1000100 2
b10001 .
b10001 5
b11100 %
b11100 '
1)
#330000
0)
#335000
b10010 /
b10010 4
b11101 '
b11101 %
1)
#340000
0)
#345000
b101000001011 -
b101000001011 1
b101000001011 0
b1000000010010000101000001011 !
b1000000010010000101000001011 ,
b1000000010010000101000001011 3
b1001000 2
b10010 .
b10010 5
b11110 %
b11110 '
1)
#350000
0)
#355000
b10011 /
b10011 4
b11111 '
b11111 %
1)
#360000
0)
#365000
b111000001111 -
b111000001111 1
b111000001111 0
b1100000011010000111000001111 !
b1100000011010000111000001111 ,
b1100000011010000111000001111 3
b1001100 2
b10011 .
b10011 5
b100000 %
b100000 '
1)
#370000
0)
#375000
b10100 /
b10100 4
b100001 '
b100001 %
1)
#380000
0)
#385000
b1001000010011 -
b1001000010011 1
b1001000010011 0
b10000000100010001001000010011 !
b10000000100010001001000010011 ,
b10000000100010001001000010011 3
b1010000 2
b10100 .
b10100 5
b100010 %
b100010 '
1)
#390000
0)
#395000
b10101 /
b10101 4
b100011 '
b100011 %
1)
#400000
0)
#405000
b1011000010111 -
b1011000010111 1
b1011000010111 0
b10100000101010001011000010111 !
b10100000101010001011000010111 ,
b10100000101010001011000010111 3
b1010100 2
b10101 .
b10101 5
b100100 %
b100100 '
1)
#410000
0)
#415000
b10110 /
b10110 4
b100101 '
b100101 %
1)
#420000
0)
#425000
b1101000011011 -
b1101000011011 1
b1101000011011 0
b11000000110010001101000011011 !
b11000000110010001101000011011 ,
b11000000110010001101000011011 3
b1011000 2
b10110 .
b10110 5
b100110 %
b100110 '
1)
#430000
0)
#435000
b10111 /
b10111 4
b100111 '
b100111 %
1)
#440000
0)
#445000
b1111000011111 -
b1111000011111 1
b1111000011111 0
b11100000111010001111000011111 !
b11100000111010001111000011111 ,
b11100000111010001111000011111 3
b1011100 2
b10111 .
b10111 5
b101000 %
b101000 '
1)
#450000
0)
#455000
b11000 /
b11000 4
b101001 '
b101001 %
1)
#460000
0)
#465000
b1000000011 -
b1000000011 1
b1000000011 0
b10000001000000011 !
b10000001000000011 ,
b10000001000000011 3
b1100000 2
b11000 .
b11000 5
b101010 %
b101010 '
1)
#470000
0)
#475000
b11001 /
b11001 4
b101011 '
b101011 %
1)
#480000
0)
#485000
b11000000111 -
b11000000111 1
b11000000111 0
b100000001010000011000000111 !
b100000001010000011000000111 ,
b100000001010000011000000111 3
b1100100 2
b11001 .
b11001 5
b101100 %
b101100 '
1)
#490000
0)
#495000
b11010 /
b11010 4
b101101 '
b101101 %
1)
#500000
0)
#505000
b101000001011 -
b101000001011 1
b101000001011 0
b1000000010010000101000001011 !
b1000000010010000101000001011 ,
b1000000010010000101000001011 3
b1101000 2
b11010 .
b11010 5
b101110 %
b101110 '
1)
#510000
0)
#515000
b11011 /
b11011 4
b101111 '
b101111 %
1)
#520000
0)
#525000
b111000001111 -
b111000001111 1
b111000001111 0
b1100000011010000111000001111 !
b1100000011010000111000001111 ,
b1100000011010000111000001111 3
b1101100 2
b11011 .
b11011 5
b110000 %
b110000 '
1)
#530000
0)
#535000
b11100 /
b11100 4
b110001 '
b110001 %
1)
#540000
0)
#545000
b1001000010011 -
b1001000010011 1
b1001000010011 0
b10000000100010001001000010011 !
b10000000100010001001000010011 ,
b10000000100010001001000010011 3
b1110000 2
b11100 .
b11100 5
b110010 %
b110010 '
1)
#550000
0)
#555000
b11101 /
b11101 4
b110011 '
b110011 %
1)
#560000
0)
#565000
b1011000010111 -
b1011000010111 1
b1011000010111 0
b10100000101010001011000010111 !
b10100000101010001011000010111 ,
b10100000101010001011000010111 3
b1110100 2
b11101 .
b11101 5
b110100 %
b110100 '
1)
#570000
0)
#575000
b11110 /
b11110 4
b110101 '
b110101 %
1)
#580000
0)
#585000
b1101000011011 -
b1101000011011 1
b1101000011011 0
b11000000110010001101000011011 !
b11000000110010001101000011011 ,
b11000000110010001101000011011 3
b1111000 2
b11110 .
b11110 5
b110110 %
b110110 '
1)
#590000
0)
#595000
b11111 /
b11111 4
b110111 '
b110111 %
1)
#600000
0)
#605000
b1111000011111 -
b1111000011111 1
b1111000011111 0
b11100000111010001111000011111 !
b11100000111010001111000011111 ,
b11100000111010001111000011111 3
b1111100 2
b11111 .
b11111 5
b111000 %
b111000 '
1)
#610000
0)
#615000
b100000 /
b100000 4
b111001 '
b111001 %
1)
#620000
0)
#625000
bx -
bx 1
bx 0
bx !
bx ,
bx 3
b10000000 2
b100000 .
b100000 5
b111010 %
b111010 '
1)
#630000
0)
#635000
b100001 /
b100001 4
b111011 '
b111011 %
1)
#640000
0)
#645000
b10000100 2
b100001 .
b100001 5
b111100 %
b111100 '
1)
#650000
0)
#655000
b100010 /
b100010 4
b111101 '
b111101 %
1)
#660000
0)
#665000
b10001000 2
b100010 .
b100010 5
b111110 %
b111110 '
1)
#670000
0)
#675000
b100011 /
b100011 4
b111111 '
b111111 %
1)
#680000
0)
#685000
b10001100 2
b100011 .
b100011 5
b1000000 %
b1000000 '
1)
#690000
0)
#695000
b100100 /
b100100 4
b1000001 '
b1000001 %
1)
#700000
0)
#705000
b10010000 2
b100100 .
b100100 5
b1000010 %
b1000010 '
1)
#710000
0)
#715000
b100101 /
b100101 4
b1000011 '
b1000011 %
1)
#720000
0)
#725000
b10010100 2
b100101 .
b100101 5
b1000100 %
b1000100 '
1)
#730000
0)
#735000
b100110 /
b100110 4
b1000101 '
b1000101 %
1)
#740000
0)
#745000
b10011000 2
b100110 .
b100110 5
b1000110 %
b1000110 '
1)
#750000
0)
#755000
b100111 /
b100111 4
b1000111 '
b1000111 %
1)
#760000
0)
#765000
b10011100 2
b100111 .
b100111 5
b1001000 %
b1001000 '
1)
#770000
0)
#775000
b101000 /
b101000 4
b1001001 '
b1001001 %
1)
#780000
0)
#785000
b10100000 2
b101000 .
b101000 5
b1001010 %
b1001010 '
1)
#790000
0)
#795000
b101001 /
b101001 4
b1001011 '
b1001011 %
1)
#800000
0)
#805000
b10100100 2
b101001 .
b101001 5
b1001100 %
b1001100 '
1)
#810000
0)
#815000
b101010 /
b101010 4
b1001101 '
b1001101 %
1)
#820000
0)
#825000
b10101000 2
b101010 .
b101010 5
b1001110 %
b1001110 '
1)
#830000
0)
#835000
b101011 /
b101011 4
b1001111 '
b1001111 %
1)
#840000
0)
#845000
b10101100 2
b101011 .
b101011 5
b1010000 %
b1010000 '
1)
#850000
0)
#855000
b101100 /
b101100 4
b1010001 '
b1010001 %
1)
#860000
0)
#865000
b10110000 2
b101100 .
b101100 5
b1010010 %
b1010010 '
1)
#870000
0)
#875000
b101101 /
b101101 4
b1010011 '
b1010011 %
1)
#880000
0)
#885000
b10110100 2
b101101 .
b101101 5
b1010100 %
b1010100 '
1)
#890000
0)
#895000
b101110 /
b101110 4
b1010101 '
b1010101 %
1)
#900000
0)
#905000
b10111000 2
b101110 .
b101110 5
b1010110 %
b1010110 '
1)
#910000
0)
#915000
b101111 /
b101111 4
b1010111 '
b1010111 %
1)
#920000
0)
#925000
b10111100 2
b101111 .
b101111 5
b1011000 %
b1011000 '
1)
#930000
0)
#935000
b110000 /
b110000 4
b1011001 '
b1011001 %
1)
#940000
0)
#945000
b11000000 2
b110000 .
b110000 5
b1011010 %
b1011010 '
1)
#950000
0)
#955000
b110001 /
b110001 4
b1011011 '
b1011011 %
1)
#960000
0)
#965000
b11000100 2
b110001 .
b110001 5
b1011100 %
b1011100 '
1)
#970000
0)
#975000
b110010 /
b110010 4
b1011101 '
b1011101 %
1)
#980000
0)
#985000
b11001000 2
b110010 .
b110010 5
b1011110 %
b1011110 '
1)
#990000
0)
#995000
b110011 /
b110011 4
b1011111 '
b1011111 %
1)
#1000000
0)
#1005000
b11001100 2
b110011 .
b110011 5
b1100000 %
b1100000 '
1)
#1010000
0)
#1015000
b110100 /
b110100 4
b1100001 '
b1100001 %
1)
#1020000
0)
#1025000
b11010000 2
b110100 .
b110100 5
b1100010 %
b1100010 '
1)
#1030000
0)
#1035000
b110101 /
b110101 4
b1100011 '
b1100011 %
1)
#1040000
0)
#1045000
b11010100 2
b110101 .
b110101 5
b1100100 %
b1100100 '
1)
#1050000
0)
#1055000
b110110 /
b110110 4
b1100101 '
b1100101 %
1)
#1060000
0)
#1065000
b11011000 2
b110110 .
b110110 5
b1100110 %
b1100110 '
1)
#1070000
0)
#1075000
b110111 /
b110111 4
b1100111 '
b1100111 %
1)
#1080000
0)
#1085000
b11011100 2
b110111 .
b110111 5
b1101000 %
b1101000 '
1)
#1090000
0)
#1095000
b111000 /
b111000 4
b1101001 '
b1101001 %
1)
#1100000
0)
#1105000
b11100000 2
b111000 .
b111000 5
b1101010 %
b1101010 '
1)
#1110000
0)
#1115000
b111001 /
b111001 4
b1101011 '
b1101011 %
1)
#1120000
0)
#1125000
b11100100 2
b111001 .
b111001 5
b1101100 %
b1101100 '
1)
#1130000
0)
#1135000
b111010 /
b111010 4
b1101101 '
b1101101 %
1)
#1140000
0)
#1145000
b11101000 2
b111010 .
b111010 5
b1101110 %
b1101110 '
1)
#1150000
0)
#1155000
b111011 /
b111011 4
b1101111 '
b1101111 %
1)
#1160000
0)
#1165000
b11101100 2
b111011 .
b111011 5
b1110000 %
b1110000 '
1)
#1170000
0)
#1175000
b111100 /
b111100 4
b1110001 '
b1110001 %
1)
#1180000
0)
#1185000
b11110000 2
b111100 .
b111100 5
b1110010 %
b1110010 '
1)
#1190000
0)
#1195000
b111101 /
b111101 4
b1110011 '
b1110011 %
1)
#1200000
0)
#1205000
b11110100 2
b111101 .
b111101 5
b1110100 %
b1110100 '
1)
#1210000
0)
#1215000
b111110 /
b111110 4
b1110101 '
b1110101 %
1)
#1220000
0)
#1225000
b11111000 2
b111110 .
b111110 5
b1110110 %
b1110110 '
1)
#1230000
0)
#1235000
b111111 /
b111111 4
b1110111 '
b1110111 %
1)
#1240000
0)
#1245000
b11111100 2
b111111 .
b111111 5
b1111000 %
b1111000 '
1)
#1250000
0)
#1255000
b1000000 /
b1000000 4
b1111001 '
b1111001 %
1)
#1260000
0)
#1265000
b100000000 2
b1000000 .
b1000000 5
b1111010 %
b1111010 '
1)
#1270000
0)
#1275000
b1000001 /
b1000001 4
b1111011 '
b1111011 %
1)
#1280000
0)
#1285000
b100000100 2
b1000001 .
b1000001 5
b1111100 %
b1111100 '
1)
#1290000
0)
#1295000
b1000010 /
b1000010 4
b1111101 '
b1111101 %
1)
#1300000
0)
#1305000
b100001000 2
b1000010 .
b1000010 5
b1111110 %
b1111110 '
1)
#1310000
0)
#1315000
b1000011 /
b1000011 4
b1111111 '
b1111111 %
1)
#1320000
0)
#1325000
b100001100 2
b1000011 .
b1000011 5
b10000000 %
b10000000 '
1)
#1330000
0)
#1335000
b1000100 /
b1000100 4
b10000001 '
b10000001 %
1)
#1340000
0)
#1345000
b100010000 2
b1000100 .
b1000100 5
b10000010 %
b10000010 '
1)
#1350000
0)
#1355000
b1000101 /
b1000101 4
b10000011 '
b10000011 %
1)
#1360000
0)
#1365000
b100010100 2
b1000101 .
b1000101 5
b10000100 %
b10000100 '
1)
#1370000
0)
#1375000
b1000110 /
b1000110 4
b10000101 '
b10000101 %
1)
#1380000
0)
#1385000
b100011000 2
b1000110 .
b1000110 5
b10000110 %
b10000110 '
1)
#1390000
0)
#1395000
b1000111 /
b1000111 4
b10000111 '
b10000111 %
1)
#1400000
0)
#1405000
b100011100 2
b1000111 .
b1000111 5
b10001000 %
b10001000 '
1)
#1410000
0)
#1415000
b1001000 /
b1001000 4
b10001001 '
b10001001 %
1)
#1420000
0)
#1425000
b100100000 2
b1001000 .
b1001000 5
b10001010 %
b10001010 '
1)
#1430000
0)
#1435000
b1001001 /
b1001001 4
b10001011 '
b10001011 %
1)
#1440000
0)
#1445000
b100100100 2
b1001001 .
b1001001 5
b10001100 %
b10001100 '
1)
#1450000
0)
#1455000
b1001010 /
b1001010 4
b10001101 '
b10001101 %
1)
#1460000
0)
#1465000
b100101000 2
b1001010 .
b1001010 5
b10001110 %
b10001110 '
1)
#1470000
0)
#1475000
b1001011 /
b1001011 4
b10001111 '
b10001111 %
1)
#1480000
0)
#1485000
b100101100 2
b1001011 .
b1001011 5
b10010000 %
b10010000 '
1)
#1490000
0)
#1495000
b1001100 /
b1001100 4
b10010001 '
b10010001 %
1)
#1500000
0)
#1505000
b100110000 2
b1001100 .
b1001100 5
b10010010 %
b10010010 '
1)
#1510000
0)
#1515000
b1001101 /
b1001101 4
b10010011 '
b10010011 %
1)
#1520000
0)
#1525000
b100110100 2
b1001101 .
b1001101 5
b10010100 %
b10010100 '
1)
#1530000
0)
#1535000
b1001110 /
b1001110 4
b10010101 '
b10010101 %
1)
#1540000
0)
#1545000
b100111000 2
b1001110 .
b1001110 5
b10010110 %
b10010110 '
1)
#1550000
0)
#1555000
b1001111 /
b1001111 4
b10010111 '
b10010111 %
1)
#1560000
0)
#1565000
b100111100 2
b1001111 .
b1001111 5
b10011000 %
b10011000 '
1)
#1570000
0)
#1575000
b1010000 /
b1010000 4
b10011001 '
b10011001 %
1)
#1580000
0)
#1585000
b101000000 2
b1010000 .
b1010000 5
b10011010 %
b10011010 '
1)
#1590000
0)
#1595000
b1010001 /
b1010001 4
b10011011 '
b10011011 %
1)
#1600000
0)
#1605000
b101000100 2
b1010001 .
b1010001 5
b10011100 %
b10011100 '
1)
#1610000
0)
#1615000
b1010010 /
b1010010 4
b10011101 '
b10011101 %
1)
#1620000
0)
#1625000
b101001000 2
b1010010 .
b1010010 5
b10011110 %
b10011110 '
1)
#1630000
0)
#1635000
b1010011 /
b1010011 4
b10011111 '
b10011111 %
1)
#1640000
0)
#1645000
b101001100 2
b1010011 .
b1010011 5
b10100000 %
b10100000 '
1)
#1650000
0)
#1655000
b1010100 /
b1010100 4
b10100001 '
b10100001 %
1)
#1660000
0)
#1665000
b101010000 2
b1010100 .
b1010100 5
b10100010 %
b10100010 '
1)
#1670000
0)
#1675000
b1010101 /
b1010101 4
b10100011 '
b10100011 %
1)
#1680000
0)
#1685000
b101010100 2
b1010101 .
b1010101 5
b10100100 %
b10100100 '
1)
#1690000
0)
#1695000
b1010110 /
b1010110 4
b10100101 '
b10100101 %
1)
#1700000
0)
#1705000
b101011000 2
b1010110 .
b1010110 5
b10100110 %
b10100110 '
1)
#1710000
0)
#1715000
b1010111 /
b1010111 4
b10100111 '
b10100111 %
1)
#1720000
0)
#1725000
b101011100 2
b1010111 .
b1010111 5
b10101000 %
b10101000 '
1)
#1730000
0)
#1735000
b1011000 /
b1011000 4
b10101001 '
b10101001 %
1)
#1740000
0)
#1745000
b101100000 2
b1011000 .
b1011000 5
b10101010 %
b10101010 '
1)
#1750000
0)
#1755000
b1011001 /
b1011001 4
b10101011 '
b10101011 %
1)
#1760000
0)
#1765000
b101100100 2
b1011001 .
b1011001 5
b10101100 %
b10101100 '
1)
#1770000
0)
#1775000
b1011010 /
b1011010 4
b10101101 '
b10101101 %
1)
#1780000
0)
#1785000
b101101000 2
b1011010 .
b1011010 5
b10101110 %
b10101110 '
1)
#1790000
0)
#1795000
b1011011 /
b1011011 4
b10101111 '
b10101111 %
1)
#1800000
0)
#1805000
b101101100 2
b1011011 .
b1011011 5
b10110000 %
b10110000 '
1)
#1810000
0)
#1815000
b1011100 /
b1011100 4
b10110001 '
b10110001 %
1)
#1820000
0)
#1825000
b101110000 2
b1011100 .
b1011100 5
b10110010 %
b10110010 '
1)
#1830000
0)
#1835000
b1011101 /
b1011101 4
b10110011 '
b10110011 %
1)
#1840000
0)
#1845000
b101110100 2
b1011101 .
b1011101 5
b10110100 %
b10110100 '
1)
#1850000
0)
#1855000
b1011110 /
b1011110 4
b10110101 '
b10110101 %
1)
#1860000
0)
#1865000
b101111000 2
b1011110 .
b1011110 5
b10110110 %
b10110110 '
1)
#1870000
0)
#1875000
b1011111 /
b1011111 4
b10110111 '
b10110111 %
1)
#1880000
0)
#1885000
b101111100 2
b1011111 .
b1011111 5
b10111000 %
b10111000 '
1)
#1890000
0)
#1895000
b1100000 /
b1100000 4
b10111001 '
b10111001 %
1)
#1900000
0)
#1905000
b110000000 2
b1100000 .
b1100000 5
b10111010 %
b10111010 '
1)
#1910000
0)
#1915000
b1100001 /
b1100001 4
b10111011 '
b10111011 %
1)
#1920000
0)
#1925000
b110000100 2
b1100001 .
b1100001 5
b10111100 %
b10111100 '
1)
#1930000
0)
#1935000
b1100010 /
b1100010 4
b10111101 '
b10111101 %
1)
#1940000
0)
#1945000
b110001000 2
b1100010 .
b1100010 5
b10111110 %
b10111110 '
1)
#1950000
0)
#1955000
b1100011 /
b1100011 4
b10111111 '
b10111111 %
1)
#1960000
0)
#1965000
b110001100 2
b1100011 .
b1100011 5
b11000000 %
b11000000 '
1)
#1970000
0)
#1975000
b1100100 /
b1100100 4
b11000001 '
b11000001 %
1)
#1980000
0)
#1985000
b110010000 2
b1100100 .
b1100100 5
b11000010 %
b11000010 '
1)
#1990000
0)
#1995000
b1100101 /
b1100101 4
b11000011 '
b11000011 %
1)
#2000000
0)
#2005000
b110010100 2
b1100101 .
b1100101 5
b11000100 %
b11000100 '
1)
#2010000
0)
#2015000
b1100110 /
b1100110 4
b11000101 '
b11000101 %
1)
#2020000
0)
#2025000
b110011000 2
b1100110 .
b1100110 5
b11000110 %
b11000110 '
1)
#2030000
0)
#2035000
b1100111 /
b1100111 4
b11000111 '
b11000111 %
1)
#2040000
0)
#2045000
b110011100 2
b1100111 .
b1100111 5
b11001000 %
b11001000 '
1)
#2050000
0)
#2055000
b1101000 /
b1101000 4
b11001001 '
b11001001 %
1)
#2060000
0)
#2065000
b110100000 2
b1101000 .
b1101000 5
b11001010 %
b11001010 '
1)
#2070000
0)
#2075000
b1101001 /
b1101001 4
b11001011 '
b11001011 %
1)
#2080000
0)
#2085000
b110100100 2
b1101001 .
b1101001 5
b11001100 %
b11001100 '
1)
#2090000
0)
#2095000
b1101010 /
b1101010 4
b11001101 '
b11001101 %
1)
#2100000
0)
#2105000
b110101000 2
b1101010 .
b1101010 5
b11001110 %
b11001110 '
1)
#2110000
0)
#2115000
b1101011 /
b1101011 4
b11001111 '
b11001111 %
1)
#2120000
0)
#2125000
b110101100 2
b1101011 .
b1101011 5
b11010000 %
b11010000 '
1)
#2130000
0)
#2135000
b1101100 /
b1101100 4
b11010001 '
b11010001 %
1)
#2140000
0)
#2145000
b110110000 2
b1101100 .
b1101100 5
b11010010 %
b11010010 '
1)
#2150000
0)
#2155000
b1101101 /
b1101101 4
b11010011 '
b11010011 %
1)
#2160000
0)
#2165000
b110110100 2
b1101101 .
b1101101 5
b11010100 %
b11010100 '
1)
#2170000
0)
#2175000
b1101110 /
b1101110 4
b11010101 '
b11010101 %
1)
#2180000
0)
#2185000
b110111000 2
b1101110 .
b1101110 5
b11010110 %
b11010110 '
1)
#2190000
0)
#2195000
b1101111 /
b1101111 4
b11010111 '
b11010111 %
1)
#2200000
0)
#2205000
b110111100 2
b1101111 .
b1101111 5
b11011000 %
b11011000 '
1)
#2210000
0)
#2215000
b1110000 /
b1110000 4
b11011001 '
b11011001 %
1)
#2220000
0)
#2225000
b111000000 2
b1110000 .
b1110000 5
b11011010 %
b11011010 '
1)
#2230000
0)
#2235000
b1110001 /
b1110001 4
b11011011 '
b11011011 %
1)
#2240000
0)
#2245000
b111000100 2
b1110001 .
b1110001 5
b11011100 %
b11011100 '
1)
#2250000
0)
#2255000
b1110010 /
b1110010 4
b11011101 '
b11011101 %
1)
#2260000
0)
#2265000
b111001000 2
b1110010 .
b1110010 5
b11011110 %
b11011110 '
1)
#2270000
0)
#2275000
b1110011 /
b1110011 4
b11011111 '
b11011111 %
1)
#2280000
0)
#2285000
b111001100 2
b1110011 .
b1110011 5
b11100000 %
b11100000 '
1)
#2290000
0)
#2295000
b1110100 /
b1110100 4
b11100001 '
b11100001 %
1)
#2300000
0)
#2305000
b111010000 2
b1110100 .
b1110100 5
b11100010 %
b11100010 '
1)
#2310000
0)
#2315000
b1110101 /
b1110101 4
b11100011 '
b11100011 %
1)
#2320000
0)
#2325000
b111010100 2
b1110101 .
b1110101 5
b11100100 %
b11100100 '
1)
#2330000
0)
#2335000
b1110110 /
b1110110 4
b11100101 '
b11100101 %
1)
#2340000
0)
#2345000
b111011000 2
b1110110 .
b1110110 5
b11100110 %
b11100110 '
1)
#2350000
0)
#2355000
b1110111 /
b1110111 4
b11100111 '
b11100111 %
1)
#2360000
0)
