REGS/user/src/Reg.v
// 定义一个名为Reg的模块，该模块模拟了一个寄存器组
module Reg(Ra, Rb, Rw, RegWr, busW, Clock, busA, busB);

// 定义一个参数n，表示数据总线的宽度
parameter n = 32;

// 定义三个5位宽的输入线，分别是两个寄存器地址和一个寄存器值
input wire[4:0] Ra, Rb, Rw;

// 定义两个输入线，分别是写入使能信号和时钟信号
input wire RegWr, Clock;

// 定义一个32位宽的输入数据总线
input wire[n-1:0] busW;

// 定义两个32位宽的输出数据总线
output reg[n-1:0] busA, busB;

// 定义一个32个元素的寄存器数组，每个元素是一个4位宽的寄存器
reg [4:0] mem [0:31];

// 在仿真开始时，将寄存器数组的前四个元素初始化为11
initial
    begin
        mem[0] <= 32'ha;
        mem[1] <= 32'hb;
        mem[2] <= 32'hc;
        mem[3] <= 32'hd;
    end

// 在时钟信号的下降沿，如果Rw为1，则将输入数据总线的值写入到寄存器数组的Rw位置
always @ (negedge Clock)
    begin
        if (RegWr == 1)
            mem[Rw] <= busW;
    end

// 当Ra或Rb的值发生变化时，将对应的寄存器值输出到数据总线
always @ (Ra or Rb)
    begin
        busA <= mem[Ra];
        busB <= mem[Rb];
    end
endmodule

REGS/user/sim/testbench.v
`include "/Users/yr/code/computer-organization/computer-organization-labs/REGS/user/src/Reg.v"
`timescale 1us/1ns

module testbench;
parameter DATA_WIDTH = 32;
parameter ADDR_WIDTH = 32;
parameter MAIN_FRE   = 100; //unit MHz
reg                   sys_clk = 0;
reg                   sys_rst = 1;
reg [DATA_WIDTH-1:0]  data = 0;
reg [ADDR_WIDTH-1:0]  addr = 0;


// 10us一个周期
always begin
    #(500/MAIN_FRE) sys_clk = ~sys_clk;
end

always begin
    #50 sys_rst = 0;
end

always @(posedge sys_clk) begin
    if (sys_rst)
        addr = 0;
    else
        addr = addr + 1;
end
always @(posedge sys_clk) begin
    if (sys_rst)
        data = 0;
    else
        data = data + 1;
end

//Instance
// outports wire
wire [31:0] 	busA;
wire [31:0] 	busB;

reg [4:0] Ra;
reg [4:0] Rb;
reg [4:0] Rw;
reg RegWr;
reg [31:0] busW;
reg Clock = 0;


Reg u_Reg(
	.Ra    	( Ra     ),
	.Rb    	( Rb     ),
	.Rw    	( Rw     ),
	.RegWr 	( RegWr  ),
	.Clock 	( sys_clk),
	.busW  	( busW   ),
	.busA  	( busA   ),
	.busB  	( busB   )
);


integer i;
integer x = 0;
initial begin
    $dumpfile("wave.vcd");
    $dumpvars(0, testbench);
    // 局部测试
    #5             // 休眠半个周期
    RegWr = 0;
    Ra = 0;
    Rb = 1;
    #10
    Ra = 2;
    Rb = 3;
    #10
    Ra = 4;
    Rb = 5;
    #10
    Rw = 0;
    RegWr = 1;
    busW = 32'h1;
    #10
    Rw = 1;
    busW = 32'h2;
    #10
    Rw = 2;
    busW = 32'h3;
    #10
    Rw = 3;
    busW = 32'h4;
    #10
    Rw = 4;
    busW = 32'h5;
    #10
    Rw = 5;
    busW = 32'h6;
    #10
    RegWr = 0;
    Ra = 0;
    Rb = 1;
    #10
    Ra = 2;
    Rb = 3;
    #10
    Ra = 4;
    Rb = 5;

    Rw = 0;
    #10

    // 0-31号寄存器全部测试
    // 向0-31号寄存器写入0-31
    RegWr = 1;
    for (i=0; i < 32; i=i+1) begin
        Rw = i;
        busW = x;
        x = x + 1;
        #10;
    end
    // 将我们向0-32号寄存器写入的数据读出来
    RegWr = 0;
    for(i = 0; i < 32; i = i + 2)begin
        Ra = i;
        Rb = i+1;
        #10;
    end

    #500 $finish;
end

endmodule  //TOP


// // 导入被测试的寄存器组模块
// `include "/Users/yr/code/computer-organization/computer-organization-labs/REGS/user/src/Reg.v"

// // 定义一个模块，用于测试寄存器组模块
// module Reg_tb;

// // 定义一个时钟信号
// reg Clock;

// // 定义一个寄存器地址信号
// reg [4:0] Ra, Rb, Rw;

// // 定义一个写入使能信号
// reg RegWr;

// // 定义一个输入数据总线
// reg [31:0] busW;

// // 定义一个输出数据总线
// wire [31:0] busA, busB;

// // 实例化被测试的寄存器组模块
// Reg UUT (.Ra(Ra), .Rb(Rb), .Rw(Rw), .RegWr(RegWr), .busW(busW), .Clock(Clock), .busA(busA), .busB(busB));

// // 初始化信号
// initial
// begin
//     // 初始化时钟信号
//     Clock = 0;

//     // 初始化寄存器地址信号
//     Ra = 0;
//     Rb = 0;
//     Rw = 0;

//     // 初始化写入使能信号
//     RegWr = 0;

//     // 初始化输入数据总线
//     busW = 0;

//     // 打印测试开始信息
//     // $display("Test started");

//     // 模拟时钟信号

// end

// always begin
//     Clock = ~Clock;
//     #1;
// end

// // 在时钟信号的上升沿，进行测试
// always @(posedge Clock)
// begin
//     $dumpfile("wave.vcd");
//     $dumpvars(0, Reg_tb);
//     // 设置寄存器地址信号
//     Ra = 1;
//     Rb = 2;
//     Rw = 3;

//     // 设置写入使能信号
//     RegWr = 1;

//     // 设置输入数据总线的值
//     busW = 55;

//     // 等待一个时钟周期
//     #10;

//     // 打印寄存器组的输出结果
//     $display("busA = %d, busB = %d", busA, busB);

//     // 设置寄存器地址信号
//     Ra = 2;
//     Rb = 3;
//     Rw = 4;

//     // 设置写入使能信号
//     RegWr = 0;

//     // 设置输入数据总线的值
//     busW = 0;

//     // 等待一个时钟周期
//     #10;

//     // 打印寄存器组的输出结果
//     $display("busA = %d, busB = %d", busA, busB);

//     // 结束仿真
//     $finish;
// end

// endmodule

REGS/user/sim/wave.vcd
$date
	Wed Nov 22 16:22:31 2023
$end
$version
	Icarus Verilog
$end
$timescale
	1ns
$end
$scope module testbench $end
$var wire 32 ! busB [31:0] $end
$var wire 32 " busA [31:0] $end
$var parameter 32 # ADDR_WIDTH $end
$var parameter 32 $ DATA_WIDTH $end
$var parameter 32 % MAIN_FRE $end
$var reg 1 & Clock $end
$var reg 5 ' Ra [4:0] $end
$var reg 5 ( Rb [4:0] $end
$var reg 1 ) RegWr $end
$var reg 5 * Rw [4:0] $end
$var reg 32 + addr [31:0] $end
$var reg 32 , busW [31:0] $end
$var reg 32 - data [31:0] $end
$var reg 1 . sys_clk $end
$var reg 1 / sys_rst $end
$var integer 32 0 i [31:0] $end
$var integer 32 1 x [31:0] $end
$scope module u_Reg $end
$var wire 1 . Clock $end
$var wire 5 2 Ra [4:0] $end
$var wire 5 3 Rb [4:0] $end
$var wire 1 ) RegWr $end
$var wire 5 4 Rw [4:0] $end
$var wire 32 5 busW [31:0] $end
$var parameter 32 6 n $end
$var reg 32 7 busA [31:0] $end
$var reg 32 8 busB [31:0] $end
$upscope $end
$upscope $end
$enddefinitions $end
$comment Show the parameter values. $end
$dumpall
b100000 6
b1100100 %
b100000 $
b100000 #
$end
#0
$dumpvars
bx 8
bx 7
bx 5
bx 4
bx 3
bx 2
b0 1
bx 0
1/
0.
b0 -
bx ,
b0 +
bx *
x)
bx (
bx '
0&
bx "
bx !
$end
#5000
b1011 !
b1011 8
b1010 "
b1010 7
b1 (
b1 3
b0 '
b0 2
0)
1.
#10000
0.
#15000
b1101 !
b1101 8
b1100 "
b1100 7
1.
b11 (
b11 3
b10 '
b10 2
#20000
0.
#25000
b0xxxxx !
b0xxxxx 8
b0xxxxx "
b0xxxxx 7
1.
b101 (
b101 3
b100 '
b100 2
#30000
0.
#35000
1.
b1 ,
b1 5
1)
b0 *
b0 4
#40000
0.
#45000
1.
b10 ,
b10 5
b1 *
b1 4
#50000
0.
0/
#55000
b1 -
b1 +
1.
b11 ,
b11 5
b10 *
b10 4
#60000
0.
#65000
b10 +
b10 -
1.
b100 ,
b100 5
b11 *
b11 4
#70000
0.
#75000
b11 -
b11 +
1.
b101 ,
b101 5
b100 *
b100 4
#80000
0.
#85000
b100 +
b100 -
1.
b110 ,
b110 5
b101 *
b101 4
#90000
0.
#95000
b10 !
b10 8
b1 "
b1 7
b101 -
b101 +
1.
b1 (
b1 3
b0 '
b0 2
0)
#100000
0.
#105000
b100 !
b100 8
b11 "
b11 7
b110 +
b110 -
1.
b11 (
b11 3
b10 '
b10 2
#110000
0.
#115000
b110 !
b110 8
b101 "
b101 7
b111 -
b111 +
1.
b0 *
b0 4
b101 (
b101 3
b100 '
b100 2
#120000
0.
#125000
b1000 +
b1000 -
1.
b1 1
b0 ,
b0 5
b0 0
1)
#130000
0.
#135000
b1001 -
b1001 +
1.
b10 1
b1 ,
b1 5
b1 *
b1 4
b1 0
#140000
0.
#145000
b1010 +
b1010 -
1.
b11 1
b10 ,
b10 5
b10 *
b10 4
b10 0
#150000
0.
#155000
b1011 -
b1011 +
1.
b100 1
b11 ,
b11 5
b11 *
b11 4
b11 0
#160000
0.
#165000
b1100 +
b1100 -
1.
b101 1
b100 ,
b100 5
b100 *
b100 4
b100 0
#170000
0.
#175000
b1101 -
b1101 +
1.
b110 1
b101 ,
b101 5
b101 *
b101 4
b101 0
#180000
0.
#185000
b1110 +
b1110 -
1.
b111 1
b110 ,
b110 5
b110 *
b110 4
b110 0
#190000
0.
#195000
b1111 -
b1111 +
1.
b1000 1
b111 ,
b111 5
b111 *
b111 4
b111 0
#200000
0.
#205000
b10000 +
b10000 -
1.
b1001 1
b1000 ,
b1000 5
b1000 *
b1000 4
b1000 0
#210000
0.
#215000
b10001 -
b10001 +
1.
b1010 1
b1001 ,
b1001 5
b1001 *
b1001 4
b1001 0
#220000
0.
#225000
b10010 +
b10010 -
1.
b1011 1
b1010 ,
b1010 5
b1010 *
b1010 4
b1010 0
#230000
0.
#235000
b10011 -
b10011 +
1.
b1100 1
b1011 ,
b1011 5
b1011 *
b1011 4
b1011 0
#240000
0.
#245000
b10100 +
b10100 -
1.
b1101 1
b1100 ,
b1100 5
b1100 *
b1100 4
b1100 0
#250000
0.
#255000
b10101 -
b10101 +
1.
b1110 1
b1101 ,
b1101 5
b1101 *
b1101 4
b1101 0
#260000
0.
#265000
b10110 +
b10110 -
1.
b1111 1
b1110 ,
b1110 5
b1110 *
b1110 4
b1110 0
#270000
0.
#275000
b10111 -
b10111 +
1.
b10000 1
b1111 ,
b1111 5
b1111 *
b1111 4
b1111 0
#280000
0.
#285000
b11000 +
b11000 -
1.
b10001 1
b10000 ,
b10000 5
b10000 *
b10000 4
b10000 0
#290000
0.
#295000
b11001 -
b11001 +
1.
b10010 1
b10001 ,
b10001 5
b10001 *
b10001 4
b10001 0
#300000
0.
#305000
b11010 +
b11010 -
1.
b10011 1
b10010 ,
b10010 5
b10010 *
b10010 4
b10010 0
#310000
0.
#315000
b11011 -
b11011 +
1.
b10100 1
b10011 ,
b10011 5
b10011 *
b10011 4
b10011 0
#320000
0.
#325000
b11100 +
b11100 -
1.
b10101 1
b10100 ,
b10100 5
b10100 *
b10100 4
b10100 0
#330000
0.
#335000
b11101 -
b11101 +
1.
b10110 1
b10101 ,
b10101 5
b10101 *
b10101 4
b10101 0
#340000
0.
#345000
b11110 +
b11110 -
1.
b10111 1
b10110 ,
b10110 5
b10110 *
b10110 4
b10110 0
#350000
0.
#355000
b11111 -
b11111 +
1.
b11000 1
b10111 ,
b10111 5
b10111 *
b10111 4
b10111 0
#360000
0.
#365000
b100000 +
b100000 -
1.
b11001 1
b11000 ,
b11000 5
b11000 *
b11000 4
b11000 0
#370000
0.
#375000
b100001 -
b100001 +
1.
b11010 1
b11001 ,
b11001 5
b11001 *
b11001 4
b11001 0
#380000
0.
#385000
b100010 +
b100010 -
1.
b11011 1
b11010 ,
b11010 5
b11010 *
b11010 4
b11010 0
#390000
0.
#395000
b100011 -
b100011 +
1.
b11100 1
b11011 ,
b11011 5
b11011 *
b11011 4
b11011 0
#400000
0.
#405000
b100100 +
b100100 -
1.
b11101 1
b11100 ,
b11100 5
b11100 *
b11100 4
b11100 0
#410000
0.
#415000
b100101 -
b100101 +
1.
b11110 1
b11101 ,
b11101 5
b11101 *
b11101 4
b11101 0
#420000
0.
#425000
b100110 +
b100110 -
1.
b11111 1
b11110 ,
b11110 5
b11110 *
b11110 4
b11110 0
#430000
0.
#435000
b100111 -
b100111 +
1.
b100000 1
b11111 ,
b11111 5
b11111 *
b11111 4
b11111 0
#440000
0.
#445000
b1 !
b1 8
b0 "
b0 7
b101000 +
b101000 -
1.
b1 (
b1 3
b0 '
b0 2
0)
b0 0
#450000
0.
#455000
b11 !
b11 8
b10 "
b10 7
b101001 -
b101001 +
1.
b11 (
b11 3
b10 '
b10 2
b10 0
#460000
0.
#465000
b101 !
b101 8
b100 "
b100 7
b101010 +
b101010 -
1.
b101 (
b101 3
b100 '
b100 2
b100 0
#470000
0.
#475000
b111 !
b111 8
b110 "
b110 7
b101011 -
b101011 +
1.
b111 (
b111 3
b110 '
b110 2
b110 0
#480000
0.
#485000
b1001 !
b1001 8
b1000 "
b1000 7
b101100 +
b101100 -
1.
b1001 (
b1001 3
b1000 '
b1000 2
b1000 0
#490000
0.
#495000
b1011 !
b1011 8
b1010 "
b1010 7
b101101 -
b101101 +
1.
b1011 (
b1011 3
b1010 '
b1010 2
b1010 0
#500000
0.
#505000
b1101 !
b1101 8
b1100 "
b1100 7
b101110 +
b101110 -
1.
b1101 (
b1101 3
b1100 '
b1100 2
b1100 0
#510000
0.
#515000
b1111 !
b1111 8
b1110 "
b1110 7
b101111 -
b101111 +
1.
b1111 (
b1111 3
b1110 '
b1110 2
b1110 0
#520000
0.
#525000
b10001 !
b10001 8
b10000 "
b10000 7
b110000 +
b110000 -
1.
b10001 (
b10001 3
b10000 '
b10000 2
b10000 0
#530000
0.
#535000
b10011 !
b10011 8
b10010 "
b10010 7
b110001 -
b110001 +
1.
b10011 (
b10011 3
b10010 '
b10010 2
b10010 0
#540000
0.
#545000
b10101 !
b10101 8
b10100 "
b10100 7
b110010 +
b110010 -
1.
b10101 (
b10101 3
b10100 '
b10100 2
b10100 0
#550000
0.
#555000
b10111 !
b10111 8
b10110 "
b10110 7
b110011 -
b110011 +
1.
b10111 (
b10111 3
b10110 '
b10110 2
b10110 0
#560000
0.
#565000
b11001 !
b11001 8
b11000 "
b11000 7
b110100 +
b110100 -
1.
b11001 (
b11001 3
b11000 '
b11000 2
b11000 0
#570000
0.
#575000
b11011 !
b11011 8
b11010 "
b11010 7
b110101 -
b110101 +
1.
b11011 (
b11011 3
b11010 '
b11010 2
b11010 0
#580000
0.
#585000
b11101 !
b11101 8
b11100 "
b11100 7
b110110 +
b110110 -
1.
b11101 (
b11101 3
b11100 '
b11100 2
b11100 0
#590000
0.
#595000
b11111 !
b11111 8
b11110 "
b11110 7
b110111 -
b110111 +
1.
b11111 (
b11111 3
b11110 '
b11110 2
b11110 0
#600000
0.
#605000
b111000 +
b111000 -
1.
b100000 0
#610000
0.
#615000
b111001 -
b111001 +
1.
#620000
0.
#625000
b111010 +
b111010 -
1.
#630000
0.
#635000
b111011 -
b111011 +
1.
#640000
0.
#645000
b111100 +
b111100 -
1.
#650000
0.
#655000
b111101 -
b111101 +
1.
#660000
0.
#665000
b111110 +
b111110 -
1.
#670000
0.
#675000
b111111 -
b111111 +
1.
#680000
0.
#685000
b1000000 +
b1000000 -
1.
#690000
0.
#695000
b1000001 -
b1000001 +
1.
#700000
0.
#705000
b1000010 +
b1000010 -
1.
#710000
0.
#715000
b1000011 -
b1000011 +
1.
#720000
0.
#725000
b1000100 +
b1000100 -
1.
#730000
0.
#735000
b1000101 -
b1000101 +
1.
#740000
0.
#745000
b1000110 +
b1000110 -
1.
#750000
0.
#755000
b1000111 -
b1000111 +
1.
#760000
0.
#765000
b1001000 +
b1001000 -
1.
#770000
0.
#775000
b1001001 -
b1001001 +
1.
#780000
0.
#785000
b1001010 +
b1001010 -
1.
#790000
0.
#795000
b1001011 -
b1001011 +
1.
#800000
0.
#805000
b1001100 +
b1001100 -
1.
#810000
0.
#815000
b1001101 -
b1001101 +
1.
#820000
0.
#825000
b1001110 +
b1001110 -
1.
#830000
0.
#835000
b1001111 -
b1001111 +
1.
#840000
0.
#845000
b1010000 +
b1010000 -
1.
#850000
0.
#855000
b1010001 -
b1010001 +
1.
#860000
0.
#865000
b1010010 +
b1010010 -
1.
#870000
0.
#875000
b1010011 -
b1010011 +
1.
#880000
0.
#885000
b1010100 +
b1010100 -
1.
#890000
0.
#895000
b1010101 -
b1010101 +
1.
#900000
0.
#905000
b1010110 +
b1010110 -
1.
#910000
0.
#915000
b1010111 -
b1010111 +
1.
#920000
0.
#925000
b1011000 +
b1011000 -
1.
#930000
0.
#935000
b1011001 -
b1011001 +
1.
#940000
0.
#945000
b1011010 +
b1011010 -
1.
#950000
0.
#955000
b1011011 -
b1011011 +
1.
#960000
0.
#965000
b1011100 +
b1011100 -
1.
#970000
0.
#975000
b1011101 -
b1011101 +
1.
#980000
0.
#985000
b1011110 +
b1011110 -
1.
#990000
0.
#995000
b1011111 -
b1011111 +
1.
#1000000
0.
#1005000
b1100000 +
b1100000 -
1.
#1010000
0.
#1015000
b1100001 -
b1100001 +
1.
#1020000
0.
#1025000
b1100010 +
b1100010 -
1.
#1030000
0.
#1035000
b1100011 -
b1100011 +
1.
#1040000
0.
#1045000
b1100100 +
b1100100 -
1.
#1050000
0.
#1055000
b1100101 -
b1100101 +
1.
#1060000
0.
#1065000
b1100110 +
b1100110 -
1.
#1070000
0.
#1075000
b1100111 -
b1100111 +
1.
#1080000
0.
#1085000
b1101000 +
b1101000 -
1.
#1090000
0.
#1095000
b1101001 -
b1101001 +
1.
#1100000
0.
#1105000
b1101010 +
b1101010 -
1.
