InsMEM/user/src/InsMEM.v
module InsMEM(
    input [31:0] InsAddr,
    output reg [31:0] InsData
    );

    reg [7:0] rom[511:0];

    initial begin
        $readmemh("/Users/yr/code/computer-organization/computer-organization-labs/InsMEM/user/data/Instruction.txt", rom);
        // $readmemh("/Users/yr/code/computer-organization/computer-organization-labs/InsMEM/user/data/fibInstruction.txt", rom);
    end
    // 大端方式
    always @(InsAddr) begin
        InsData[7:0] = rom[InsAddr+3];
        InsData[15:8] = rom[InsAddr+2];
        InsData[23:16] = rom[InsAddr+1];
        InsData[31:24] = rom[InsAddr];
    end

endmodule

InsMEM/user/sim/testbench.v
`timescale 1ns/1ps
`include "/Users/yr/code/computer-organization/computer-organization-labs/InsMEM/user/src/InsMEM.v"
module testbench();

parameter DATA_WIDTH = 32;
parameter ADDR_WIDTH = 32;
parameter MAIN_FRE   = 500; //unit MHz
reg                   sys_clk = 0;
reg                   sys_rst = 1;
reg [DATA_WIDTH-1:0]  data = 0;
reg [ADDR_WIDTH-1:0]  addr = 0;

always begin
    #1000 sys_clk = ~sys_clk;
end

always begin
    #50 sys_rst = 0;
end

always @(posedge sys_clk) begin
    if (sys_rst)
        addr = 0;
    else
        addr = addr + 4;
end
always @(posedge sys_clk) begin
    if (sys_rst)
        data = 0;
    else
        data = data + 1;
end

//Instance
// outports wire
wire [31:0] 	InsData;

InsMEM u_InsMEM(
	.InsAddr 	( addr  ),
	.InsData 	( InsData  )
);



initial begin
    $dumpfile("wave.vcd");
    $dumpvars(0, testbench);
    #50000 $finish;
end

endmodule  //TOP

InsMEM/user/sim/wave.vcd
$date
	Tue Dec 26 09:34:29 2023
$end
$version
	Icarus Verilog
$end
$timescale
	1ps
$end
$scope module testbench $end
$var wire 32 ! InsData [31:0] $end
$var parameter 32 " ADDR_WIDTH $end
$var parameter 32 # DATA_WIDTH $end
$var parameter 32 $ MAIN_FRE $end
$var reg 32 % addr [31:0] $end
$var reg 32 & data [31:0] $end
$var reg 1 ' sys_clk $end
$var reg 1 ( sys_rst $end
$scope module u_InsMEM $end
$var wire 32 ) InsAddr [31:0] $end
$var reg 32 * InsData [31:0] $end
$upscope $end
$upscope $end
$enddefinitions $end
$comment Show the parameter values. $end
$dumpall
b111110100 $
b100000 #
b100000 "
$end
#0
$dumpvars
b10001100000001000000000000000000 *
b0 )
1(
0'
b0 &
b0 %
b10001100000001000000000000000000 !
$end
#50000
0(
#1000000
b10001100000001010000000000000000 !
b10001100000001010000000000000000 *
b100 %
b100 )
b1 &
1'
#2000000
0'
#3000000
b100001010011000000100000 !
b100001010011000000100000 *
b10 &
b1000 %
b1000 )
1'
#4000000
0'
#5000000
b10101100000001100000000000000100 !
b10101100000001100000000000000100 *
b1100 %
b1100 )
b11 &
1'
#6000000
0'
#7000000
b10001100000001110000000000000100 !
b10001100000001110000000000000100 *
b100 &
b10000 %
b10000 )
1'
#8000000
0'
#9000000
b100001110100000000100010 !
b100001110100000000100010 *
b10100 %
b10100 )
b101 &
1'
#10000000
0'
#11000000
b10101100000010000000000000001000 !
b10101100000010000000000000001000 *
b110 &
b11000 %
b11000 )
1'
#12000000
0'
#13000000
b100100000000010000101000000101 !
b100100000000010000101000000101 *
b11100 %
b11100 )
b111 &
1'
#14000000
0'
#15000000
b100100000000101111111110101000 !
b100100000000101111111110101000 *
b1000 &
b100000 %
b100000 )
1'
#16000000
0'
#17000000
b110100001000010000010110010000 !
b110100001000010000010110010000 *
b100100 %
b100100 )
b1001 &
1'
#18000000
0'
#19000000
b110100010000101000111101101100 !
b110100010000101000111101101100 *
b1010 &
b101000 %
b101000 )
1'
#20000000
0'
#21000000
b1000100001100000101010 !
b1000100001100000101010 *
b101100 %
b101100 )
b1011 &
1'
#22000000
0'
#23000000
b1000100001100000101011 !
b1000100001100000101011 *
b1100 &
b110000 %
b110000 )
1'
#24000000
0'
#25000000
b10001100000001000000000000001100 !
b10001100000001000000000000001100 *
b110100 %
b110100 )
b1101 &
1'
#26000000
0'
#27000000
b100001010011000000100010 !
b100001010011000000100010 *
b1110 &
b111000 %
b111000 )
1'
#28000000
0'
#29000000
b1010011000000100011 !
b1010011000000100011 *
b111100 %
b111100 )
b1111 &
1'
#30000000
0'
#31000000
b10000011001100000000000000010 !
b10000011001100000000000000010 *
b10000 &
b1000000 %
b1000000 )
1'
#32000000
0'
#33000000
b10001100000010100000000000000000 !
b10001100000010100000000000000000 *
b1000100 %
b1000100 )
b10001 &
1'
#34000000
0'
#35000000
b10001100000010110000000000000000 !
b10001100000010110000000000000000 *
b10010 &
b1001000 %
b1001000 )
1'
#36000000
0'
#37000000
b10001100000011000000000000000000 !
b10001100000011000000000000000000 *
b1001100 %
b1001100 )
b10011 &
1'
#38000000
0'
#39000000
b1000000000000000000000010111 !
b1000000000000000000000010111 *
b10100 &
b1010000 %
b1010000 )
1'
#40000000
0'
#41000000
b10001100000011010000000000000000 !
b10001100000011010000000000000000 *
b1010100 %
b1010100 )
b10101 &
1'
#42000000
0'
#43000000
b10001100000011100000000000000000 !
b10001100000011100000000000000000 *
b10110 &
b1011000 %
b1011000 )
1'
#44000000
0'
#45000000
b10001100000011110000000000000000 !
b10001100000011110000000000000000 *
b1011100 %
b1011100 )
b10111 &
1'
#46000000
0'
#47000000
bx !
bx *
b11000 &
b1100000 %
b1100000 )
1'
#48000000
0'
#49000000
b1100100 %
b1100100 )
b11001 &
1'
