InsMEM/user/src/InsMEM.v
module InsMEM(
    input [31:0] InsAddr,
    output reg [31:0] InsData
    );

    reg [7:0] rom[127:0];

    initial begin
        $readmemh("/Users/yr/code/computer-organization/computer-organization-labs/InsMEM/user/data/Instruction.txt", rom);
    end
    // 大端方式
    always @(InsAddr) begin
        InsData[7:0] = rom[InsAddr+3];
        InsData[15:8] = rom[InsAddr+2];
        InsData[23:16] = rom[InsAddr+1];
        InsData[31:24] = rom[InsAddr];
    end

endmodule

InsMEM/user/sim/testbench.v
`timescale 1ns/1ps
`include "/Users/yr/code/computer-organization/computer-organization-labs/InsMEM/user/src/InsMEM.v"
module testbench();

parameter DATA_WIDTH = 32;
parameter ADDR_WIDTH = 32;
parameter MAIN_FRE   = 500; //unit MHz
reg                   sys_clk = 0;
reg                   sys_rst = 1;
reg [DATA_WIDTH-1:0]  data = 0;
reg [ADDR_WIDTH-1:0]  addr = 0;

always begin
    #(500/MAIN_FRE) sys_clk = ~sys_clk;
end

always begin
    #50 sys_rst = 0;
end

always @(posedge sys_clk) begin
    if (sys_rst)
        addr = 0;
    else
        addr = addr + 4;
end
always @(posedge sys_clk) begin
    if (sys_rst)
        data = 0;
    else
        data = data + 1;
end

//Instance
// outports wire
wire [31:0] 	InsData;

InsMEM u_InsMEM(
	.InsAddr 	( addr  ),
	.InsData 	( InsData  )
);



initial begin
    $dumpfile("wave.vcd");
    $dumpvars(0, testbench);
    #50000 $finish;
end

endmodule  //TOP

InsMEM/user/sim/wave.vcd
$date
	Mon Dec 18 09:11:14 2023
$end
$version
	Icarus Verilog
$end
$timescale
	1ps
$end
$scope module testbench $end
$var wire 32 ! InsData [31:0] $end
$var parameter 32 " ADDR_WIDTH $end
$var parameter 32 # DATA_WIDTH $end
$var parameter 32 $ MAIN_FRE $end
$var reg 32 % addr [31:0] $end
$var reg 32 & data [31:0] $end
$var reg 1 ' sys_clk $end
$var reg 1 ( sys_rst $end
$scope module u_InsMEM $end
$var wire 32 ) InsAddr [31:0] $end
$var reg 32 * InsData [31:0] $end
$upscope $end
$upscope $end
$enddefinitions $end
$comment Show the parameter values. $end
$dumpall
b111110100 $
b100000 #
b100000 "
$end
#0
$dumpvars
b10000001000000011 *
b0 )
1(
0'
b0 &
b0 %
b10000001000000011 !
$end
#1000
1'
#2000
0'
#3000
1'
#4000
0'
#5000
1'
#6000
0'
#7000
1'
#8000
0'
#9000
1'
#10000
0'
#11000
1'
#12000
0'
#13000
1'
#14000
0'
#15000
1'
#16000
0'
#17000
1'
#18000
0'
#19000
1'
#20000
0'
#21000
1'
#22000
0'
#23000
1'
#24000
0'
#25000
1'
#26000
0'
#27000
1'
#28000
0'
#29000
1'
#30000
0'
#31000
1'
#32000
0'
#33000
1'
#34000
0'
#35000
1'
#36000
0'
#37000
1'
#38000
0'
#39000
1'
#40000
0'
#41000
1'
#42000
0'
#43000
1'
#44000
0'
#45000
1'
#46000
0'
#47000
1'
#48000
0'
#49000
1'
#50000
0'
0(
#51000
b100000001010000011000000111 !
b100000001010000011000000111 *
b1 &
b100 %
b100 )
1'
#52000
0'
#53000
b1000000010010000101000001011 !
b1000000010010000101000001011 *
b1000 %
b1000 )
b10 &
1'
#54000
0'
#55000
b1100000011010000111000001111 !
b1100000011010000111000001111 *
b11 &
b1100 %
b1100 )
1'
#56000
0'
#57000
b10000000100010001001000010011 !
b10000000100010001001000010011 *
b10000 %
b10000 )
b100 &
1'
#58000
0'
#59000
b10100000101010001011000010111 !
b10100000101010001011000010111 *
b101 &
b10100 %
b10100 )
1'
#60000
0'
#61000
b11000000110010001101000011011 !
b11000000110010001101000011011 *
b11000 %
b11000 )
b110 &
1'
#62000
0'
#63000
b11100000111010001111000011111 !
b11100000111010001111000011111 *
b111 &
b11100 %
b11100 )
1'
#64000
0'
#65000
b10000001000000011 !
b10000001000000011 *
b100000 %
b100000 )
b1000 &
1'
#66000
0'
#67000
b100000001010000011000000111 !
b100000001010000011000000111 *
b1001 &
b100100 %
b100100 )
1'
#68000
0'
#69000
b1000000010010000101000001011 !
b1000000010010000101000001011 *
b101000 %
b101000 )
b1010 &
1'
#70000
0'
#71000
b1100000011010000111000001111 !
b1100000011010000111000001111 *
b1011 &
b101100 %
b101100 )
1'
#72000
0'
#73000
b10000000100010001001000010011 !
b10000000100010001001000010011 *
b110000 %
b110000 )
b1100 &
1'
#74000
0'
#75000
b10100000101010001011000010111 !
b10100000101010001011000010111 *
b1101 &
b110100 %
b110100 )
1'
#76000
0'
#77000
b11000000110010001101000011011 !
b11000000110010001101000011011 *
b111000 %
b111000 )
b1110 &
1'
#78000
0'
#79000
b11100000111010001111000011111 !
b11100000111010001111000011111 *
b1111 &
b111100 %
b111100 )
1'
#80000
0'
#81000
b10000001000000011 !
b10000001000000011 *
b1000000 %
b1000000 )
b10000 &
1'
#82000
0'
#83000
b100000001010000011000000111 !
b100000001010000011000000111 *
b10001 &
b1000100 %
b1000100 )
1'
#84000
0'
#85000
b1000000010010000101000001011 !
b1000000010010000101000001011 *
b1001000 %
b1001000 )
b10010 &
1'
#86000
0'
#87000
b1100000011010000111000001111 !
b1100000011010000111000001111 *
b10011 &
b1001100 %
b1001100 )
1'
#88000
0'
#89000
b10000000100010001001000010011 !
b10000000100010001001000010011 *
b1010000 %
b1010000 )
b10100 &
1'
#90000
0'
#91000
b10100000101010001011000010111 !
b10100000101010001011000010111 *
b10101 &
b1010100 %
b1010100 )
1'
#92000
0'
#93000
b11000000110010001101000011011 !
b11000000110010001101000011011 *
b1011000 %
b1011000 )
b10110 &
1'
#94000
0'
#95000
b11100000111010001111000011111 !
b11100000111010001111000011111 *
b10111 &
b1011100 %
b1011100 )
1'
#96000
0'
#97000
b10000001000000011 !
b10000001000000011 *
b1100000 %
b1100000 )
b11000 &
1'
#98000
0'
#99000
b100000001010000011000000111 !
b100000001010000011000000111 *
b11001 &
b1100100 %
b1100100 )
1'
#100000
0'
#101000
b1000000010010000101000001011 !
b1000000010010000101000001011 *
b1101000 %
b1101000 )
b11010 &
1'
#102000
0'
#103000
b1100000011010000111000001111 !
b1100000011010000111000001111 *
b11011 &
b1101100 %
b1101100 )
1'
#104000
0'
#105000
b10000000100010001001000010011 !
b10000000100010001001000010011 *
b1110000 %
b1110000 )
b11100 &
1'
#106000
0'
#107000
b10100000101010001011000010111 !
b10100000101010001011000010111 *
b11101 &
b1110100 %
b1110100 )
1'
#108000
0'
#109000
b11000000110010001101000011011 !
b11000000110010001101000011011 *
b1111000 %
b1111000 )
b11110 &
1'
#110000
0'
#111000
b11100000111010001111000011111 !
b11100000111010001111000011111 *
b11111 &
b1111100 %
b1111100 )
1'
#112000
0'
#113000
bx !
bx *
b10000000 %
b10000000 )
b100000 &
1'
#114000
0'
#115000
b100001 &
b10000100 %
b10000100 )
1'
#116000
0'
#117000
b10001000 %
b10001000 )
b100010 &
1'
#118000
0'
#119000
b100011 &
b10001100 %
b10001100 )
1'
#120000
0'
#121000
b10010000 %
b10010000 )
b100100 &
1'
#122000
0'
#123000
b100101 &
b10010100 %
b10010100 )
1'
#124000
0'
#125000
b10011000 %
b10011000 )
b100110 &
1'
#126000
0'
#127000
b100111 &
b10011100 %
b10011100 )
1'
#128000
0'
#129000
b10100000 %
b10100000 )
b101000 &
1'
#130000
0'
#131000
b101001 &
b10100100 %
b10100100 )
1'
#132000
0'
#133000
b10101000 %
b10101000 )
b101010 &
1'
#134000
0'
#135000
b101011 &
b10101100 %
b10101100 )
1'
#136000
0'
#137000
b10110000 %
b10110000 )
b101100 &
1'
#138000
0'
#139000
b101101 &
b10110100 %
b10110100 )
1'
#140000
0'
#141000
b10111000 %
b10111000 )
b101110 &
1'
#142000
0'
#143000
b101111 &
b10111100 %
b10111100 )
1'
#144000
0'
#145000
b11000000 %
b11000000 )
b110000 &
1'
#146000
0'
#147000
b110001 &
b11000100 %
b11000100 )
1'
#148000
0'
#149000
b11001000 %
b11001000 )
b110010 &
1'
#150000
0'
#151000
b110011 &
b11001100 %
b11001100 )
1'
#152000
0'
#153000
b11010000 %
b11010000 )
b110100 &
1'
#154000
0'
#155000
b110101 &
b11010100 %
b11010100 )
1'
#156000
0'
#157000
b11011000 %
b11011000 )
b110110 &
1'
#158000
0'
#159000
b110111 &
b11011100 %
b11011100 )
1'
#160000
0'
#161000
b11100000 %
b11100000 )
b111000 &
1'
#162000
0'
#163000
b111001 &
b11100100 %
b11100100 )
1'
#164000
0'
#165000
b11101000 %
b11101000 )
b111010 &
1'
#166000
0'
#167000
b111011 &
b11101100 %
b11101100 )
1'
#168000
0'
#169000
b11110000 %
b11110000 )
b111100 &
1'
#170000
0'
#171000
b111101 &
b11110100 %
b11110100 )
1'
#172000
0'
#173000
b11111000 %
b11111000 )
b111110 &
1'
#174000
0'
#175000
b111111 &
b11111100 %
b11111100 )
1'
#176000
0'
#177000
b100000000 %
b100000000 )
b1000000 &
1'
#178000
0'
#179000
b1000001 &
b100000100 %
b100000100 )
1'
#180000
0'
#181000
b100001000 %
b100001000 )
b1000010 &
1'
#182000
0'
#183000
b1000011 &
b100001100 %
b100001100 )
1'
#184000
0'
#185000
b100010000 %
b100010000 )
b1000100 &
1'
#186000
0'
#187000
b1000101 &
b100010100 %
b100010100 )
1'
#188000
0'
#189000
b100011000 %
b100011000 )
b1000110 &
1'
#190000
0'
#191000
b1000111 &
b100011100 %
b100011100 )
1'
#192000
0'
#193000
b100100000 %
b100100000 )
b1001000 &
1'
#194000
0'
#195000
b1001001 &
b100100100 %
b100100100 )
1'
#196000
0'
#197000
b100101000 %
b100101000 )
b1001010 &
1'
#198000
0'
#199000
b1001011 &
b100101100 %
b100101100 )
1'
#200000
0'
#201000
b100110000 %
b100110000 )
b1001100 &
1'
#202000
0'
#203000
b1001101 &
b100110100 %
b100110100 )
1'
#204000
0'
#205000
b100111000 %
b100111000 )
b1001110 &
1'
#206000
0'
#207000
b1001111 &
b100111100 %
b100111100 )
1'
#208000
0'
#209000
b101000000 %
b101000000 )
b1010000 &
1'
#210000
0'
#211000
b1010001 &
b101000100 %
b101000100 )
1'
#212000
0'
#213000
b101001000 %
b101001000 )
b1010010 &
1'
#214000
0'
#215000
b1010011 &
b101001100 %
b101001100 )
1'
#216000
0'
#217000
b101010000 %
b101010000 )
b1010100 &
1'
#218000
0'
#219000
b1010101 &
b101010100 %
b101010100 )
1'
#220000
0'
#221000
b101011000 %
b101011000 )
b1010110 &
1'
#222000
0'
#223000
b1010111 &
b101011100 %
b101011100 )
1'
#224000
0'
#225000
b101100000 %
b101100000 )
b1011000 &
1'
#226000
0'
#227000
b1011001 &
b101100100 %
b101100100 )
1'
#228000
0'
#229000
b101101000 %
b101101000 )
b1011010 &
1'
#230000
0'
#231000
b1011011 &
b101101100 %
b101101100 )
1'
#232000
0'
#233000
b101110000 %
b101110000 )
b1011100 &
1'
#234000
0'
#235000
b1011101 &
b101110100 %
b101110100 )
1'
#236000
0'
#237000
b101111000 %
b101111000 )
b1011110 &
1'
#238000
0'
#239000
b1011111 &
b101111100 %
b101111100 )
1'
#240000
0'
#241000
b110000000 %
b110000000 )
b1100000 &
1'
#242000
0'
#243000
b1100001 &
b110000100 %
b110000100 )
1'
#244000
0'
#245000
b110001000 %
b110001000 )
b1100010 &
1'
#246000
0'
#247000
b1100011 &
b110001100 %
b110001100 )
1'
#248000
0'
#249000
b110010000 %
b110010000 )
b1100100 &
1'
#250000
0'
#251000
b1100101 &
b110010100 %
b110010100 )
1'
#252000
0'
#253000
b110011000 %
b110011000 )
b1100110 &
1'
#254000
0'
#255000
b1100111 &
b110011100 %
b110011100 )
1'
#256000
0'
#257000
b110100000 %
b110100000 )
b1101000 &
1'
#258000
0'
#259000
b1101001 &
b110100100 %
b110100100 )
1'
#260000
0'
#261000
b110101000 %
b110101000 )
b1101010 &
1'
#262000
0'
#263000
b1101011 &
b110101100 %
b110101100 )
1'
#264000
0'
#265000
b110110000 %
b110110000 )
b1101100 &
1'
#266000
0'
#267000
b1101101 &
b110110100 %
b110110100 )
1'
#268000
0'
#269000
b110111000 %
b110111000 )
b1101110 &
1'
#270000
0'
#271000
b1101111 &
b110111100 %
b110111100 )
1'
#272000
0'
#273000
b111000000 %
b111000000 )
b1110000 &
1'
#274000
0'
#275000
b1110001 &
b111000100 %
b111000100 )
1'
#276000
0'
#277000
b111001000 %
b111001000 )
b1110010 &
1'
#278000
0'
#279000
b1110011 &
b111001100 %
b111001100 )
1'
#280000
0'
#281000
b111010000 %
b111010000 )
b1110100 &
1'
#282000
0'
#283000
b1110101 &
b111010100 %
b111010100 )
1'
#284000
0'
#285000
b111011000 %
b111011000 )
b1110110 &
1'
#286000
0'
#287000
b1110111 &
b111011100 %
b111011100 )
1'
#288000
0'
#289000
b111100000 %
b111100000 )
b1111000 &
1'
#290000
0'
#291000
b1111001 &
b111100100 %
b111100100 )
1'
#292000
0'
#293000
b111101000 %
b111101000 )
b1111010 &
1'
#294000
0'
#295000
b1111011 &
b111101100 %
b111101100 )
1'
#296000
0'
#297000
b111110000 %
b111110000 )
b1111100 &
1'
#298000
0'
#299000
b1111101 &
b111110100 %
b111110100 )
1'
#300000
0'
#301000
b111111000 %
b111111000 )
b1111110 &
1'
#302000
0'
#303000
b1111111 &
b111111100 %
b111111100 )
1'
#304000
0'
#305000
b1000000000 %
b1000000000 )
b10000000 &
1'
#306000
0'
#307000
b10000001 &
b1000000100 %
b1000000100 )
1'
#308000
0'
#309000
b1000001000 %
b1000001000 )
b10000010 &
1'
#310000
0'
#311000
b10000011 &
b1000001100 %
b1000001100 )
1'
#312000
0'
#313000
b1000010000 %
b1000010000 )
b10000100 &
1'
#314000
0'
#315000
b10000101 &
b1000010100 %
b1000010100 )
1'
#316000
0'
#317000
b1000011000 %
b1000011000 )
b10000110 &
1'
#318000
0'
#319000
b10000111 &
b1000011100 %
b1000011100 )
1'
#320000
0'
#321000
b1000100000 %
b1000100000 )
b10001000 &
1'
#322000
0'
#323000
b10001001 &
b1000100100 %
b1000100100 )
1'
#324000
0'
#325000
b1000101000 %
b1000101000 )
b10001010 &
1'
#326000
0'
#327000
b10001011 &
b1000101100 %
b1000101100 )
1'
#328000
0'
#329000
b1000110000 %
b1000110000 )
b10001100 &
1'
#330000
0'
#331000
b10001101 &
b1000110100 %
b1000110100 )
1'
#332000
0'
#333000
b1000111000 %
b1000111000 )
b10001110 &
1'
#334000
0'
#335000
b10001111 &
b1000111100 %
b1000111100 )
1'
#336000
0'
#337000
b1001000000 %
b1001000000 )
b10010000 &
1'
#338000
0'
#339000
b10010001 &
b1001000100 %
b1001000100 )
1'
#340000
0'
#341000
b1001001000 %
b1001001000 )
b10010010 &
1'
#342000
0'
#343000
b10010011 &
b1001001100 %
b1001001100 )
1'
#344000
0'
#345000
b1001010000 %
b1001010000 )
b10010100 &
1'
#346000
0'
#347000
b10010101 &
b1001010100 %
b1001010100 )
1'
#348000
0'
#349000
b1001011000 %
b1001011000 )
b10010110 &
1'
#350000
0'
#351000
b10010111 &
b1001011100 %
b1001011100 )
1'
#352000
0'
#353000
b1001100000 %
b1001100000 )
b10011000 &
1'
#354000
0'
#355000
b10011001 &
b1001100100 %
b1001100100 )
1'
#356000
0'
#357000
b1001101000 %
b1001101000 )
b10011010 &
1'
#358000
0'
#359000
b10011011 &
b1001101100 %
b1001101100 )
1'
#360000
0'
#361000
b1001110000 %
b1001110000 )
b10011100 &
1'
#362000
0'
#363000
b10011101 &
b1001110100 %
b1001110100 )
1'
#364000
0'
#365000
b1001111000 %
b1001111000 )
b10011110 &
1'
#366000
0'
#367000
b10011111 &
b1001111100 %
b1001111100 )
1'
#368000
0'
#369000
b1010000000 %
b1010000000 )
b10100000 &
1'
#370000
0'
#371000
b10100001 &
b1010000100 %
b1010000100 )
1'
#372000
0'
#373000
b1010001000 %
b1010001000 )
b10100010 &
1'
#374000
0'
#375000
b10100011 &
b1010001100 %
b1010001100 )
1'
#376000
0'
#377000
b1010010000 %
b1010010000 )
b10100100 &
1'
#378000
0'
#379000
b10100101 &
b1010010100 %
b1010010100 )
1'
#380000
0'
#381000
b1010011000 %
b1010011000 )
b10100110 &
1'
#382000
0'
#383000
b10100111 &
b1010011100 %
b1010011100 )
1'
#384000
0'
#385000
b1010100000 %
b1010100000 )
b10101000 &
1'
#386000
0'
#387000
b10101001 &
b1010100100 %
b1010100100 )
1'
#388000
0'
#389000
b1010101000 %
b1010101000 )
b10101010 &
1'
#390000
0'
#391000
b10101011 &
b1010101100 %
b1010101100 )
1'
#392000
0'
#393000
b1010110000 %
b1010110000 )
b10101100 &
1'
#394000
0'
#395000
b10101101 &
b1010110100 %
b1010110100 )
1'
#396000
0'
#397000
b1010111000 %
b1010111000 )
b10101110 &
1'
#398000
0'
#399000
b10101111 &
b1010111100 %
b1010111100 )
1'
#400000
0'
#401000
b1011000000 %
b1011000000 )
b10110000 &
1'
#402000
0'
#403000
b10110001 &
b1011000100 %
b1011000100 )
1'
#404000
0'
#405000
b1011001000 %
b1011001000 )
b10110010 &
1'
#406000
0'
#407000
b10110011 &
b1011001100 %
b1011001100 )
1'
#408000
0'
#409000
b1011010000 %
b1011010000 )
b10110100 &
1'
#410000
0'
#411000
b10110101 &
b1011010100 %
b1011010100 )
1'
#412000
0'
#413000
b1011011000 %
b1011011000 )
b10110110 &
1'
#414000
0'
#415000
b10110111 &
b1011011100 %
b1011011100 )
1'
#416000
0'
#417000
b1011100000 %
b1011100000 )
b10111000 &
1'
#418000
0'
#419000
b10111001 &
b1011100100 %
b1011100100 )
1'
#420000
0'
#421000
b1011101000 %
b1011101000 )
b10111010 &
1'
#422000
0'
#423000
b10111011 &
b1011101100 %
b1011101100 )
1'
#424000
0'
#425000
b1011110000 %
b1011110000 )
b10111100 &
1'
#426000
0'
#427000
b10111101 &
b1011110100 %
b1011110100 )
1'
#428000
0'
#429000
b1011111000 %
b1011111000 )
b10111110 &
1'
#430000
0'
#431000
b10111111 &
b1011111100 %
b1011111100 )
1'
#432000
0'
#433000
b1100000000 %
b1100000000 )
b11000000 &
1'
#434000
0'
#435000
b11000001 &
b1100000100 %
b1100000100 )
1'
#436000
0'
#437000
b1100001000 %
b1100001000 )
b11000010 &
1'
#438000
0'
#439000
b11000011 &
b1100001100 %
b1100001100 )
1'
#440000
0'
#441000
b1100010000 %
b1100010000 )
b11000100 &
1'
#442000
0'
#443000
b11000101 &
b1100010100 %
b1100010100 )
1'
#444000
0'
#445000
b1100011000 %
b1100011000 )
b11000110 &
1'
#446000
0'
#447000
b11000111 &
b1100011100 %
b1100011100 )
1'
#448000
0'
#449000
b1100100000 %
b1100100000 )
b11001000 &
1'
#450000
0'
#451000
b11001001 &
b1100100100 %
b1100100100 )
1'
#452000
0'
#453000
b1100101000 %
b1100101000 )
b11001010 &
1'
#454000
0'
#455000
b11001011 &
b1100101100 %
b1100101100 )
1'
#456000
0'
#457000
b1100110000 %
b1100110000 )
b11001100 &
1'
#458000
0'
#459000
b11001101 &
b1100110100 %
b1100110100 )
1'
#460000
0'
#461000
b1100111000 %
b1100111000 )
b11001110 &
1'
#462000
0'
#463000
b11001111 &
b1100111100 %
b1100111100 )
1'
#464000
0'
#465000
b1101000000 %
b1101000000 )
b11010000 &
1'
#466000
0'
#467000
b11010001 &
b1101000100 %
b1101000100 )
1'
#468000
0'
#469000
b1101001000 %
b1101001000 )
b11010010 &
1'
#470000
0'
#471000
b11010011 &
b1101001100 %
b1101001100 )
1'
#472000
0'
#473000
b1101010000 %
b1101010000 )
b11010100 &
1'
#474000
0'
#475000
b11010101 &
b1101010100 %
b1101010100 )
1'
#476000
0'
#477000
b1101011000 %
b1101011000 )
b11010110 &
1'
#478000
0'
#479000
b11010111 &
b1101011100 %
b1101011100 )
1'
#480000
0'
#481000
b1101100000 %
b1101100000 )
b11011000 &
1'
#482000
0'
#483000
b11011001 &
b1101100100 %
b1101100100 )
1'
#484000
0'
#485000
b1101101000 %
b1101101000 )
b11011010 &
1'
#486000
0'
#487000
b11011011 &
b1101101100 %
b1101101100 )
1'
#488000
0'
#489000
b1101110000 %
b1101110000 )
b11011100 &
1'
#490000
0'
#491000
b11011101 &
b1101110100 %
b1101110100 )
1'
#492000
0'
#493000
b1101111000 %
b1101111000 )
b11011110 &
1'
#494000
0'
#495000
b11011111 &
b1101111100 %
b1101111100 )
1'
#496000
0'
#497000
b1110000000 %
b1110000000 )
b11100000 &
1'
#498000
0'
#499000
b11100001 &
b1110000100 %
b1110000100 )
1'
#500000
0'
#501000
b1110001000 %
b1110001000 )
b11100010 &
1'
#502000
0'
#503000
b11100011 &
b1110001100 %
b1110001100 )
1'
#504000
0'
#505000
b1110010000 %
b1110010000 )
b11100100 &
1'
#506000
0'
#507000
b11100101 &
b1110010100 %
b1110010100 )
1'
#508000
0'
#509000
b1110011000 %
b1110011000 )
b11100110 &
1'
#510000
0'
#511000
b11100111 &
b1110011100 %
b1110011100 )
1'
#512000
0'
#513000
b1110100000 %
b1110100000 )
b11101000 &
1'
#514000
0'
#515000
b11101001 &
b1110100100 %
b1110100100 )
1'
#516000
0'
#517000
b1110101000 %
b1110101000 )
b11101010 &
1'
#518000
0'
#519000
b11101011 &
b1110101100 %
b1110101100 )
1'
#520000
0'
#521000
b1110110000 %
b1110110000 )
b11101100 &
1'
#522000
0'
#523000
b11101101 &
b1110110100 %
b1110110100 )
1'
#524000
0'
#525000
b1110111000 %
b1110111000 )
b11101110 &
1'
#526000
0'
#527000
b11101111 &
b1110111100 %
b1110111100 )
1'
#528000
0'
#529000
b1111000000 %
b1111000000 )
b11110000 &
1'
#530000
0'
#531000
b11110001 &
b1111000100 %
b1111000100 )
1'
#532000
0'
#533000
b1111001000 %
b1111001000 )
b11110010 &
1'
#534000
0'
#535000
b11110011 &
b1111001100 %
b1111001100 )
1'
#536000
0'
#537000
b1111010000 %
b1111010000 )
b11110100 &
1'
#538000
0'
#539000
b11110101 &
b1111010100 %
b1111010100 )
1'
#540000
0'
#541000
b1111011000 %
b1111011000 )
b11110110 &
1'
#542000
0'
#543000
b11110111 &
b1111011100 %
b1111011100 )
1'
#544000
0'
#545000
b1111100000 %
b1111100000 )
b11111000 &
1'
#546000
0'
#547000
b11111001 &
b1111100100 %
b1111100100 )
1'
#548000
0'
#549000
b1111101000 %
b1111101000 )
b11111010 &
1'
#550000
0'
#551000
b11111011 &
b1111101100 %
b1111101100 )
1'
#552000
0'
#553000
b1111110000 %
b1111110000 )
b11111100 &
1'
#554000
0'
#555000
b11111101 &
b1111110100 %
b1111110100 )
1'
#556000
0'
#557000
b1111111000 %
b1111111000 )
b11111110 &
1'
#558000
0'
#559000
b11111111 &
b1111111100 %
b1111111100 )
1'
#560000
0'
#561000
b10000000000 %
b10000000000 )
b100000000 &
1'
#562000
0'
#563000
b100000001 &
b10000000100 %
b10000000100 )
1'
#564000
0'
#565000
b10000001000 %
b10000001000 )
b100000010 &
1'
#566000
0'
#567000
b100000011 &
b10000001100 %
b10000001100 )
1'
#568000
0'
#569000
b10000010000 %
b10000010000 )
b100000100 &
1'
#570000
0'
#571000
b100000101 &
b10000010100 %
b10000010100 )
1'
#572000
0'
#573000
b10000011000 %
b10000011000 )
b100000110 &
1'
#574000
0'
#575000
b100000111 &
b10000011100 %
b10000011100 )
1'
#576000
0'
#577000
b10000100000 %
b10000100000 )
b100001000 &
1'
#578000
0'
#579000
b100001001 &
b10000100100 %
b10000100100 )
1'
#580000
0'
#581000
b10000101000 %
b10000101000 )
b100001010 &
1'
#582000
0'
#583000
b100001011 &
b10000101100 %
b10000101100 )
1'
#584000
0'
#585000
b10000110000 %
b10000110000 )
b100001100 &
1'
#586000
0'
#587000
b100001101 &
b10000110100 %
b10000110100 )
1'
#588000
0'
#589000
b10000111000 %
b10000111000 )
b100001110 &
1'
#590000
0'
#591000
b100001111 &
b10000111100 %
b10000111100 )
1'
#592000
0'
#593000
b10001000000 %
b10001000000 )
b100010000 &
1'
#594000
0'
#595000
b100010001 &
b10001000100 %
b10001000100 )
1'
#596000
0'
#597000
b10001001000 %
b10001001000 )
b100010010 &
1'
#598000
0'
#599000
b100010011 &
b10001001100 %
b10001001100 )
1'
#600000
0'
#601000
b10001010000 %
b10001010000 )
b100010100 &
1'
#602000
0'
#603000
b100010101 &
b10001010100 %
b10001010100 )
1'
#604000
0'
#605000
b10001011000 %
b10001011000 )
b100010110 &
1'
#606000
0'
#607000
b100010111 &
b10001011100 %
b10001011100 )
1'
#608000
0'
#609000
b10001100000 %
b10001100000 )
b100011000 &
1'
#610000
0'
#611000
b100011001 &
b10001100100 %
b10001100100 )
1'
#612000
0'
#613000
b10001101000 %
b10001101000 )
b100011010 &
1'
#614000
0'
#615000
b100011011 &
b10001101100 %
b10001101100 )
1'
#616000
0'
#617000
b10001110000 %
b10001110000 )
b100011100 &
1'
#618000
0'
#619000
b100011101 &
b10001110100 %
b10001110100 )
1'
#620000
0'
#621000
b10001111000 %
b10001111000 )
b100011110 &
1'
#622000
0'
#623000
b100011111 &
b10001111100 %
b10001111100 )
1'
#624000
0'
#625000
b10010000000 %
b10010000000 )
b100100000 &
1'
#626000
0'
#627000
b100100001 &
b10010000100 %
b10010000100 )
1'
#628000
0'
#629000
b10010001000 %
b10010001000 )
b100100010 &
1'
#630000
0'
#631000
b100100011 &
b10010001100 %
b10010001100 )
1'
#632000
0'
#633000
b10010010000 %
b10010010000 )
b100100100 &
1'
#634000
0'
#635000
b100100101 &
b10010010100 %
b10010010100 )
1'
#636000
0'
#637000
b10010011000 %
b10010011000 )
b100100110 &
1'
#638000
0'
#639000
b100100111 &
b10010011100 %
b10010011100 )
1'
#640000
0'
#641000
b10010100000 %
b10010100000 )
b100101000 &
1'
#642000
0'
#643000
b100101001 &
b10010100100 %
b10010100100 )
1'
#644000
0'
#645000
b10010101000 %
b10010101000 )
b100101010 &
1'
#646000
0'
#647000
b100101011 &
b10010101100 %
b10010101100 )
1'
#648000
0'
#649000
b10010110000 %
b10010110000 )
b100101100 &
1'
#650000
0'
#651000
b100101101 &
b10010110100 %
b10010110100 )
1'
#652000
0'
#653000
b10010111000 %
b10010111000 )
b100101110 &
1'
#654000
0'
#655000
b100101111 &
b10010111100 %
b10010111100 )
1'
#656000
0'
#657000
b10011000000 %
b10011000000 )
b100110000 &
1'
#658000
0'
#659000
b100110001 &
b10011000100 %
b10011000100 )
1'
#660000
0'
#661000
b10011001000 %
b10011001000 )
b100110010 &
1'
#662000
0'
#663000
b100110011 &
b10011001100 %
b10011001100 )
1'
#664000
0'
#665000
b10011010000 %
b10011010000 )
b100110100 &
1'
#666000
0'
#667000
b100110101 &
b10011010100 %
b10011010100 )
1'
#668000
0'
#669000
b10011011000 %
b10011011000 )
b100110110 &
1'
#670000
0'
#671000
b100110111 &
b10011011100 %
b10011011100 )
1'
#672000
0'
#673000
b10011100000 %
b10011100000 )
b100111000 &
1'
#674000
0'
#675000
b100111001 &
b10011100100 %
b10011100100 )
1'
#676000
0'
#677000
b10011101000 %
b10011101000 )
b100111010 &
1'
#678000
0'
#679000
b100111011 &
b10011101100 %
b10011101100 )
1'
#680000
0'
#681000
b10011110000 %
b10011110000 )
b100111100 &
1'
#682000
0'
#683000
b100111101 &
b10011110100 %
b10011110100 )
1'
#684000
0'
#685000
b10011111000 %
b10011111000 )
b100111110 &
1'
#686000
0'
#687000
b100111111 &
b10011111100 %
b10011111100 )
1'
#688000
0'
#689000
b10100000000 %
b10100000000 )
b101000000 &
1'
#690000
0'
#691000
b101000001 &
b10100000100 %
b10100000100 )
1'
#692000
0'
#693000
b10100001000 %
b10100001000 )
b101000010 &
1'
#694000
0'
#695000
b101000011 &
b10100001100 %
b10100001100 )
1'
#696000
0'
#697000
b10100010000 %
b10100010000 )
b101000100 &
1'
#698000
0'
#699000
b101000101 &
b10100010100 %
b10100010100 )
1'
#700000
0'
#701000
b10100011000 %
b10100011000 )
b101000110 &
1'
#702000
0'
#703000
b101000111 &
b10100011100 %
b10100011100 )
1'
#704000
0'
#705000
b10100100000 %
b10100100000 )
b101001000 &
1'
#706000
0'
#707000
b101001001 &
b10100100100 %
b10100100100 )
1'
#708000
0'
#709000
b10100101000 %
b10100101000 )
b101001010 &
1'
#710000
0'
#711000
b101001011 &
b10100101100 %
b10100101100 )
1'
#712000
0'
#713000
b10100110000 %
b10100110000 )
b101001100 &
1'
#714000
0'
#715000
b101001101 &
b10100110100 %
b10100110100 )
1'
#716000
0'
#717000
b10100111000 %
b10100111000 )
b101001110 &
1'
#718000
0'
#719000
b101001111 &
b10100111100 %
b10100111100 )
1'
#720000
0'
#721000
b10101000000 %
b10101000000 )
b101010000 &
1'
#722000
0'
#723000
b101010001 &
b10101000100 %
b10101000100 )
1'
#724000
0'
#725000
b10101001000 %
b10101001000 )
b101010010 &
1'
#726000
0'
#727000
b101010011 &
b10101001100 %
b10101001100 )
1'
#728000
0'
#729000
b10101010000 %
b10101010000 )
b101010100 &
1'
#730000
0'
#731000
b101010101 &
b10101010100 %
b10101010100 )
1'
#732000
0'
#733000
b10101011000 %
b10101011000 )
b101010110 &
1'
#734000
0'
#735000
b101010111 &
b10101011100 %
b10101011100 )
1'
#736000
0'
#737000
b10101100000 %
b10101100000 )
b101011000 &
1'
#738000
0'
#739000
b101011001 &
b10101100100 %
b10101100100 )
1'
#740000
0'
#741000
b10101101000 %
b10101101000 )
b101011010 &
1'
#742000
0'
#743000
b101011011 &
b10101101100 %
b10101101100 )
1'
#744000
0'
#745000
b10101110000 %
b10101110000 )
b101011100 &
1'
#746000
0'
#747000
b101011101 &
b10101110100 %
b10101110100 )
1'
#748000
0'
#749000
b10101111000 %
b10101111000 )
b101011110 &
1'
#750000
0'
#751000
b101011111 &
b10101111100 %
b10101111100 )
1'
#752000
0'
