MEM/user/src/MEM.v
// module MEM (Address, VE, dataout, clk)
// 定义一个名为MEM的模块，该模块模拟了一个内存模块
module MEM (Address, WE, data, dataout, clk);

// 定义一个参数n，表示数据总线的宽度
parameter n = 32;

// 定义两个32位宽的输入线，分别是地址和数据
input wire[n-1:0] Address, data;

// 定义两个输入线，分别是写入使能信号和时钟信号
input wire WE, clk;

// 定义一个32位宽的输出数据总线
output reg[n-1:0] dataout;

// 定义一个256个元素的内存数组，每个元素是一个8位宽的寄存器
(* ram_style = "distributed" *) reg [7:0] mem [255:0];

initial
    begin
        $readmemh("/Users/yr/code/computer-organization/computer-organization-labs/MEM/user/data/data.txt", mem);
        // $readmemh("/Users/yr/code/computer-organization/computer-organization-labs/MEM/user/data/fibData.txt", mem);
    end

// 在时钟信号的下降沿，如果WE为1，则将输入数据写入到内存数组的指定地址
always @ (negedge clk)
    begin
        if(WE ==1)begin
            {mem[Address+3], mem[Address+2], mem[Address+1], mem[Address]} = data;
            $display("[DEBUG] write %h to memory address:%h, %h", data, Address, {mem[Address+3], mem[Address+2], mem[Address+1], mem[Address]});
        end

    end

always @ (*)
    begin
        dataout = {mem[Address+3], mem[Address+2], mem[Address+1], mem[Address]};
        //$display("[DEBUG] read %h from memory address:%h", dataout, Address);
    end
endmodule

MEM/user/sim/testbench.v
`include "/Users/yr/code/computer-organization/computer-organization-labs/MEM/user/src/MEM.v"
module testbench();

parameter DATA_WIDTH = 32;
parameter ADDR_WIDTH = 32;
parameter MAIN_FRE   = 500; //unit MHz
reg                   sys_clk = 0;
reg                   sys_rst = 1;
reg [DATA_WIDTH-1:0]  data = 0;
reg [ADDR_WIDTH-1:0]  addr = 0;

always begin
    #(500/MAIN_FRE) sys_clk = ~sys_clk;
end

always begin
    #2 sys_rst = 0;
end

always @(posedge sys_clk) begin
    if (sys_rst)
        addr = 0;
    else
        addr = addr + 4;
end
always @(posedge sys_clk) begin
    if (sys_rst)
        data = 0;
    else
        data = data + 1;
end

// Instance
// outports wire
parameter n = 32;
wire [n-1:0] dataout;
reg WE;

MEM u_MEM(
	.Address 	( addr     ),
	.data    	( data     ),
	.WE      	( WE       ),
	.clk     	( sys_clk  ),
	.dataout 	( dataout  )
);



initial begin
    $dumpfile("wave.vcd");
    $dumpvars(0, testbench);
    WE = 1;
    #20
    WE = 0;
    addr = 0;
    #21
    WE = 1;
    addr = 30; // 往30地址及以后写入数据

    #20
    // 读取刚刚写的数据
    WE = 0;
    addr = 30;


    #5000 $finish;
end

endmodule  //TOP

MEM/user/sim/wave.vcd
$date
	Wed Nov 22 15:21:18 2023
$end
$version
	Icarus Verilog
$end
$timescale
	1s
$end
$scope module testbench $end
$var wire 32 ! dataout [31:0] $end
$var parameter 32 " ADDR_WIDTH $end
$var parameter 32 # DATA_WIDTH $end
$var parameter 32 $ MAIN_FRE $end
$var parameter 32 % n $end
$var reg 1 & WE $end
$var reg 32 ' addr [31:0] $end
$var reg 32 ( data [31:0] $end
$var reg 1 ) sys_clk $end
$var reg 1 * sys_rst $end
$scope module u_MEM $end
$var wire 32 + Address [31:0] $end
$var wire 1 & WE $end
$var wire 1 ) clk $end
$var wire 32 , data [31:0] $end
$var parameter 32 - n $end
$var reg 32 . dataout [31:0] $end
$upscope $end
$upscope $end
$enddefinitions $end
$comment Show the parameter values. $end
$dumpall
b100000 -
b100000 %
b111110100 $
b100000 #
b100000 "
$end
#0
$dumpvars
bx .
b0 ,
b0 +
1*
0)
b0 (
b0 '
1&
bx !
$end
#1
1)
#2
0)
0*
#3
b1 (
b1 ,
b100 '
b100 +
1)
#4
0)
#5
b1000 '
b1000 +
b10 (
b10 ,
1)
#6
0)
#7
b11 (
b11 ,
b1100 '
b1100 +
1)
#8
0)
#9
b10000 '
b10000 +
b100 (
b100 ,
1)
#10
0)
#11
b101 (
b101 ,
b10100 '
b10100 +
1)
#12
0)
#13
b11000 '
b11000 +
b110 (
b110 ,
1)
#14
0)
#15
b111 (
b111 ,
b11100 '
b11100 +
1)
#16
0)
#17
b100000 '
b100000 +
b1000 (
b1000 ,
1)
#18
0)
#19
b1001 (
b1001 ,
b100100 '
b100100 +
1)
#20
b0 !
b0 .
0)
b0 '
b0 +
0&
#21
b1 !
b1 .
b100 '
b100 +
b1010 (
b1010 ,
1)
#22
0)
#23
b10 !
b10 .
b1011 (
b1011 ,
b1000 '
b1000 +
1)
#24
0)
#25
b11 !
b11 .
b1100 '
b1100 +
b1100 (
b1100 ,
1)
#26
0)
#27
b100 !
b100 .
b1101 (
b1101 ,
b10000 '
b10000 +
1)
#28
0)
#29
b101 !
b101 .
b10100 '
b10100 +
b1110 (
b1110 ,
1)
#30
0)
#31
b110 !
b110 .
b1111 (
b1111 ,
b11000 '
b11000 +
1)
#32
0)
#33
b111 !
b111 .
b11100 '
b11100 +
b10000 (
b10000 ,
1)
#34
0)
#35
b1000 !
b1000 .
b10001 (
b10001 ,
b100000 '
b100000 +
1)
#36
0)
#37
bx !
bx .
b100100 '
b100100 +
b10010 (
b10010 ,
1)
#38
0)
#39
b10011 (
b10011 ,
b101000 '
b101000 +
1)
#40
0)
#41
bx0000000000000000 !
bx0000000000000000 .
b10100 (
b10100 ,
1)
b100010 '
b100010 +
1&
#42
0)
#43
bx !
bx .
b10101 (
b10101 ,
b100110 '
b100110 +
1)
#44
0)
#45
b101010 '
b101010 +
b10110 (
b10110 ,
1)
#46
0)
#47
b10111 (
b10111 ,
b101110 '
b101110 +
1)
#48
0)
#49
b110010 '
b110010 +
b11000 (
b11000 ,
1)
#50
0)
#51
b11001 (
b11001 ,
b110110 '
b110110 +
1)
#52
0)
#53
b111010 '
b111010 +
b11010 (
b11010 ,
1)
#54
0)
#55
b11011 (
b11011 ,
b111110 '
b111110 +
1)
#56
0)
#57
b1000010 '
b1000010 +
b11100 (
b11100 ,
1)
#58
0)
#59
b11101 (
b11101 ,
b1000110 '
b1000110 +
1)
#60
0)
#61
b10100 !
b10100 .
b11110 (
b11110 ,
1)
b100010 '
b100010 +
0&
#62
0)
#63
b10101 !
b10101 .
b11111 (
b11111 ,
b100110 '
b100110 +
1)
#64
0)
#65
b10110 !
b10110 .
b101010 '
b101010 +
b100000 (
b100000 ,
1)
#66
0)
#67
b10111 !
b10111 .
b100001 (
b100001 ,
b101110 '
b101110 +
1)
#68
0)
#69
b11000 !
b11000 .
b110010 '
b110010 +
b100010 (
b100010 ,
1)
#70
0)
#71
b11001 !
b11001 .
b100011 (
b100011 ,
b110110 '
b110110 +
1)
#72
0)
#73
b11010 !
b11010 .
b111010 '
b111010 +
b100100 (
b100100 ,
1)
#74
0)
#75
b11011 !
b11011 .
b100101 (
b100101 ,
b111110 '
b111110 +
1)
#76
0)
#77
b11100 !
b11100 .
b1000010 '
b1000010 +
b100110 (
b100110 ,
1)
#78
0)
#79
b11101 !
b11101 .
b100111 (
b100111 ,
b1000110 '
b1000110 +
1)
#80
0)
#81
bx !
bx .
b1001010 '
b1001010 +
b101000 (
b101000 ,
1)
#82
0)
#83
b101001 (
b101001 ,
b1001110 '
b1001110 +
1)
#84
0)
#85
b1010010 '
b1010010 +
b101010 (
b101010 ,
1)
#86
0)
#87
b101011 (
b101011 ,
b1010110 '
b1010110 +
1)
#88
0)
#89
b1011010 '
b1011010 +
b101100 (
b101100 ,
1)
#90
0)
#91
b101101 (
b101101 ,
b1011110 '
b1011110 +
1)
#92
0)
#93
b1100010 '
b1100010 +
b101110 (
b101110 ,
1)
#94
0)
#95
b101111 (
b101111 ,
b1100110 '
b1100110 +
1)
#96
0)
#97
b1101010 '
b1101010 +
b110000 (
b110000 ,
1)
#98
0)
#99
b110001 (
b110001 ,
b1101110 '
b1101110 +
1)
#100
0)
#101
b1110010 '
b1110010 +
b110010 (
b110010 ,
1)
#102
0)
#103
b110011 (
b110011 ,
b1110110 '
b1110110 +
1)
#104
0)
#105
b1111010 '
b1111010 +
b110100 (
b110100 ,
1)
#106
0)
#107
b110101 (
b110101 ,
b1111110 '
b1111110 +
1)
#108
0)
#109
b10000010 '
b10000010 +
b110110 (
b110110 ,
1)
#110
0)
#111
b110111 (
b110111 ,
b10000110 '
b10000110 +
1)
#112
0)
#113
b10001010 '
b10001010 +
b111000 (
b111000 ,
1)
#114
0)
#115
b111001 (
b111001 ,
b10001110 '
b10001110 +
1)
#116
0)
#117
b10010010 '
b10010010 +
b111010 (
b111010 ,
1)
#118
0)
#119
b111011 (
b111011 ,
b10010110 '
b10010110 +
1)
#120
0)
#121
b10011010 '
b10011010 +
b111100 (
b111100 ,
1)
#122
0)
#123
b111101 (
b111101 ,
b10011110 '
b10011110 +
1)
#124
0)
#125
b10100010 '
b10100010 +
b111110 (
b111110 ,
1)
#126
0)
#127
b111111 (
b111111 ,
b10100110 '
b10100110 +
1)
#128
0)
#129
b10101010 '
b10101010 +
b1000000 (
b1000000 ,
1)
#130
0)
#131
b1000001 (
b1000001 ,
b10101110 '
b10101110 +
1)
#132
0)
#133
b10110010 '
b10110010 +
b1000010 (
b1000010 ,
1)
#134
0)
#135
b1000011 (
b1000011 ,
b10110110 '
b10110110 +
1)
#136
0)
#137
b10111010 '
b10111010 +
b1000100 (
b1000100 ,
1)
#138
0)
#139
b1000101 (
b1000101 ,
b10111110 '
b10111110 +
1)
#140
0)
#141
b11000010 '
b11000010 +
b1000110 (
b1000110 ,
1)
#142
0)
#143
b1000111 (
b1000111 ,
b11000110 '
b11000110 +
1)
#144
0)
#145
b11001010 '
b11001010 +
b1001000 (
b1001000 ,
1)
#146
0)
#147
b1001001 (
b1001001 ,
b11001110 '
b11001110 +
1)
#148
0)
#149
b11010010 '
b11010010 +
b1001010 (
b1001010 ,
1)
#150
0)
#151
b1001011 (
b1001011 ,
b11010110 '
b11010110 +
1)
#152
0)
#153
b11011010 '
b11011010 +
b1001100 (
b1001100 ,
1)
#154
0)
#155
b1001101 (
b1001101 ,
b11011110 '
b11011110 +
1)
#156
0)
#157
b11100010 '
b11100010 +
b1001110 (
b1001110 ,
1)
#158
0)
#159
b1001111 (
b1001111 ,
b11100110 '
b11100110 +
1)
#160
0)
#161
b11101010 '
b11101010 +
b1010000 (
b1010000 ,
1)
#162
0)
#163
b1010001 (
b1010001 ,
b11101110 '
b11101110 +
1)
#164
0)
#165
b11110010 '
b11110010 +
b1010010 (
b1010010 ,
1)
#166
0)
#167
b1010011 (
b1010011 ,
b11110110 '
b11110110 +
1)
#168
0)
#169
b11111010 '
b11111010 +
b1010100 (
b1010100 ,
1)
#170
0)
#171
b1010101 (
b1010101 ,
b11111110 '
b11111110 +
1)
#172
0)
#173
b100000010 '
b100000010 +
b1010110 (
b1010110 ,
1)
#174
0)
#175
b1010111 (
b1010111 ,
b100000110 '
b100000110 +
1)
#176
0)
#177
b100001010 '
b100001010 +
b1011000 (
b1011000 ,
1)
#178
0)
#179
b1011001 (
b1011001 ,
b100001110 '
b100001110 +
1)
#180
0)
#181
b100010010 '
b100010010 +
b1011010 (
b1011010 ,
1)
#182
0)
#183
b1011011 (
b1011011 ,
b100010110 '
b100010110 +
1)
#184
0)
#185
b100011010 '
b100011010 +
b1011100 (
b1011100 ,
1)
#186
0)
#187
b1011101 (
b1011101 ,
b100011110 '
b100011110 +
1)
#188
0)
#189
b100100010 '
b100100010 +
b1011110 (
b1011110 ,
1)
#190
0)
#191
b1011111 (
b1011111 ,
b100100110 '
b100100110 +
1)
#192
0)
#193
b100101010 '
b100101010 +
b1100000 (
b1100000 ,
1)
#194
0)
#195
b1100001 (
b1100001 ,
b100101110 '
b100101110 +
1)
#196
0)
#197
b100110010 '
b100110010 +
b1100010 (
b1100010 ,
1)
#198
0)
#199
b1100011 (
b1100011 ,
b100110110 '
b100110110 +
1)
#200
0)
#201
b100111010 '
b100111010 +
b1100100 (
b1100100 ,
1)
#202
0)
#203
b1100101 (
b1100101 ,
b100111110 '
b100111110 +
1)
#204
0)
#205
b101000010 '
b101000010 +
b1100110 (
b1100110 ,
1)
#206
0)
#207
b1100111 (
b1100111 ,
b101000110 '
b101000110 +
1)
#208
0)
#209
b101001010 '
b101001010 +
b1101000 (
b1101000 ,
1)
#210
0)
#211
b1101001 (
b1101001 ,
b101001110 '
b101001110 +
1)
#212
0)
#213
b101010010 '
b101010010 +
b1101010 (
b1101010 ,
1)
#214
0)
#215
b1101011 (
b1101011 ,
b101010110 '
b101010110 +
1)
#216
0)
#217
b101011010 '
b101011010 +
b1101100 (
b1101100 ,
1)
#218
0)
#219
b1101101 (
b1101101 ,
b101011110 '
b101011110 +
1)
#220
0)
#221
b101100010 '
b101100010 +
b1101110 (
b1101110 ,
1)
#222
0)
#223
b1101111 (
b1101111 ,
b101100110 '
b101100110 +
1)
#224
0)
#225
b101101010 '
b101101010 +
b1110000 (
b1110000 ,
1)
#226
0)
#227
b1110001 (
b1110001 ,
b101101110 '
b101101110 +
1)
#228
0)
#229
b101110010 '
b101110010 +
b1110010 (
b1110010 ,
1)
#230
0)
#231
b1110011 (
b1110011 ,
b101110110 '
b101110110 +
1)
#232
0)
#233
b101111010 '
b101111010 +
b1110100 (
b1110100 ,
1)
#234
0)
#235
b1110101 (
b1110101 ,
b101111110 '
b101111110 +
1)
#236
0)
#237
b110000010 '
b110000010 +
b1110110 (
b1110110 ,
1)
#238
0)
#239
b1110111 (
b1110111 ,
b110000110 '
b110000110 +
1)
#240
0)
#241
b110001010 '
b110001010 +
b1111000 (
b1111000 ,
1)
#242
0)
#243
b1111001 (
b1111001 ,
b110001110 '
b110001110 +
1)
#244
0)
#245
b110010010 '
b110010010 +
b1111010 (
b1111010 ,
1)
#246
0)
#247
b1111011 (
b1111011 ,
b110010110 '
b110010110 +
1)
#248
0)
#249
b110011010 '
b110011010 +
b1111100 (
b1111100 ,
1)
#250
0)
#251
b1111101 (
b1111101 ,
b110011110 '
b110011110 +
1)
#252
0)
#253
b110100010 '
b110100010 +
b1111110 (
b1111110 ,
1)
#254
0)
#255
b1111111 (
b1111111 ,
b110100110 '
b110100110 +
1)
#256
0)
#257
b110101010 '
b110101010 +
b10000000 (
b10000000 ,
1)
#258
0)
#259
b10000001 (
b10000001 ,
b110101110 '
b110101110 +
1)
#260
0)
#261
b110110010 '
b110110010 +
b10000010 (
b10000010 ,
1)
#262
0)
#263
b10000011 (
b10000011 ,
b110110110 '
b110110110 +
1)
#264
0)
#265
b110111010 '
b110111010 +
b10000100 (
b10000100 ,
1)
#266
0)
#267
b10000101 (
b10000101 ,
b110111110 '
b110111110 +
1)
#268
0)
#269
b111000010 '
b111000010 +
b10000110 (
b10000110 ,
1)
#270
0)
#271
b10000111 (
b10000111 ,
b111000110 '
b111000110 +
1)
#272
0)
#273
b111001010 '
b111001010 +
b10001000 (
b10001000 ,
1)
#274
0)
#275
b10001001 (
b10001001 ,
b111001110 '
b111001110 +
1)
#276
0)
#277
b111010010 '
b111010010 +
b10001010 (
b10001010 ,
1)
#278
0)
#279
b10001011 (
b10001011 ,
b111010110 '
b111010110 +
1)
#280
0)
#281
b111011010 '
b111011010 +
b10001100 (
b10001100 ,
1)
#282
0)
#283
b10001101 (
b10001101 ,
b111011110 '
b111011110 +
1)
#284
0)
#285
b111100010 '
b111100010 +
b10001110 (
b10001110 ,
1)
#286
0)
#287
b10001111 (
b10001111 ,
b111100110 '
b111100110 +
1)
#288
0)
#289
b111101010 '
b111101010 +
b10010000 (
b10010000 ,
1)
#290
0)
#291
b10010001 (
b10010001 ,
b111101110 '
b111101110 +
1)
#292
0)
#293
b111110010 '
b111110010 +
b10010010 (
b10010010 ,
1)
#294
0)
#295
b10010011 (
b10010011 ,
b111110110 '
b111110110 +
1)
#296
0)
#297
b111111010 '
b111111010 +
b10010100 (
b10010100 ,
1)
#298
0)
#299
b10010101 (
b10010101 ,
b111111110 '
b111111110 +
1)
#300
0)
#301
b1000000010 '
b1000000010 +
b10010110 (
b10010110 ,
1)
#302
0)
#303
b10010111 (
b10010111 ,
b1000000110 '
b1000000110 +
1)
#304
0)
#305
b1000001010 '
b1000001010 +
b10011000 (
b10011000 ,
1)
#306
0)
#307
b10011001 (
b10011001 ,
b1000001110 '
b1000001110 +
1)
#308
0)
#309
b1000010010 '
b1000010010 +
b10011010 (
b10011010 ,
1)
#310
0)
#311
b10011011 (
b10011011 ,
b1000010110 '
b1000010110 +
1)
#312
0)
#313
b1000011010 '
b1000011010 +
b10011100 (
b10011100 ,
1)
#314
0)
#315
b10011101 (
b10011101 ,
b1000011110 '
b1000011110 +
1)
#316
0)
#317
b1000100010 '
b1000100010 +
b10011110 (
b10011110 ,
1)
#318
0)
#319
b10011111 (
b10011111 ,
b1000100110 '
b1000100110 +
1)
#320
0)
#321
b1000101010 '
b1000101010 +
b10100000 (
b10100000 ,
1)
#322
0)
#323
b10100001 (
b10100001 ,
b1000101110 '
b1000101110 +
1)
#324
0)
#325
b1000110010 '
b1000110010 +
b10100010 (
b10100010 ,
1)
#326
0)
#327
b10100011 (
b10100011 ,
b1000110110 '
b1000110110 +
1)
#328
0)
#329
b1000111010 '
b1000111010 +
b10100100 (
b10100100 ,
1)
#330
0)
#331
b10100101 (
b10100101 ,
b1000111110 '
b1000111110 +
1)
#332
0)
#333
b1001000010 '
b1001000010 +
b10100110 (
b10100110 ,
1)
#334
0)
#335
b10100111 (
b10100111 ,
b1001000110 '
b1001000110 +
1)
#336
0)
#337
b1001001010 '
b1001001010 +
b10101000 (
b10101000 ,
1)
#338
0)
#339
b10101001 (
b10101001 ,
b1001001110 '
b1001001110 +
1)
#340
0)
#341
b1001010010 '
b1001010010 +
b10101010 (
b10101010 ,
1)
#342
0)
#343
b10101011 (
b10101011 ,
b1001010110 '
b1001010110 +
1)
#344
0)
#345
b1001011010 '
b1001011010 +
b10101100 (
b10101100 ,
1)
#346
0)
#347
b10101101 (
b10101101 ,
b1001011110 '
b1001011110 +
1)
#348
0)
#349
b1001100010 '
b1001100010 +
b10101110 (
b10101110 ,
1)
#350
0)
#351
b10101111 (
b10101111 ,
b1001100110 '
b1001100110 +
1)
#352
0)
#353
b1001101010 '
b1001101010 +
b10110000 (
b10110000 ,
1)
#354
0)
#355
b10110001 (
b10110001 ,
b1001101110 '
b1001101110 +
1)
#356
0)
#357
b1001110010 '
b1001110010 +
b10110010 (
b10110010 ,
1)
#358
0)
#359
b10110011 (
b10110011 ,
b1001110110 '
b1001110110 +
1)
#360
0)
#361
b1001111010 '
b1001111010 +
b10110100 (
b10110100 ,
1)
#362
0)
#363
b10110101 (
b10110101 ,
b1001111110 '
b1001111110 +
1)
#364
0)
#365
b1010000010 '
b1010000010 +
b10110110 (
b10110110 ,
1)
#366
0)
#367
b10110111 (
b10110111 ,
b1010000110 '
b1010000110 +
1)
#368
0)
#369
b1010001010 '
b1010001010 +
b10111000 (
b10111000 ,
1)
#370
0)
#371
b10111001 (
b10111001 ,
b1010001110 '
b1010001110 +
1)
#372
0)
#373
b1010010010 '
b1010010010 +
b10111010 (
b10111010 ,
1)
#374
0)
#375
b10111011 (
b10111011 ,
b1010010110 '
b1010010110 +
1)
#376
0)
#377
b1010011010 '
b1010011010 +
b10111100 (
b10111100 ,
1)
#378
0)
#379
b10111101 (
b10111101 ,
b1010011110 '
b1010011110 +
1)
#380
0)
#381
b1010100010 '
b1010100010 +
b10111110 (
b10111110 ,
1)
#382
0)
#383
b10111111 (
b10111111 ,
b1010100110 '
b1010100110 +
1)
#384
0)
#385
b1010101010 '
b1010101010 +
b11000000 (
b11000000 ,
1)
#386
0)
#387
b11000001 (
b11000001 ,
b1010101110 '
b1010101110 +
1)
#388
0)
#389
b1010110010 '
b1010110010 +
b11000010 (
b11000010 ,
1)
#390
0)
#391
b11000011 (
b11000011 ,
b1010110110 '
b1010110110 +
1)
#392
0)
#393
b1010111010 '
b1010111010 +
b11000100 (
b11000100 ,
1)
#394
0)
#395
b11000101 (
b11000101 ,
b1010111110 '
b1010111110 +
1)
#396
0)
#397
b1011000010 '
b1011000010 +
b11000110 (
b11000110 ,
1)
#398
0)
#399
b11000111 (
b11000111 ,
b1011000110 '
b1011000110 +
1)
#400
0)
#401
b1011001010 '
b1011001010 +
b11001000 (
b11001000 ,
1)
#402
0)
#403
b11001001 (
b11001001 ,
b1011001110 '
b1011001110 +
1)
#404
0)
#405
b1011010010 '
b1011010010 +
b11001010 (
b11001010 ,
1)
#406
0)
#407
b11001011 (
b11001011 ,
b1011010110 '
b1011010110 +
1)
#408
0)
#409
b1011011010 '
b1011011010 +
b11001100 (
b11001100 ,
1)
#410
0)
#411
b11001101 (
b11001101 ,
b1011011110 '
b1011011110 +
1)
#412
0)
#413
b1011100010 '
b1011100010 +
b11001110 (
b11001110 ,
1)
#414
0)
#415
b11001111 (
b11001111 ,
b1011100110 '
b1011100110 +
1)
#416
0)
#417
b1011101010 '
b1011101010 +
b11010000 (
b11010000 ,
1)
#418
0)
#419
b11010001 (
b11010001 ,
b1011101110 '
b1011101110 +
1)
#420
0)
#421
b1011110010 '
b1011110010 +
b11010010 (
b11010010 ,
1)
#422
0)
#423
b11010011 (
b11010011 ,
b1011110110 '
b1011110110 +
1)
#424
0)
#425
b1011111010 '
b1011111010 +
b11010100 (
b11010100 ,
1)
#426
0)
#427
b11010101 (
b11010101 ,
b1011111110 '
b1011111110 +
1)
#428
0)
#429
b1100000010 '
b1100000010 +
b11010110 (
b11010110 ,
1)
#430
0)
#431
b11010111 (
b11010111 ,
b1100000110 '
b1100000110 +
1)
#432
0)
#433
b1100001010 '
b1100001010 +
b11011000 (
b11011000 ,
1)
#434
0)
#435
b11011001 (
b11011001 ,
b1100001110 '
b1100001110 +
1)
#436
0)
#437
b1100010010 '
b1100010010 +
b11011010 (
b11011010 ,
1)
#438
0)
#439
b11011011 (
b11011011 ,
b1100010110 '
b1100010110 +
1)
#440
0)
#441
b1100011010 '
b1100011010 +
b11011100 (
b11011100 ,
1)
#442
0)
#443
b11011101 (
b11011101 ,
b1100011110 '
b1100011110 +
1)
#444
0)
#445
b1100100010 '
b1100100010 +
b11011110 (
b11011110 ,
1)
#446
0)
#447
b11011111 (
b11011111 ,
b1100100110 '
b1100100110 +
1)
#448
0)
#449
b1100101010 '
b1100101010 +
b11100000 (
b11100000 ,
1)
#450
0)
#451
b11100001 (
b11100001 ,
b1100101110 '
b1100101110 +
1)
#452
0)
#453
b1100110010 '
b1100110010 +
b11100010 (
b11100010 ,
1)
#454
0)
#455
b11100011 (
b11100011 ,
b1100110110 '
b1100110110 +
1)
#456
0)
#457
b1100111010 '
b1100111010 +
b11100100 (
b11100100 ,
1)
#458
0)
#459
b11100101 (
b11100101 ,
b1100111110 '
b1100111110 +
1)
#460
0)
#461
b1101000010 '
b1101000010 +
b11100110 (
b11100110 ,
1)
#462
0)
#463
b11100111 (
b11100111 ,
b1101000110 '
b1101000110 +
1)
#464
0)
#465
b1101001010 '
b1101001010 +
b11101000 (
b11101000 ,
1)
#466
0)
#467
b11101001 (
b11101001 ,
b1101001110 '
b1101001110 +
1)
#468
0)
#469
b1101010010 '
b1101010010 +
b11101010 (
b11101010 ,
1)
#470
0)
#471
b11101011 (
b11101011 ,
b1101010110 '
b1101010110 +
1)
#472
0)
#473
b1101011010 '
b1101011010 +
b11101100 (
b11101100 ,
1)
#474
0)
#475
b11101101 (
b11101101 ,
b1101011110 '
b1101011110 +
1)
#476
0)
#477
b1101100010 '
b1101100010 +
b11101110 (
b11101110 ,
1)
#478
0)
#479
b11101111 (
b11101111 ,
b1101100110 '
b1101100110 +
1)
#480
0)
#481
b1101101010 '
b1101101010 +
b11110000 (
b11110000 ,
1)
#482
0)
#483
b11110001 (
b11110001 ,
b1101101110 '
b1101101110 +
1)
#484
0)
#485
b1101110010 '
b1101110010 +
b11110010 (
b11110010 ,
1)
#486
0)
#487
b11110011 (
b11110011 ,
b1101110110 '
b1101110110 +
1)
#488
0)
#489
b1101111010 '
b1101111010 +
b11110100 (
b11110100 ,
1)
#490
0)
#491
b11110101 (
b11110101 ,
b1101111110 '
b1101111110 +
1)
#492
0)
#493
b1110000010 '
b1110000010 +
b11110110 (
b11110110 ,
1)
#494
0)
#495
b11110111 (
b11110111 ,
b1110000110 '
b1110000110 +
1)
#496
0)
#497
b1110001010 '
b1110001010 +
b11111000 (
b11111000 ,
1)
#498
0)
#499
b11111001 (
b11111001 ,
b1110001110 '
b1110001110 +
1)
#500
0)
#501
b1110010010 '
b1110010010 +
b11111010 (
b11111010 ,
1)
#502
0)
#503
b11111011 (
b11111011 ,
b1110010110 '
b1110010110 +
1)
#504
0)
#505
b1110011010 '
b1110011010 +
b11111100 (
b11111100 ,
1)
#506
0)
#507
b11111101 (
b11111101 ,
b1110011110 '
b1110011110 +
1)
#508
0)
#509
b1110100010 '
b1110100010 +
b11111110 (
b11111110 ,
1)
#510
0)
#511
b11111111 (
b11111111 ,
b1110100110 '
b1110100110 +
1)
#512
0)
#513
b1110101010 '
b1110101010 +
b100000000 (
b100000000 ,
1)
#514
0)
#515
b100000001 (
b100000001 ,
b1110101110 '
b1110101110 +
1)
#516
0)
#517
b1110110010 '
b1110110010 +
b100000010 (
b100000010 ,
1)
#518
0)
#519
b100000011 (
b100000011 ,
b1110110110 '
b1110110110 +
1)
#520
0)
#521
b1110111010 '
b1110111010 +
b100000100 (
b100000100 ,
1)
#522
0)
#523
b100000101 (
b100000101 ,
b1110111110 '
b1110111110 +
1)
#524
0)
#525
b1111000010 '
b1111000010 +
b100000110 (
b100000110 ,
1)
#526
0)
#527
b100000111 (
b100000111 ,
b1111000110 '
b1111000110 +
1)
#528
0)
#529
b1111001010 '
b1111001010 +
b100001000 (
b100001000 ,
1)
#530
0)
#531
b100001001 (
b100001001 ,
b1111001110 '
b1111001110 +
1)
#532
0)
#533
b1111010010 '
b1111010010 +
b100001010 (
b100001010 ,
1)
#534
0)
#535
b100001011 (
b100001011 ,
b1111010110 '
b1111010110 +
1)
#536
0)
#537
b1111011010 '
b1111011010 +
b100001100 (
b100001100 ,
1)
#538
0)
#539
b100001101 (
b100001101 ,
b1111011110 '
b1111011110 +
1)
#540
0)
#541
b1111100010 '
b1111100010 +
b100001110 (
b100001110 ,
1)
#542
0)
#543
b100001111 (
b100001111 ,
b1111100110 '
b1111100110 +
1)
#544
0)
#545
b1111101010 '
b1111101010 +
b100010000 (
b100010000 ,
1)
#546
0)
#547
b100010001 (
b100010001 ,
b1111101110 '
b1111101110 +
1)
#548
0)
#549
b1111110010 '
b1111110010 +
b100010010 (
b100010010 ,
1)
#550
0)
#551
b100010011 (
b100010011 ,
b1111110110 '
b1111110110 +
1)
#552
0)
#553
b1111111010 '
b1111111010 +
b100010100 (
b100010100 ,
1)
#554
0)
#555
b100010101 (
b100010101 ,
b1111111110 '
b1111111110 +
1)
#556
0)
#557
b10000000010 '
b10000000010 +
b100010110 (
b100010110 ,
1)
#558
0)
#559
b100010111 (
b100010111 ,
b10000000110 '
b10000000110 +
1)
#560
0)
#561
b10000001010 '
b10000001010 +
b100011000 (
b100011000 ,
1)
#562
0)
#563
b100011001 (
b100011001 ,
b10000001110 '
b10000001110 +
1)
#564
0)
#565
b10000010010 '
b10000010010 +
b100011010 (
b100011010 ,
1)
#566
0)
#567
b100011011 (
b100011011 ,
b10000010110 '
b10000010110 +
1)
#568
0)
#569
b10000011010 '
b10000011010 +
b100011100 (
b100011100 ,
1)
#570
0)
#571
b100011101 (
b100011101 ,
b10000011110 '
b10000011110 +
1)
#572
0)
#573
b10000100010 '
b10000100010 +
b100011110 (
b100011110 ,
1)
#574
0)
#575
b100011111 (
b100011111 ,
b10000100110 '
b10000100110 +
1)
#576
0)
#577
b10000101010 '
b10000101010 +
b100100000 (
b100100000 ,
1)
#578
0)
#579
b100100001 (
b100100001 ,
b10000101110 '
b10000101110 +
1)
#580
0)
#581
b10000110010 '
b10000110010 +
b100100010 (
b100100010 ,
1)
#582
0)
#583
b100100011 (
b100100011 ,
b10000110110 '
b10000110110 +
1)
#584
0)
#585
b10000111010 '
b10000111010 +
b100100100 (
b100100100 ,
1)
#586
0)
#587
b100100101 (
b100100101 ,
b10000111110 '
b10000111110 +
1)
#588
0)
#589
b10001000010 '
b10001000010 +
b100100110 (
b100100110 ,
1)
#590
0)
#591
b100100111 (
b100100111 ,
b10001000110 '
b10001000110 +
1)
#592
0)
#593
b10001001010 '
b10001001010 +
b100101000 (
b100101000 ,
1)
#594
0)
#595
b100101001 (
b100101001 ,
b10001001110 '
b10001001110 +
1)
#596
0)
#597
b10001010010 '
b10001010010 +
b100101010 (
b100101010 ,
1)
#598
0)
#599
b100101011 (
b100101011 ,
b10001010110 '
b10001010110 +
1)
#600
0)
#601
b10001011010 '
b10001011010 +
b100101100 (
b100101100 ,
1)
#602
0)
#603
b100101101 (
b100101101 ,
b10001011110 '
b10001011110 +
1)
#604
0)
#605
b10001100010 '
b10001100010 +
b100101110 (
b100101110 ,
1)
#606
0)
#607
b100101111 (
b100101111 ,
b10001100110 '
b10001100110 +
1)
#608
0)
#609
b10001101010 '
b10001101010 +
b100110000 (
b100110000 ,
1)
#610
0)
#611
b100110001 (
b100110001 ,
b10001101110 '
b10001101110 +
1)
#612
0)
#613
b10001110010 '
b10001110010 +
b100110010 (
b100110010 ,
1)
#614
0)
#615
b100110011 (
b100110011 ,
b10001110110 '
b10001110110 +
1)
#616
0)
#617
b10001111010 '
b10001111010 +
b100110100 (
b100110100 ,
1)
#618
0)
#619
b100110101 (
b100110101 ,
b10001111110 '
b10001111110 +
1)
#620
0)
#621
b10010000010 '
b10010000010 +
b100110110 (
b100110110 ,
1)
#622
0)
#623
b100110111 (
b100110111 ,
b10010000110 '
b10010000110 +
1)
#624
0)
#625
b10010001010 '
b10010001010 +
b100111000 (
b100111000 ,
1)
#626
0)
