MEM/user/src/MEM.v
// module MEM (Address, VE, dataout, clk)
// 定义一个名为MEM的模块，该模块模拟了一个内存模块
module MEM (Address, WE, data, dataout, clk);

// 定义一个参数n，表示数据总线的宽度
parameter n = 32;

// 定义两个32位宽的输入线，分别是地址和数据
input wire[n-1:0] Address, data;

// 定义两个输入线，分别是写入使能信号和时钟信号
input wire WE, clk;

// 定义一个32位宽的输出数据总线
output reg[n-1:0] dataout;

// 定义一个256个元素的内存数组，每个元素是一个8位宽的寄存器
(* ram_style = "distributed" *) reg [7:0] mem [255:0];

initial
    begin
        $readmemh("/Users/yr/code/computer-organization/computer-organization-labs/MEM/user/data/data.txt", mem);
    end

// 在时钟信号的下降沿，如果WE为1，则将输入数据写入到内存数组的指定地址
always @ (negedge clk)
    begin
        if(WE ==1)begin
            {mem[Address+3], mem[Address+2], mem[Address+1], mem[Address]} = data;
            $display("[DEBUG] write %h to memory address:%h, %h", data, Address, {mem[Address+3], mem[Address+2], mem[Address+1], mem[Address]});
        end

    end

always @ (*)
    begin
        dataout = {mem[Address+3], mem[Address+2], mem[Address+1], mem[Address]};
        //$display("[DEBUG] read %h from memory address:%h", dataout, Address);
    end
endmodule

MEM/user/sim/testbench.v
`include "/Users/yr/code/computer-organization/computer-organization-labs/MEM/user/src/MEM.v"
`timescale 1ns/1ps
module testbench();

parameter DATA_WIDTH = 32;
parameter ADDR_WIDTH = 32;
parameter MAIN_FRE   = 500; //unit MHz
reg                   sys_clk = 0;
reg                   sys_rst = 1;
reg [DATA_WIDTH-1:0]  data = 0;
reg [ADDR_WIDTH-1:0]  addr = 0;

always begin
    #100 sys_clk = ~sys_clk;
end

always begin
    #2 sys_rst = 0;
end

always @(posedge sys_clk) begin
    if (sys_rst)
        addr = 0;
    else
        addr = addr + 4;
end
always @(posedge sys_clk) begin
    if (sys_rst)
        data = 0;
    else
        data = data + 1;
end

// Instance
// outports wire
parameter n = 32;
wire [n-1:0] dataout;
reg WE;

MEM u_MEM(
	.Address 	( addr     ),
	.data    	( data     ),
	.WE      	( WE       ),
	.clk     	( sys_clk  ),
	.dataout 	( dataout  )
);



initial begin
    $dumpfile("wave.vcd");
    $dumpvars(0, testbench);

    // 内存被全部初始化为1
    // 希望把所有的内存读一遍，看看是否都是1
    WE = 0;
    // WE = 1;
    // #20
    // WE = 0;
    // addr = 0;
    // #21
    // WE = 1;
    // addr = 30; // 往30地址及以后写入数据

    // #20
    // // 读取刚刚写的数据
    // WE = 0;
    // addr = 30;
    #25200

    WE = 1;
    addr = 0;
    data = 10;
    #200
    WE = 0;
    addr = 0;


    #10000 $finish;
end

endmodule  //TOP

MEM/user/sim/wave.vcd
$date
	Tue Dec 19 23:12:57 2023
$end
$version
	Icarus Verilog
$end
$timescale
	1ps
$end
$scope module testbench $end
$var wire 32 ! dataout [31:0] $end
$var parameter 32 " ADDR_WIDTH $end
$var parameter 32 # DATA_WIDTH $end
$var parameter 32 $ MAIN_FRE $end
$var parameter 32 % n $end
$var reg 1 & WE $end
$var reg 32 ' addr [31:0] $end
$var reg 32 ( data [31:0] $end
$var reg 1 ) sys_clk $end
$var reg 1 * sys_rst $end
$scope module u_MEM $end
$var wire 32 + Address [31:0] $end
$var wire 1 & WE $end
$var wire 1 ) clk $end
$var wire 32 , data [31:0] $end
$var parameter 32 - n $end
$var reg 32 . dataout [31:0] $end
$upscope $end
$upscope $end
$enddefinitions $end
$comment Show the parameter values. $end
$dumpall
b100000 -
b100000 %
b111110100 $
b100000 #
b100000 "
$end
#0
$dumpvars
b1 .
b0 ,
b0 +
1*
0)
b0 (
b0 '
0&
b1 !
$end
#2000
0*
#100000
b100 '
b100 +
b1 (
b1 ,
1)
#200000
0)
#300000
b10 (
b10 ,
b1000 '
b1000 +
1)
#400000
0)
#500000
b1100 '
b1100 +
b11 (
b11 ,
1)
#600000
0)
#700000
b100 (
b100 ,
b10000 '
b10000 +
1)
#800000
0)
#900000
b10100 '
b10100 +
b101 (
b101 ,
1)
#1000000
0)
#1100000
b110 (
b110 ,
b11000 '
b11000 +
1)
#1200000
0)
#1300000
b11100 '
b11100 +
b111 (
b111 ,
1)
#1400000
0)
#1500000
b1000 (
b1000 ,
b100000 '
b100000 +
1)
#1600000
0)
#1700000
b100100 '
b100100 +
b1001 (
b1001 ,
1)
#1800000
0)
#1900000
b1010 (
b1010 ,
b101000 '
b101000 +
1)
#2000000
0)
#2100000
b101100 '
b101100 +
b1011 (
b1011 ,
1)
#2200000
0)
#2300000
b1100 (
b1100 ,
b110000 '
b110000 +
1)
#2400000
0)
#2500000
b110100 '
b110100 +
b1101 (
b1101 ,
1)
#2600000
0)
#2700000
b1110 (
b1110 ,
b111000 '
b111000 +
1)
#2800000
0)
#2900000
b111100 '
b111100 +
b1111 (
b1111 ,
1)
#3000000
0)
#3100000
b10000 (
b10000 ,
b1000000 '
b1000000 +
1)
#3200000
0)
#3300000
b1000100 '
b1000100 +
b10001 (
b10001 ,
1)
#3400000
0)
#3500000
b10010 (
b10010 ,
b1001000 '
b1001000 +
1)
#3600000
0)
#3700000
b1001100 '
b1001100 +
b10011 (
b10011 ,
1)
#3800000
0)
#3900000
b10100 (
b10100 ,
b1010000 '
b1010000 +
1)
#4000000
0)
#4100000
b1010100 '
b1010100 +
b10101 (
b10101 ,
1)
#4200000
0)
#4300000
b10110 (
b10110 ,
b1011000 '
b1011000 +
1)
#4400000
0)
#4500000
b1011100 '
b1011100 +
b10111 (
b10111 ,
1)
#4600000
0)
#4700000
b11000 (
b11000 ,
b1100000 '
b1100000 +
1)
#4800000
0)
#4900000
b1100100 '
b1100100 +
b11001 (
b11001 ,
1)
#5000000
0)
#5100000
b11010 (
b11010 ,
b1101000 '
b1101000 +
1)
#5200000
0)
#5300000
b1101100 '
b1101100 +
b11011 (
b11011 ,
1)
#5400000
0)
#5500000
b11100 (
b11100 ,
b1110000 '
b1110000 +
1)
#5600000
0)
#5700000
b1110100 '
b1110100 +
b11101 (
b11101 ,
1)
#5800000
0)
#5900000
b11110 (
b11110 ,
b1111000 '
b1111000 +
1)
#6000000
0)
#6100000
b1111100 '
b1111100 +
b11111 (
b11111 ,
1)
#6200000
0)
#6300000
b100000 (
b100000 ,
b10000000 '
b10000000 +
1)
#6400000
0)
#6500000
b10000100 '
b10000100 +
b100001 (
b100001 ,
1)
#6600000
0)
#6700000
b100010 (
b100010 ,
b10001000 '
b10001000 +
1)
#6800000
0)
#6900000
b10001100 '
b10001100 +
b100011 (
b100011 ,
1)
#7000000
0)
#7100000
b100100 (
b100100 ,
b10010000 '
b10010000 +
1)
#7200000
0)
#7300000
b10010100 '
b10010100 +
b100101 (
b100101 ,
1)
#7400000
0)
#7500000
b100110 (
b100110 ,
b10011000 '
b10011000 +
1)
#7600000
0)
#7700000
b10011100 '
b10011100 +
b100111 (
b100111 ,
1)
#7800000
0)
#7900000
b101000 (
b101000 ,
b10100000 '
b10100000 +
1)
#8000000
0)
#8100000
b10100100 '
b10100100 +
b101001 (
b101001 ,
1)
#8200000
0)
#8300000
b101010 (
b101010 ,
b10101000 '
b10101000 +
1)
#8400000
0)
#8500000
b10101100 '
b10101100 +
b101011 (
b101011 ,
1)
#8600000
0)
#8700000
b101100 (
b101100 ,
b10110000 '
b10110000 +
1)
#8800000
0)
#8900000
b10110100 '
b10110100 +
b101101 (
b101101 ,
1)
#9000000
0)
#9100000
b101110 (
b101110 ,
b10111000 '
b10111000 +
1)
#9200000
0)
#9300000
b10111100 '
b10111100 +
b101111 (
b101111 ,
1)
#9400000
0)
#9500000
b110000 (
b110000 ,
b11000000 '
b11000000 +
1)
#9600000
0)
#9700000
b11000100 '
b11000100 +
b110001 (
b110001 ,
1)
#9800000
0)
#9900000
b110010 (
b110010 ,
b11001000 '
b11001000 +
1)
#10000000
0)
#10100000
b11001100 '
b11001100 +
b110011 (
b110011 ,
1)
#10200000
0)
#10300000
b110100 (
b110100 ,
b11010000 '
b11010000 +
1)
#10400000
0)
#10500000
b11010100 '
b11010100 +
b110101 (
b110101 ,
1)
#10600000
0)
#10700000
b110110 (
b110110 ,
b11011000 '
b11011000 +
1)
#10800000
0)
#10900000
b11011100 '
b11011100 +
b110111 (
b110111 ,
1)
#11000000
0)
#11100000
b111000 (
b111000 ,
b11100000 '
b11100000 +
1)
#11200000
0)
#11300000
b11100100 '
b11100100 +
b111001 (
b111001 ,
1)
#11400000
0)
#11500000
b111010 (
b111010 ,
b11101000 '
b11101000 +
1)
#11600000
0)
#11700000
b11101100 '
b11101100 +
b111011 (
b111011 ,
1)
#11800000
0)
#11900000
b111100 (
b111100 ,
b11110000 '
b11110000 +
1)
#12000000
0)
#12100000
b11110100 '
b11110100 +
b111101 (
b111101 ,
1)
#12200000
0)
#12300000
b111110 (
b111110 ,
b11111000 '
b11111000 +
1)
#12400000
0)
#12500000
b11111100 '
b11111100 +
b111111 (
b111111 ,
1)
#12600000
0)
#12700000
bx !
bx .
b1000000 (
b1000000 ,
b100000000 '
b100000000 +
1)
#12800000
0)
#12900000
b100000100 '
b100000100 +
b1000001 (
b1000001 ,
1)
#13000000
0)
#13100000
b1000010 (
b1000010 ,
b100001000 '
b100001000 +
1)
#13200000
0)
#13300000
b100001100 '
b100001100 +
b1000011 (
b1000011 ,
1)
#13400000
0)
#13500000
b1000100 (
b1000100 ,
b100010000 '
b100010000 +
1)
#13600000
0)
#13700000
b100010100 '
b100010100 +
b1000101 (
b1000101 ,
1)
#13800000
0)
#13900000
b1000110 (
b1000110 ,
b100011000 '
b100011000 +
1)
#14000000
0)
#14100000
b100011100 '
b100011100 +
b1000111 (
b1000111 ,
1)
#14200000
0)
#14300000
b1001000 (
b1001000 ,
b100100000 '
b100100000 +
1)
#14400000
0)
#14500000
b100100100 '
b100100100 +
b1001001 (
b1001001 ,
1)
#14600000
0)
#14700000
b1001010 (
b1001010 ,
b100101000 '
b100101000 +
1)
#14800000
0)
#14900000
b100101100 '
b100101100 +
b1001011 (
b1001011 ,
1)
#15000000
0)
#15100000
b1001100 (
b1001100 ,
b100110000 '
b100110000 +
1)
#15200000
0)
#15300000
b100110100 '
b100110100 +
b1001101 (
b1001101 ,
1)
#15400000
0)
#15500000
b1001110 (
b1001110 ,
b100111000 '
b100111000 +
1)
#15600000
0)
#15700000
b100111100 '
b100111100 +
b1001111 (
b1001111 ,
1)
#15800000
0)
#15900000
b1010000 (
b1010000 ,
b101000000 '
b101000000 +
1)
#16000000
0)
#16100000
b101000100 '
b101000100 +
b1010001 (
b1010001 ,
1)
#16200000
0)
#16300000
b1010010 (
b1010010 ,
b101001000 '
b101001000 +
1)
#16400000
0)
#16500000
b101001100 '
b101001100 +
b1010011 (
b1010011 ,
1)
#16600000
0)
#16700000
b1010100 (
b1010100 ,
b101010000 '
b101010000 +
1)
#16800000
0)
#16900000
b101010100 '
b101010100 +
b1010101 (
b1010101 ,
1)
#17000000
0)
#17100000
b1010110 (
b1010110 ,
b101011000 '
b101011000 +
1)
#17200000
0)
#17300000
b101011100 '
b101011100 +
b1010111 (
b1010111 ,
1)
#17400000
0)
#17500000
b1011000 (
b1011000 ,
b101100000 '
b101100000 +
1)
#17600000
0)
#17700000
b101100100 '
b101100100 +
b1011001 (
b1011001 ,
1)
#17800000
0)
#17900000
b1011010 (
b1011010 ,
b101101000 '
b101101000 +
1)
#18000000
0)
#18100000
b101101100 '
b101101100 +
b1011011 (
b1011011 ,
1)
#18200000
0)
#18300000
b1011100 (
b1011100 ,
b101110000 '
b101110000 +
1)
#18400000
0)
#18500000
b101110100 '
b101110100 +
b1011101 (
b1011101 ,
1)
#18600000
0)
#18700000
b1011110 (
b1011110 ,
b101111000 '
b101111000 +
1)
#18800000
0)
#18900000
b101111100 '
b101111100 +
b1011111 (
b1011111 ,
1)
#19000000
0)
#19100000
b1100000 (
b1100000 ,
b110000000 '
b110000000 +
1)
#19200000
0)
#19300000
b110000100 '
b110000100 +
b1100001 (
b1100001 ,
1)
#19400000
0)
#19500000
b1100010 (
b1100010 ,
b110001000 '
b110001000 +
1)
#19600000
0)
#19700000
b110001100 '
b110001100 +
b1100011 (
b1100011 ,
1)
#19800000
0)
#19900000
b1100100 (
b1100100 ,
b110010000 '
b110010000 +
1)
#20000000
0)
#20100000
b110010100 '
b110010100 +
b1100101 (
b1100101 ,
1)
#20200000
0)
#20300000
b1100110 (
b1100110 ,
b110011000 '
b110011000 +
1)
#20400000
0)
#20500000
b110011100 '
b110011100 +
b1100111 (
b1100111 ,
1)
#20600000
0)
#20700000
b1101000 (
b1101000 ,
b110100000 '
b110100000 +
1)
#20800000
0)
#20900000
b110100100 '
b110100100 +
b1101001 (
b1101001 ,
1)
#21000000
0)
#21100000
b1101010 (
b1101010 ,
b110101000 '
b110101000 +
1)
#21200000
0)
#21300000
b110101100 '
b110101100 +
b1101011 (
b1101011 ,
1)
#21400000
0)
#21500000
b1101100 (
b1101100 ,
b110110000 '
b110110000 +
1)
#21600000
0)
#21700000
b110110100 '
b110110100 +
b1101101 (
b1101101 ,
1)
#21800000
0)
#21900000
b1101110 (
b1101110 ,
b110111000 '
b110111000 +
1)
#22000000
0)
#22100000
b110111100 '
b110111100 +
b1101111 (
b1101111 ,
1)
#22200000
0)
#22300000
b1110000 (
b1110000 ,
b111000000 '
b111000000 +
1)
#22400000
0)
#22500000
b111000100 '
b111000100 +
b1110001 (
b1110001 ,
1)
#22600000
0)
#22700000
b1110010 (
b1110010 ,
b111001000 '
b111001000 +
1)
#22800000
0)
#22900000
b111001100 '
b111001100 +
b1110011 (
b1110011 ,
1)
#23000000
0)
#23100000
b1110100 (
b1110100 ,
b111010000 '
b111010000 +
1)
#23200000
0)
#23300000
b111010100 '
b111010100 +
b1110101 (
b1110101 ,
1)
#23400000
0)
#23500000
b1110110 (
b1110110 ,
b111011000 '
b111011000 +
1)
#23600000
0)
#23700000
b111011100 '
b111011100 +
b1110111 (
b1110111 ,
1)
#23800000
0)
#23900000
b1111000 (
b1111000 ,
b111100000 '
b111100000 +
1)
#24000000
0)
#24100000
b111100100 '
b111100100 +
b1111001 (
b1111001 ,
1)
#24200000
0)
#24300000
b1111010 (
b1111010 ,
b111101000 '
b111101000 +
1)
#24400000
0)
#24500000
b111101100 '
b111101100 +
b1111011 (
b1111011 ,
1)
#24600000
0)
#24700000
b1111100 (
b1111100 ,
b111110000 '
b111110000 +
1)
#24800000
0)
#24900000
b111110100 '
b111110100 +
b1111101 (
b1111101 ,
1)
#25000000
0)
#25100000
b1111110 (
b1111110 ,
b111111000 '
b111111000 +
1)
#25200000
b1010 !
b1010 .
0)
b1010 (
b1010 ,
b0 '
b0 +
1&
#25300000
b1 !
b1 .
b100 '
b100 +
b1011 (
b1011 ,
1)
#25400000
b1010 !
b1010 .
0)
b0 '
b0 +
0&
#25500000
b1 !
b1 .
b1100 (
b1100 ,
b100 '
b100 +
1)
#25600000
0)
#25700000
b1000 '
b1000 +
b1101 (
b1101 ,
1)
#25800000
0)
#25900000
b1110 (
b1110 ,
b1100 '
b1100 +
1)
#26000000
0)
#26100000
b10000 '
b10000 +
b1111 (
b1111 ,
1)
#26200000
0)
#26300000
b10000 (
b10000 ,
b10100 '
b10100 +
1)
#26400000
0)
#26500000
b11000 '
b11000 +
b10001 (
b10001 ,
1)
#26600000
0)
#26700000
b10010 (
b10010 ,
b11100 '
b11100 +
1)
#26800000
0)
#26900000
b100000 '
b100000 +
b10011 (
b10011 ,
1)
#27000000
0)
#27100000
b10100 (
b10100 ,
b100100 '
b100100 +
1)
#27200000
0)
#27300000
b101000 '
b101000 +
b10101 (
b10101 ,
1)
#27400000
0)
#27500000
b10110 (
b10110 ,
b101100 '
b101100 +
1)
#27600000
0)
#27700000
b110000 '
b110000 +
b10111 (
b10111 ,
1)
#27800000
0)
#27900000
b11000 (
b11000 ,
b110100 '
b110100 +
1)
#28000000
0)
#28100000
b111000 '
b111000 +
b11001 (
b11001 ,
1)
#28200000
0)
#28300000
b11010 (
b11010 ,
b111100 '
b111100 +
1)
#28400000
0)
#28500000
b1000000 '
b1000000 +
b11011 (
b11011 ,
1)
#28600000
0)
#28700000
b11100 (
b11100 ,
b1000100 '
b1000100 +
1)
#28800000
0)
#28900000
b1001000 '
b1001000 +
b11101 (
b11101 ,
1)
#29000000
0)
#29100000
b11110 (
b11110 ,
b1001100 '
b1001100 +
1)
#29200000
0)
#29300000
b1010000 '
b1010000 +
b11111 (
b11111 ,
1)
#29400000
0)
#29500000
b100000 (
b100000 ,
b1010100 '
b1010100 +
1)
#29600000
0)
#29700000
b1011000 '
b1011000 +
b100001 (
b100001 ,
1)
#29800000
0)
#29900000
b100010 (
b100010 ,
b1011100 '
b1011100 +
1)
#30000000
0)
#30100000
b1100000 '
b1100000 +
b100011 (
b100011 ,
1)
#30200000
0)
#30300000
b100100 (
b100100 ,
b1100100 '
b1100100 +
1)
#30400000
0)
#30500000
b1101000 '
b1101000 +
b100101 (
b100101 ,
1)
#30600000
0)
#30700000
b100110 (
b100110 ,
b1101100 '
b1101100 +
1)
#30800000
0)
#30900000
b1110000 '
b1110000 +
b100111 (
b100111 ,
1)
#31000000
0)
#31100000
b101000 (
b101000 ,
b1110100 '
b1110100 +
1)
#31200000
0)
#31300000
b1111000 '
b1111000 +
b101001 (
b101001 ,
1)
#31400000
0)
#31500000
b101010 (
b101010 ,
b1111100 '
b1111100 +
1)
#31600000
0)
#31700000
b10000000 '
b10000000 +
b101011 (
b101011 ,
1)
#31800000
0)
#31900000
b101100 (
b101100 ,
b10000100 '
b10000100 +
1)
#32000000
0)
#32100000
b10001000 '
b10001000 +
b101101 (
b101101 ,
1)
#32200000
0)
#32300000
b101110 (
b101110 ,
b10001100 '
b10001100 +
1)
#32400000
0)
#32500000
b10010000 '
b10010000 +
b101111 (
b101111 ,
1)
#32600000
0)
#32700000
b110000 (
b110000 ,
b10010100 '
b10010100 +
1)
#32800000
0)
#32900000
b10011000 '
b10011000 +
b110001 (
b110001 ,
1)
#33000000
0)
#33100000
b110010 (
b110010 ,
b10011100 '
b10011100 +
1)
#33200000
0)
#33300000
b10100000 '
b10100000 +
b110011 (
b110011 ,
1)
#33400000
0)
#33500000
b110100 (
b110100 ,
b10100100 '
b10100100 +
1)
#33600000
0)
#33700000
b10101000 '
b10101000 +
b110101 (
b110101 ,
1)
#33800000
0)
#33900000
b110110 (
b110110 ,
b10101100 '
b10101100 +
1)
#34000000
0)
#34100000
b10110000 '
b10110000 +
b110111 (
b110111 ,
1)
#34200000
0)
#34300000
b111000 (
b111000 ,
b10110100 '
b10110100 +
1)
#34400000
0)
#34500000
b10111000 '
b10111000 +
b111001 (
b111001 ,
1)
#34600000
0)
#34700000
b111010 (
b111010 ,
b10111100 '
b10111100 +
1)
#34800000
0)
#34900000
b11000000 '
b11000000 +
b111011 (
b111011 ,
1)
#35000000
0)
#35100000
b111100 (
b111100 ,
b11000100 '
b11000100 +
1)
#35200000
0)
#35300000
b11001000 '
b11001000 +
b111101 (
b111101 ,
1)
